{
  "snapshot_timestamptz": "2019-08-07T19:10:23.651971+00:00",
  "snapshot_timestamptz_s": 1565205023.65197,
  "queries": {
    "5ea24c6fa36fca74368f683ce46db5e0": {
      "rownum": 1,
      "query": "create table t_slw_q as select id::int8 from generate_series(0, 10000000) _(id)",
      "calls": 1,
      "total_time": 31943.445543,
      "rows": 0,
      "shared_blks_hit": 130,
      "shared_blks_read": 44248,
      "shared_blks_dirtied": 44248,
      "shared_blks_written": 42200,
      "local_blks_hit": 0,
      "local_blks_read": 0,
      "local_blks_dirtied": 0,
      "local_blks_written": 0,
      "temp_blks_read": 17090,
      "temp_blks_written": 17090,
      "blk_read_time": 0,
      "blk_write_time": 0,
      "queryid": -837353630728469800,
      "md5": "5ea24c6fa36fca74368f683ce46db5e0"
    },
    "fc89994603784033979249977e304289": {
      "rownum": 2,
      "query": "VACUUM ANALYZE",
      "calls": 1,
      "total_time": 13620.981593,
      "rows": 0,
      "shared_blks_hit": 132886,
      "shared_blks_read": 177481,
      "shared_blks_dirtied": 91368,
      "shared_blks_written": 77456,
      "local_blks_hit": 0,
      "local_blks_read": 0,
      "local_blks_dirtied": 0,
      "local_blks_written": 0,
      "temp_blks_read": 0,
      "temp_blks_written": 0,
      "blk_read_time": 0,
      "blk_write_time": 0,
      "queryid": -4922882474069691000,
      "md5": "fc89994603784033979249977e304289"
    },
    "8af1e5f39b7de7d8eeaffad3d8acd54b": {
      "rownum": 3,
      "query": "update t_rar_q set t_dat=$1 where t_dat between $2 and $3",
      "calls": 9,
      "total_time": 9092.537002,
      "rows": 743952,
      "shared_blks_hit": 1519852,
      "shared_blks_read": 17298,
      "shared_blks_dirtied": 11929,
      "shared_blks_written": 9048,
      "local_blks_hit": 0,
      "local_blks_read": 0,
      "local_blks_dirtied": 0,
      "local_blks_written": 0,
      "temp_blks_read": 0,
      "temp_blks_written": 0,
      "blk_read_time": 0,
      "blk_write_time": 0,
      "queryid": -3222149299978340400,
      "md5": "8af1e5f39b7de7d8eeaffad3d8acd54b"
    },
    "f04600d0b0c9a2d20505d593f69c9b7f": {
      "rownum": 4,
      "query": "VACUUM (ANALYZE)",
      "calls": 1,
      "total_time": 5750.750201,
      "rows": 0,
      "shared_blks_hit": 54594,
      "shared_blks_read": 88474,
      "shared_blks_dirtied": 14810,
      "shared_blks_written": 12072,
      "local_blks_hit": 0,
      "local_blks_read": 0,
      "local_blks_dirtied": 0,
      "local_blks_written": 0,
      "temp_blks_read": 0,
      "temp_blks_written": 0,
      "blk_read_time": 0,
      "blk_write_time": 0,
      "queryid": 613725734663719400,
      "md5": "f04600d0b0c9a2d20505d593f69c9b7f"
    },
    "8729d45b34fea2d78356073d4de81396": {
      "rownum": 5,
      "query": "update t_with_bloat set i = i",
      "calls": 1,
      "total_time": 5456.597745,
      "rows": 1000000,
      "shared_blks_hit": 2013284,
      "shared_blks_read": 8851,
      "shared_blks_dirtied": 8850,
      "shared_blks_written": 4892,
      "local_blks_hit": 0,
      "local_blks_read": 0,
      "local_blks_dirtied": 0,
      "local_blks_written": 0,
      "temp_blks_read": 0,
      "temp_blks_written": 0,
      "blk_read_time": 0,
      "blk_write_time": 0,
      "queryid": 4145010178302556700,
      "md5": "8729d45b34fea2d78356073d4de81396"
    },
    "95f449a74e628c4e8d47ae2af9b2fd43": {
      "rownum": 6,
      "query": "create index r_red_fk_1_id_idx on t_red_fk_1(id)",
      "calls": 1,
      "total_time": 4152.87845,
      "rows": 0,
      "shared_blks_hit": 1167,
      "shared_blks_read": 1221,
      "shared_blks_dirtied": 0,
      "shared_blks_written": 0,
      "local_blks_hit": 0,
      "local_blks_read": 0,
      "local_blks_dirtied": 0,
      "local_blks_written": 0,
      "temp_blks_read": 2449,
      "temp_blks_written": 1273,
      "blk_read_time": 0,
      "blk_write_time": 0,
      "queryid": 3040282640922053000,
      "md5": "95f449a74e628c4e8d47ae2af9b2fd43"
    },
    "e722b82f5ebb6dbabf7e05bd0004d039": {
      "rownum": 7,
      "query": "create table t_rar_q as select id, (random() * 1000000)::int8 as t_dat from generate_series(1, 1000000) _(id)",
      "calls": 1,
      "total_time": 3246.209442,
      "rows": 0,
      "shared_blks_hit": 197,
      "shared_blks_read": 5407,
      "shared_blks_dirtied": 5425,
      "shared_blks_written": 3358,
      "local_blks_hit": 0,
      "local_blks_read": 0,
      "local_blks_dirtied": 0,
      "local_blks_written": 0,
      "temp_blks_read": 1709,
      "temp_blks_written": 1709,
      "blk_read_time": 0,
      "blk_write_time": 0,
      "queryid": 8726250694613120000,
      "md5": "e722b82f5ebb6dbabf7e05bd0004d039"
    },
    "7035f68c6b282d8119eec6722d1d3abc": {
      "rownum": 8,
      "query": "create index concurrently i_redundant_2 on t_with_redundant_index(i)",
      "calls": 1,
      "total_time": 2845.944302,
      "rows": 0,
      "shared_blks_hit": 3420,
      "shared_blks_read": 6189,
      "shared_blks_dirtied": 2,
      "shared_blks_written": 0,
      "local_blks_hit": 0,
      "local_blks_read": 0,
      "local_blks_dirtied": 0,
      "local_blks_written": 0,
      "temp_blks_read": 2449,
      "temp_blks_written": 1284,
      "blk_read_time": 0,
      "blk_write_time": 0,
      "queryid": 5045454327338548000,
      "md5": "7035f68c6b282d8119eec6722d1d3abc"
    },
    "2708cb9f644092f24be600bdcf8e0e26": {
      "rownum": 9,
      "query": "create table t_with_redundant_idx as select id, id as f1, id as f2, id as f3, id as f4 from generate_series(1, 1000000) _(id)",
      "calls": 1,
      "total_time": 2731.321487,
      "rows": 0,
      "shared_blks_hit": 158,
      "shared_blks_read": 6370,
      "shared_blks_dirtied": 6370,
      "shared_blks_written": 4902,
      "local_blks_hit": 0,
      "local_blks_read": 0,
      "local_blks_dirtied": 0,
      "local_blks_written": 0,
      "temp_blks_read": 1709,
      "temp_blks_written": 1709,
      "blk_read_time": 0,
      "blk_write_time": 0,
      "queryid": 2527906257619262000,
      "md5": "2708cb9f644092f24be600bdcf8e0e26"
    },
    "9496008daf0f193d85061c9f64bde9ab": {
      "rownum": 10,
      "query": "create table t_red_fk_2 as select id, (random() * 1000000)::int8 as r_t1_id from generate_series(1, 1000000) _(id)",
      "calls": 1,
      "total_time": 2367.155746,
      "rows": 0,
      "shared_blks_hit": 141,
      "shared_blks_read": 5408,
      "shared_blks_dirtied": 5409,
      "shared_blks_written": 3358,
      "local_blks_hit": 0,
      "local_blks_read": 0,
      "local_blks_dirtied": 0,
      "local_blks_written": 0,
      "temp_blks_read": 1709,
      "temp_blks_written": 1709,
      "blk_read_time": 0,
      "blk_write_time": 0,
      "queryid": 591824813582986000,
      "md5": "9496008daf0f193d85061c9f64bde9ab"
    },
    "85058944e069d1ab2406dcb7614028c3": {
      "rownum": 11,
      "query": "create table t_with_bloat as select i from generate_series(1, 1000000) _(i)",
      "calls": 1,
      "total_time": 2293.964251,
      "rows": 0,
      "shared_blks_hit": 132,
      "shared_blks_read": 4429,
      "shared_blks_dirtied": 4429,
      "shared_blks_written": 2377,
      "local_blks_hit": 0,
      "local_blks_read": 0,
      "local_blks_dirtied": 0,
      "local_blks_written": 0,
      "temp_blks_read": 1709,
      "temp_blks_written": 1709,
      "blk_read_time": 0,
      "blk_write_time": 0,
      "queryid": -6446764050704029000,
      "md5": "85058944e069d1ab2406dcb7614028c3"
    },
    "d16ce3233d3d18f9e990387d5892ee22": {
      "rownum": 12,
      "query": "create table public.t_with_redundant_ref_idx as select i from generate_series(1, 1000000) _(i)",
      "calls": 1,
      "total_time": 2247.598703,
      "rows": 0,
      "shared_blks_hit": 124,
      "shared_blks_read": 4425,
      "shared_blks_dirtied": 4425,
      "shared_blks_written": 2377,
      "local_blks_hit": 0,
      "local_blks_read": 0,
      "local_blks_dirtied": 0,
      "local_blks_written": 0,
      "temp_blks_read": 1709,
      "temp_blks_written": 1709,
      "blk_read_time": 0,
      "blk_write_time": 0,
      "queryid": 4227063200314075600,
      "md5": "d16ce3233d3d18f9e990387d5892ee22"
    },
    "ef0f4334b8f15b0a142c41903e836106": {
      "rownum": 13,
      "query": "create table exp_redundant.t_with_redundant_ref_idx as select i from generate_series(1, 1000000) _(i)",
      "calls": 1,
      "total_time": 2243.54485,
      "rows": 0,
      "shared_blks_hit": 126,
      "shared_blks_read": 4425,
      "shared_blks_dirtied": 4426,
      "shared_blks_written": 2377,
      "local_blks_hit": 0,
      "local_blks_read": 0,
      "local_blks_dirtied": 0,
      "local_blks_written": 0,
      "temp_blks_read": 1709,
      "temp_blks_written": 1709,
      "blk_read_time": 0,
      "blk_write_time": 0,
      "queryid": -1861943955546907400,
      "md5": "ef0f4334b8f15b0a142c41903e836106"
    },
    "8bd7f2c2ba1ee035dd61d0040f578590": {
      "rownum": 14,
      "query": "create table test_schema.t_with_invalid_index as select i from generate_series(1, 1000000) _(i)",
      "calls": 1,
      "total_time": 2197.872587,
      "rows": 0,
      "shared_blks_hit": 130,
      "shared_blks_read": 4425,
      "shared_blks_dirtied": 4432,
      "shared_blks_written": 2377,
      "local_blks_hit": 0,
      "local_blks_read": 0,
      "local_blks_dirtied": 0,
      "local_blks_written": 0,
      "temp_blks_read": 1709,
      "temp_blks_written": 1709,
      "blk_read_time": 0,
      "blk_write_time": 0,
      "queryid": 5156236148593934000,
      "md5": "8bd7f2c2ba1ee035dd61d0040f578590"
    },
    "3f094705882eaade4441c4dfbc1809b9": {
      "rownum": 15,
      "query": "create table t_with_unused_index as select i from generate_series(1, 1000000) _(i)",
      "calls": 1,
      "total_time": 2193.521678,
      "rows": 0,
      "shared_blks_hit": 126,
      "shared_blks_read": 4425,
      "shared_blks_dirtied": 4425,
      "shared_blks_written": 2377,
      "local_blks_hit": 0,
      "local_blks_read": 0,
      "local_blks_dirtied": 0,
      "local_blks_written": 0,
      "temp_blks_read": 1709,
      "temp_blks_written": 1709,
      "blk_read_time": 0,
      "blk_write_time": 0,
      "queryid": -678916242629262500,
      "md5": "3f094705882eaade4441c4dfbc1809b9"
    },
    "32f5ef2ab3cfc8ba05d96229f852c456": {
      "rownum": 16,
      "query": "create table t_with_redundant_index as select i from generate_series(1, 1000000) _(i)",
      "calls": 1,
      "total_time": 2179.202169,
      "rows": 0,
      "shared_blks_hit": 128,
      "shared_blks_read": 4425,
      "shared_blks_dirtied": 4427,
      "shared_blks_written": 2377,
      "local_blks_hit": 0,
      "local_blks_read": 0,
      "local_blks_dirtied": 0,
      "local_blks_written": 0,
      "temp_blks_read": 1709,
      "temp_blks_written": 1709,
      "blk_read_time": 0,
      "blk_write_time": 0,
      "queryid": -5095830603244401000,
      "md5": "32f5ef2ab3cfc8ba05d96229f852c456"
    },
    "7d09632ff93304084401533d8f67aa16": {
      "rownum": 17,
      "query": "create table t_red_fk_1 as select id::int8 from generate_series(0, 1000000) _(id)",
      "calls": 1,
      "total_time": 1950.948957,
      "rows": 0,
      "shared_blks_hit": 128,
      "shared_blks_read": 4429,
      "shared_blks_dirtied": 4429,
      "shared_blks_written": 2377,
      "local_blks_hit": 0,
      "local_blks_read": 0,
      "local_blks_dirtied": 0,
      "local_blks_written": 0,
      "temp_blks_read": 1709,
      "temp_blks_written": 1709,
      "blk_read_time": 0,
      "blk_write_time": 0,
      "queryid": -5601151487238124000,
      "md5": "7d09632ff93304084401533d8f67aa16"
    },
    "59e32b402631edd68f57233d02a6ff1c": {
      "rownum": 18,
      "query": "alter table t_with_redundant_idx add primary key (id)",
      "calls": 1,
      "total_time": 1856.474353,
      "rows": 0,
      "shared_blks_hit": 3227,
      "shared_blks_read": 6653,
      "shared_blks_dirtied": 4329,
      "shared_blks_written": 4290,
      "local_blks_hit": 0,
      "local_blks_read": 0,
      "local_blks_dirtied": 0,
      "local_blks_written": 0,
      "temp_blks_read": 2449,
      "temp_blks_written": 1284,
      "blk_read_time": 0,
      "blk_write_time": 0,
      "queryid": 3416651331628416000,
      "md5": "59e32b402631edd68f57233d02a6ff1c"
    },
    "41649b5376672435db270b265abd719b": {
      "rownum": 19,
      "query": "create index r_red_fk_2_fk_idx on t_red_fk_2(r_t1_id)",
      "calls": 1,
      "total_time": 1731.77653,
      "rows": 0,
      "shared_blks_hit": 1103,
      "shared_blks_read": 1824,
      "shared_blks_dirtied": 0,
      "shared_blks_written": 0,
      "local_blks_hit": 0,
      "local_blks_read": 0,
      "local_blks_dirtied": 0,
      "local_blks_written": 0,
      "temp_blks_read": 2449,
      "temp_blks_written": 1284,
      "blk_read_time": 0,
      "blk_write_time": 0,
      "queryid": -2801630118753177600,
      "md5": "41649b5376672435db270b265abd719b"
    },
    "d2b42fdb3e69ab37ae920aa6154580d5": {
      "rownum": 20,
      "query": "alter table t_red_fk_1 add primary key (id)",
      "calls": 1,
      "total_time": 1655.219281,
      "rows": 0,
      "shared_blks_hit": 3190,
      "shared_blks_read": 3957,
      "shared_blks_dirtied": 2383,
      "shared_blks_written": 2345,
      "local_blks_hit": 0,
      "local_blks_read": 0,
      "local_blks_dirtied": 0,
      "local_blks_written": 0,
      "temp_blks_read": 2449,
      "temp_blks_written": 1423,
      "blk_read_time": 0,
      "blk_write_time": 0,
      "queryid": 7202543407834562000,
      "md5": "d2b42fdb3e69ab37ae920aa6154580d5"
    },
    "10ea71b17cbe4e8574737f13d9aa74a7": {
      "rownum": 21,
      "query": "create index concurrently t_with_redundant_idx_f1_f2 on t_with_redundant_idx(f1,f2)",
      "calls": 1,
      "total_time": 1389.968646,
      "rows": 0,
      "shared_blks_hit": 3982,
      "shared_blks_read": 8621,
      "shared_blks_dirtied": 2,
      "shared_blks_written": 0,
      "local_blks_hit": 0,
      "local_blks_read": 0,
      "local_blks_dirtied": 0,
      "local_blks_written": 0,
      "temp_blks_read": 2448,
      "temp_blks_written": 1283,
      "blk_read_time": 0,
      "blk_write_time": 0,
      "queryid": -8920212056722243000,
      "md5": "10ea71b17cbe4e8574737f13d9aa74a7"
    },
    "eb413a8ade520c34aa6278929cd8b8d0": {
      "rownum": 22,
      "query": "create index concurrently i_redundant_1 on t_with_redundant_index(i)",
      "calls": 1,
      "total_time": 1291.916119,
      "rows": 0,
      "shared_blks_hit": 3297,
      "shared_blks_read": 6302,
      "shared_blks_dirtied": 1246,
      "shared_blks_written": 1212,
      "local_blks_hit": 0,
      "local_blks_read": 0,
      "local_blks_dirtied": 0,
      "local_blks_written": 0,
      "temp_blks_read": 2448,
      "temp_blks_written": 1267,
      "blk_read_time": 0,
      "blk_write_time": 0,
      "queryid": 566438153080519400,
      "md5": "eb413a8ade520c34aa6278929cd8b8d0"
    },
    "1657dd3ac6a8396cda288ccf95b3e93e": {
      "rownum": 23,
      "query": "create index concurrently t_with_redundant_idx_f3_1 on t_with_redundant_idx(f3)",
      "calls": 1,
      "total_time": 1250.280684,
      "rows": 0,
      "shared_blks_hit": 3794,
      "shared_blks_read": 8786,
      "shared_blks_dirtied": 2,
      "shared_blks_written": 1,
      "local_blks_hit": 0,
      "local_blks_read": 0,
      "local_blks_dirtied": 0,
      "local_blks_written": 0,
      "temp_blks_read": 2448,
      "temp_blks_written": 1286,
      "blk_read_time": 0,
      "blk_write_time": 0,
      "queryid": -7990293000632035000,
      "md5": "1657dd3ac6a8396cda288ccf95b3e93e"
    },
    "179dd95fcd8662bf4e071266e75a8377": {
      "rownum": 24,
      "query": "create index concurrently t_with_redundant_idx_id on t_with_redundant_idx(id)",
      "calls": 1,
      "total_time": 1240.414997,
      "rows": 0,
      "shared_blks_hit": 3388,
      "shared_blks_read": 9191,
      "shared_blks_dirtied": 2,
      "shared_blks_written": 463,
      "local_blks_hit": 0,
      "local_blks_read": 0,
      "local_blks_dirtied": 0,
      "local_blks_written": 0,
      "temp_blks_read": 2448,
      "temp_blks_written": 1283,
      "blk_read_time": 0,
      "blk_write_time": 0,
      "queryid": 5967467509848557000,
      "md5": "179dd95fcd8662bf4e071266e75a8377"
    },
    "df3e7ad51d29398d30aebde32df0d71d": {
      "rownum": 25,
      "query": "create index concurrently t_with_redundant_idx_f2 on t_with_redundant_idx(f2)",
      "calls": 1,
      "total_time": 1230.876506,
      "rows": 0,
      "shared_blks_hit": 3714,
      "shared_blks_read": 8856,
      "shared_blks_dirtied": 2,
      "shared_blks_written": 356,
      "local_blks_hit": 0,
      "local_blks_read": 0,
      "local_blks_dirtied": 0,
      "local_blks_written": 0,
      "temp_blks_read": 2448,
      "temp_blks_written": 1283,
      "blk_read_time": 0,
      "blk_write_time": 0,
      "queryid": 1902759977384827000,
      "md5": "df3e7ad51d29398d30aebde32df0d71d"
    },
    "1e7bc5cce40a35c4730e436ea664a3f9": {
      "rownum": 26,
      "query": "create index concurrently t_with_redundant_idx_f1_2 on t_with_redundant_idx(f1)",
      "calls": 1,
      "total_time": 1219.901449,
      "rows": 0,
      "shared_blks_hit": 3728,
      "shared_blks_read": 8867,
      "shared_blks_dirtied": 2,
      "shared_blks_written": 743,
      "local_blks_hit": 0,
      "local_blks_read": 0,
      "local_blks_dirtied": 0,
      "local_blks_written": 0,
      "temp_blks_read": 2449,
      "temp_blks_written": 1293,
      "blk_read_time": 0,
      "blk_write_time": 0,
      "queryid": 879148290678321700,
      "md5": "1e7bc5cce40a35c4730e436ea664a3f9"
    },
    "287d9693318affc139279ec76e414f24": {
      "rownum": 27,
      "query": "create index concurrently t_with_redundant_idx_f3_2 on t_with_redundant_idx(f3)",
      "calls": 1,
      "total_time": 1208.263211,
      "rows": 0,
      "shared_blks_hit": 3789,
      "shared_blks_read": 8781,
      "shared_blks_dirtied": 2,
      "shared_blks_written": 0,
      "local_blks_hit": 0,
      "local_blks_read": 0,
      "local_blks_dirtied": 0,
      "local_blks_written": 0,
      "temp_blks_read": 2448,
      "temp_blks_written": 1283,
      "blk_read_time": 0,
      "blk_write_time": 0,
      "queryid": 8565802378619238000,
      "md5": "287d9693318affc139279ec76e414f24"
    },
    "76531a1eb8e34ee84b9f6f32762a30e1": {
      "rownum": 28,
      "query": "create index concurrently i_unused on t_with_unused_index(i)",
      "calls": 1,
      "total_time": 1192.071934,
      "rows": 0,
      "shared_blks_hit": 3308,
      "shared_blks_read": 6331,
      "shared_blks_dirtied": 1272,
      "shared_blks_written": 1235,
      "local_blks_hit": 0,
      "local_blks_read": 0,
      "local_blks_dirtied": 0,
      "local_blks_written": 0,
      "temp_blks_read": 2448,
      "temp_blks_written": 1283,
      "blk_read_time": 0,
      "blk_write_time": 0,
      "queryid": -6612128672608002000,
      "md5": "76531a1eb8e34ee84b9f6f32762a30e1"
    },
    "5f8e51e07770412b1911cebb26c55f4b": {
      "rownum": 29,
      "query": "create index t_with_redundant_ref_idx_1 on public.t_with_redundant_ref_idx using btree (i)",
      "calls": 1,
      "total_time": 1182.665615,
      "rows": 0,
      "shared_blks_hit": 1148,
      "shared_blks_read": 1263,
      "shared_blks_dirtied": 1264,
      "shared_blks_written": 1230,
      "local_blks_hit": 0,
      "local_blks_read": 0,
      "local_blks_dirtied": 0,
      "local_blks_written": 0,
      "temp_blks_read": 2448,
      "temp_blks_written": 1283,
      "blk_read_time": 0,
      "blk_write_time": 0,
      "queryid": 7121640066867289000,
      "md5": "5f8e51e07770412b1911cebb26c55f4b"
    },
    "62992e0ccb57f6bdfda778c7c473e8ad": {
      "rownum": 30,
      "query": "create index t_with_redundant_ref_idx_1 on exp_redundant.t_with_redundant_ref_idx using btree (i)",
      "calls": 1,
      "total_time": 1179.026509,
      "rows": 0,
      "shared_blks_hit": 1140,
      "shared_blks_read": 1272,
      "shared_blks_dirtied": 1286,
      "shared_blks_written": 1238,
      "local_blks_hit": 0,
      "local_blks_read": 0,
      "local_blks_dirtied": 0,
      "local_blks_written": 0,
      "temp_blks_read": 2448,
      "temp_blks_written": 1283,
      "blk_read_time": 0,
      "blk_write_time": 0,
      "queryid": -395938069363296600,
      "md5": "62992e0ccb57f6bdfda778c7c473e8ad"
    },
    "479aad6eb92a27d10c03fb12a793614e": {
      "rownum": 31,
      "query": "create index concurrently t_with_redundant_idx_f1 on t_with_redundant_idx(f1)",
      "calls": 1,
      "total_time": 1178.637773,
      "rows": 0,
      "shared_blks_hit": 3571,
      "shared_blks_read": 8971,
      "shared_blks_dirtied": 2,
      "shared_blks_written": 0,
      "local_blks_hit": 0,
      "local_blks_read": 0,
      "local_blks_dirtied": 0,
      "local_blks_written": 0,
      "temp_blks_read": 2448,
      "temp_blks_written": 1272,
      "blk_read_time": 0,
      "blk_write_time": 0,
      "queryid": -7862275411983427000,
      "md5": "479aad6eb92a27d10c03fb12a793614e"
    },
    "63ed402d488d71cb2ac691b882743cad": {
      "rownum": 32,
      "query": "alter table t_red_fk_2 add constraint fk_red_fk2_t1 foreign key (r_t1_id) references t_red_fk_1(id)",
      "calls": 1,
      "total_time": 1176.377091,
      "rows": 0,
      "shared_blks_hit": 4597,
      "shared_blks_read": 5537,
      "shared_blks_dirtied": 3366,
      "shared_blks_written": 3326,
      "local_blks_hit": 0,
      "local_blks_read": 0,
      "local_blks_dirtied": 0,
      "local_blks_written": 0,
      "temp_blks_read": 0,
      "temp_blks_written": 0,
      "blk_read_time": 0,
      "blk_write_time": 0,
      "queryid": 2911641097746118700,
      "md5": "63ed402d488d71cb2ac691b882743cad"
    },
    "cbcd92704dd802d204b9bc7ee8b39187": {
      "rownum": 33,
      "query": "create index t_rar_q_idx on t_rar_q(id)",
      "calls": 1,
      "total_time": 1176.353114,
      "rows": 0,
      "shared_blks_hit": 1149,
      "shared_blks_read": 1751,
      "shared_blks_dirtied": 1747,
      "shared_blks_written": 1711,
      "local_blks_hit": 0,
      "local_blks_read": 0,
      "local_blks_dirtied": 0,
      "local_blks_written": 0,
      "temp_blks_read": 2449,
      "temp_blks_written": 1255,
      "blk_read_time": 0,
      "blk_write_time": 0,
      "queryid": 2650688778442027500,
      "md5": "cbcd92704dd802d204b9bc7ee8b39187"
    },
    "c8703f324c1fb37854d9a2c6edbaa6a2": {
      "rownum": 34,
      "query": "create index r_red_fk_1_X_idx on t_red_fk_1(id)",
      "calls": 1,
      "total_time": 1153.041333,
      "rows": 0,
      "shared_blks_hit": 1201,
      "shared_blks_read": 1226,
      "shared_blks_dirtied": 0,
      "shared_blks_written": 0,
      "local_blks_hit": 0,
      "local_blks_read": 0,
      "local_blks_dirtied": 0,
      "local_blks_written": 0,
      "temp_blks_read": 2448,
      "temp_blks_written": 1299,
      "blk_read_time": 0,
      "blk_write_time": 0,
      "queryid": 3969450259942249000,
      "md5": "c8703f324c1fb37854d9a2c6edbaa6a2"
    },
    "3ebee924ec35c0d73b9480782463f72e": {
      "rownum": 35,
      "query": "create unique index t_with_redundant_idx_f1_uniq on t_with_redundant_idx (f1)",
      "calls": 1,
      "total_time": 1134.025111,
      "rows": 0,
      "shared_blks_hit": 1210,
      "shared_blks_read": 2221,
      "shared_blks_dirtied": 3,
      "shared_blks_written": 33,
      "local_blks_hit": 0,
      "local_blks_read": 0,
      "local_blks_dirtied": 0,
      "local_blks_written": 0,
      "temp_blks_read": 2449,
      "temp_blks_written": 1284,
      "blk_read_time": 0,
      "blk_write_time": 0,
      "queryid": 1566471017150549200,
      "md5": "3ebee924ec35c0d73b9480782463f72e"
    },
    "6bc4ef68211b4d4714588b1314c3b450": {
      "rownum": 36,
      "query": "create index t_with_redundant_ref_idx_3 on public.t_with_redundant_ref_idx using btree (i)",
      "calls": 1,
      "total_time": 1125.96872,
      "rows": 0,
      "shared_blks_hit": 1149,
      "shared_blks_read": 1249,
      "shared_blks_dirtied": 0,
      "shared_blks_written": 0,
      "local_blks_hit": 0,
      "local_blks_read": 0,
      "local_blks_dirtied": 0,
      "local_blks_written": 0,
      "temp_blks_read": 2448,
      "temp_blks_written": 1283,
      "blk_read_time": 0,
      "blk_write_time": 0,
      "queryid": 39141847517093180,
      "md5": "6bc4ef68211b4d4714588b1314c3b450"
    },
    "cdfd61b4586420038e5e614ab85aeeae": {
      "rownum": 37,
      "query": "create index t_with_redundant_ref_idx_2 on public.t_with_redundant_ref_idx using btree (i)",
      "calls": 1,
      "total_time": 1108.390941,
      "rows": 0,
      "shared_blks_hit": 1124,
      "shared_blks_read": 1280,
      "shared_blks_dirtied": 0,
      "shared_blks_written": 0,
      "local_blks_hit": 0,
      "local_blks_read": 0,
      "local_blks_dirtied": 0,
      "local_blks_written": 0,
      "temp_blks_read": 2448,
      "temp_blks_written": 1283,
      "blk_read_time": 0,
      "blk_write_time": 0,
      "queryid": -3115028882787390000,
      "md5": "cdfd61b4586420038e5e614ab85aeeae"
    },
    "7d1bf9b05e76b943c47b50b366c65772": {
      "rownum": 38,
      "query": "create index t_with_redundant_ref_idx_3 on exp_redundant.t_with_redundant_ref_idx using btree (i)",
      "calls": 1,
      "total_time": 1105.144634,
      "rows": 0,
      "shared_blks_hit": 1148,
      "shared_blks_read": 1239,
      "shared_blks_dirtied": 0,
      "shared_blks_written": 0,
      "local_blks_hit": 0,
      "local_blks_read": 0,
      "local_blks_dirtied": 0,
      "local_blks_written": 0,
      "temp_blks_read": 2448,
      "temp_blks_written": 1277,
      "blk_read_time": 0,
      "blk_write_time": 0,
      "queryid": -1845904424067371800,
      "md5": "7d1bf9b05e76b943c47b50b366c65772"
    },
    "7e370d36c2447380a7d5678a0b2040d7": {
      "rownum": 39,
      "query": "create index t_with_redundant_ref_idx_2 on exp_redundant.t_with_redundant_ref_idx using btree (i)",
      "calls": 1,
      "total_time": 1073.536521,
      "rows": 0,
      "shared_blks_hit": 1141,
      "shared_blks_read": 1263,
      "shared_blks_dirtied": 0,
      "shared_blks_written": 0,
      "local_blks_hit": 0,
      "local_blks_read": 0,
      "local_blks_dirtied": 0,
      "local_blks_written": 0,
      "temp_blks_read": 2448,
      "temp_blks_written": 1283,
      "blk_read_time": 0,
      "blk_write_time": 0,
      "queryid": -94268938950487040,
      "md5": "7e370d36c2447380a7d5678a0b2040d7"
    },
    "182ba4f0ffb554baf311c8fa6800939f": {
      "rownum": 40,
      "query": "create database dbname",
      "calls": 1,
      "total_time": 928.939602,
      "rows": 0,
      "shared_blks_hit": 50,
      "shared_blks_read": 9,
      "shared_blks_dirtied": 3,
      "shared_blks_written": 0,
      "local_blks_hit": 0,
      "local_blks_read": 0,
      "local_blks_dirtied": 0,
      "local_blks_written": 0,
      "temp_blks_read": 0,
      "temp_blks_written": 0,
      "blk_read_time": 0,
      "blk_write_time": 0,
      "queryid": 3617698589948080000,
      "md5": "182ba4f0ffb554baf311c8fa6800939f"
    },
    "6d85f5ed15e4a22c77379c8c27e4a096": {
      "rownum": 41,
      "query": "create database checkup_test_db",
      "calls": 1,
      "total_time": 778.992973,
      "rows": 0,
      "shared_blks_hit": 61,
      "shared_blks_read": 4,
      "shared_blks_dirtied": 6,
      "shared_blks_written": 0,
      "local_blks_hit": 0,
      "local_blks_read": 0,
      "local_blks_dirtied": 0,
      "local_blks_written": 0,
      "temp_blks_read": 0,
      "temp_blks_written": 0,
      "blk_read_time": 0,
      "blk_write_time": 0,
      "queryid": -2133351059478393300,
      "md5": "6d85f5ed15e4a22c77379c8c27e4a096"
    },
    "f975f70089262d562c3884413b6f9eaa": {
      "rownum": 42,
      "query": "select count(*) from t_slw_q",
      "calls": 1,
      "total_time": 700.764399,
      "rows": 1,
      "shared_blks_hit": 0,
      "shared_blks_read": 44248,
      "shared_blks_dirtied": 0,
      "shared_blks_written": 0,
      "local_blks_hit": 0,
      "local_blks_read": 0,
      "local_blks_dirtied": 0,
      "local_blks_written": 0,
      "temp_blks_read": 0,
      "temp_blks_written": 0,
      "blk_read_time": 0,
      "blk_write_time": 0,
      "queryid": -8706753100138026000,
      "md5": "f975f70089262d562c3884413b6f9eaa"
    },
    "7069ca8f2e6e2b02c19024b45b325961": {
      "rownum": 43,
      "query": "create table t_36 as select i from generate_series(1, 1000) _(i)",
      "calls": 1,
      "total_time": 89.473587,
      "rows": 0,
      "shared_blks_hit": 228,
      "shared_blks_read": 7,
      "shared_blks_dirtied": 8,
      "shared_blks_written": 0,
      "local_blks_hit": 0,
      "local_blks_read": 0,
      "local_blks_dirtied": 0,
      "local_blks_written": 0,
      "temp_blks_read": 0,
      "temp_blks_written": 0,
      "blk_read_time": 0,
      "blk_write_time": 0,
      "queryid": -8138322207121438000,
      "md5": "7069ca8f2e6e2b02c19024b45b325961"
    },
    "b56c0bbcdd112624648ef48f216f3e92": {
      "rownum": 44,
      "query": "alter system set random_page_cost = 2.22",
      "calls": 1,
      "total_time": 74.038764,
      "rows": 0,
      "shared_blks_hit": 0,
      "shared_blks_read": 0,
      "shared_blks_dirtied": 0,
      "shared_blks_written": 0,
      "local_blks_hit": 0,
      "local_blks_read": 0,
      "local_blks_dirtied": 0,
      "local_blks_written": 0,
      "temp_blks_read": 0,
      "temp_blks_written": 0,
      "blk_read_time": 0,
      "blk_write_time": 0,
      "queryid": 1881993450838449000,
      "md5": "b56c0bbcdd112624648ef48f216f3e92"
    },
    "b7d373c8db27e676fdfdc77dc47b08a0": {
      "rownum": 45,
      "query": "CREATE TABLE test_schema.orders\n(\n id serial,\n cnt integer,\n CONSTRAINT orders_pk PRIMARY KEY (id)\n)",
      "calls": 1,
      "total_time": 72.23005,
      "rows": 0,
      "shared_blks_hit": 457,
      "shared_blks_read": 40,
      "shared_blks_dirtied": 45,
      "shared_blks_written": 0,
      "local_blks_hit": 0,
      "local_blks_read": 0,
      "local_blks_dirtied": 0,
      "local_blks_written": 0,
      "temp_blks_read": 0,
      "temp_blks_written": 0,
      "blk_read_time": 0,
      "blk_write_time": 0,
      "queryid": -1491185255100233500,
      "md5": "b7d373c8db27e676fdfdc77dc47b08a0"
    },
    "d02d1aef973dfdb7a87f56b6b6dfea91": {
      "rownum": 46,
      "query": "create table bloated as select i from generate_series(1, 100000) _(i)",
      "calls": 1,
      "total_time": 66.156754,
      "rows": 0,
      "shared_blks_hit": 126,
      "shared_blks_read": 443,
      "shared_blks_dirtied": 444,
      "shared_blks_written": 0,
      "local_blks_hit": 0,
      "local_blks_read": 0,
      "local_blks_dirtied": 0,
      "local_blks_written": 0,
      "temp_blks_read": 171,
      "temp_blks_written": 171,
      "blk_read_time": 0,
      "blk_write_time": 0,
      "queryid": -2951921325210440700,
      "md5": "d02d1aef973dfdb7a87f56b6b6dfea91"
    },
    "5cd67d267cf565c7d9032a50af03cfee": {
      "rownum": 47,
      "query": "create table t_30 as select i from generate_series(1, 1000) _(i)",
      "calls": 1,
      "total_time": 45.002717,
      "rows": 0,
      "shared_blks_hit": 232,
      "shared_blks_read": 7,
      "shared_blks_dirtied": 8,
      "shared_blks_written": 0,
      "local_blks_hit": 0,
      "local_blks_read": 0,
      "local_blks_dirtied": 0,
      "local_blks_written": 0,
      "temp_blks_read": 0,
      "temp_blks_written": 0,
      "blk_read_time": 0,
      "blk_write_time": 0,
      "queryid": -2808691262207182300,
      "md5": "5cd67d267cf565c7d9032a50af03cfee"
    },
    "23bbd085bb37c5fafcd10ade38dfacf7": {
      "rownum": 48,
      "query": "create index i_bloated on bloated(i)",
      "calls": 1,
      "total_time": 38.040189,
      "rows": 0,
      "shared_blks_hit": 534,
      "shared_blks_read": 0,
      "shared_blks_dirtied": 0,
      "shared_blks_written": 0,
      "local_blks_hit": 0,
      "local_blks_read": 0,
      "local_blks_dirtied": 0,
      "local_blks_written": 0,
      "temp_blks_read": 0,
      "temp_blks_written": 0,
      "blk_read_time": 0,
      "blk_write_time": 0,
      "queryid": 8841083458873351000,
      "md5": "23bbd085bb37c5fafcd10ade38dfacf7"
    },
    "19ad86429ce9586b23276499ccbc3332": {
      "rownum": 49,
      "query": "create index concurrently i_r_36 on t_36(i)",
      "calls": 1,
      "total_time": 32.873169,
      "rows": 0,
      "shared_blks_hit": 129,
      "shared_blks_read": 7,
      "shared_blks_dirtied": 4,
      "shared_blks_written": 0,
      "local_blks_hit": 0,
      "local_blks_read": 0,
      "local_blks_dirtied": 0,
      "local_blks_written": 0,
      "temp_blks_read": 0,
      "temp_blks_written": 0,
      "blk_read_time": 0,
      "blk_write_time": 0,
      "queryid": 6908822462161268000,
      "md5": "19ad86429ce9586b23276499ccbc3332"
    },
    "ab7d8f0edf844d85869cd324de44e515": {
      "rownum": 50,
      "query": "delete from bloated where i % $1 = $2",
      "calls": 1,
      "total_time": 31.908433,
      "rows": 50000,
      "shared_blks_hit": 50443,
      "shared_blks_read": 0,
      "shared_blks_dirtied": 0,
      "shared_blks_written": 0,
      "local_blks_hit": 0,
      "local_blks_read": 0,
      "local_blks_dirtied": 0,
      "local_blks_written": 0,
      "temp_blks_read": 0,
      "temp_blks_written": 0,
      "blk_read_time": 0,
      "blk_write_time": 0,
      "queryid": -3076169388096589300,
      "md5": "ab7d8f0edf844d85869cd324de44e515"
    },
    "7ed1e0a10c6a02c54b4d60f7426fa7ba": {
      "rownum": 51,
      "query": "create index concurrently i_r_66 on t_66(i)",
      "calls": 1,
      "total_time": 21.487236,
      "rows": 0,
      "shared_blks_hit": 128,
      "shared_blks_read": 5,
      "shared_blks_dirtied": 2,
      "shared_blks_written": 0,
      "local_blks_hit": 0,
      "local_blks_read": 0,
      "local_blks_dirtied": 0,
      "local_blks_written": 0,
      "temp_blks_read": 0,
      "temp_blks_written": 0,
      "blk_read_time": 0,
      "blk_write_time": 0,
      "queryid": 1206033848688972500,
      "md5": "7ed1e0a10c6a02c54b4d60f7426fa7ba"
    },
    "ff68c2d52ff52cf5a1df23f0176ea83d": {
      "rownum": 52,
      "query": "create index concurrently i_u_70 on t_70(i)",
      "calls": 1,
      "total_time": 19.148176,
      "rows": 0,
      "shared_blks_hit": 200,
      "shared_blks_read": 5,
      "shared_blks_dirtied": 2,
      "shared_blks_written": 0,
      "local_blks_hit": 0,
      "local_blks_read": 0,
      "local_blks_dirtied": 0,
      "local_blks_written": 0,
      "temp_blks_read": 0,
      "temp_blks_written": 0,
      "blk_read_time": 0,
      "blk_write_time": 0,
      "queryid": 3694177823672669000,
      "md5": "ff68c2d52ff52cf5a1df23f0176ea83d"
    },
    "607420b7ab000cbfecd67b661a26d750": {
      "rownum": 53,
      "query": "create index concurrently i_u_64 on t_64(i)",
      "calls": 1,
      "total_time": 19.001822,
      "rows": 0,
      "shared_blks_hit": 200,
      "shared_blks_read": 5,
      "shared_blks_dirtied": 2,
      "shared_blks_written": 0,
      "local_blks_hit": 0,
      "local_blks_read": 0,
      "local_blks_dirtied": 0,
      "local_blks_written": 0,
      "temp_blks_read": 0,
      "temp_blks_written": 0,
      "blk_read_time": 0,
      "blk_write_time": 0,
      "queryid": 177860461183167600,
      "md5": "607420b7ab000cbfecd67b661a26d750"
    },
    "1cd9522240ff44b55c71c091cba0ef3e": {
      "rownum": 54,
      "query": "create index concurrently i_u_71 on t_71(i)",
      "calls": 1,
      "total_time": 18.976389,
      "rows": 0,
      "shared_blks_hit": 200,
      "shared_blks_read": 5,
      "shared_blks_dirtied": 2,
      "shared_blks_written": 0,
      "local_blks_hit": 0,
      "local_blks_read": 0,
      "local_blks_dirtied": 0,
      "local_blks_written": 0,
      "temp_blks_read": 0,
      "temp_blks_written": 0,
      "blk_read_time": 0,
      "blk_write_time": 0,
      "queryid": 8663923673739985000,
      "md5": "1cd9522240ff44b55c71c091cba0ef3e"
    },
    "8320a0ed02a7ee0ddeed3abd836333e6": {
      "rownum": 55,
      "query": "create index concurrently i_u_84 on t_84(i)",
      "calls": 1,
      "total_time": 17.10972,
      "rows": 0,
      "shared_blks_hit": 200,
      "shared_blks_read": 5,
      "shared_blks_dirtied": 2,
      "shared_blks_written": 0,
      "local_blks_hit": 0,
      "local_blks_read": 0,
      "local_blks_dirtied": 0,
      "local_blks_written": 0,
      "temp_blks_read": 0,
      "temp_blks_written": 0,
      "blk_read_time": 0,
      "blk_write_time": 0,
      "queryid": 5901824851018781000,
      "md5": "8320a0ed02a7ee0ddeed3abd836333e6"
    },
    "829d7036f387e638c1b64244a8405959": {
      "rownum": 56,
      "query": "create index concurrently i_u_76 on t_76(i)",
      "calls": 1,
      "total_time": 16.835416,
      "rows": 0,
      "shared_blks_hit": 200,
      "shared_blks_read": 5,
      "shared_blks_dirtied": 2,
      "shared_blks_written": 0,
      "local_blks_hit": 0,
      "local_blks_read": 0,
      "local_blks_dirtied": 0,
      "local_blks_written": 0,
      "temp_blks_read": 0,
      "temp_blks_written": 0,
      "blk_read_time": 0,
      "blk_write_time": 0,
      "queryid": 915394385423267100,
      "md5": "829d7036f387e638c1b64244a8405959"
    },
    "28dc3c924e72370594c0ba4c1b259642": {
      "rownum": 57,
      "query": "create index concurrently i_u_50 on t_50(i)",
      "calls": 1,
      "total_time": 15.63331,
      "rows": 0,
      "shared_blks_hit": 200,
      "shared_blks_read": 5,
      "shared_blks_dirtied": 2,
      "shared_blks_written": 0,
      "local_blks_hit": 0,
      "local_blks_read": 0,
      "local_blks_dirtied": 0,
      "local_blks_written": 0,
      "temp_blks_read": 0,
      "temp_blks_written": 0,
      "blk_read_time": 0,
      "blk_write_time": 0,
      "queryid": 7953863237307717000,
      "md5": "28dc3c924e72370594c0ba4c1b259642"
    },
    "eabc82a0ec9ae7e287269167c797b89b": {
      "rownum": 58,
      "query": "create index concurrently i_u_75 on t_75(i)",
      "calls": 1,
      "total_time": 14.564001,
      "rows": 0,
      "shared_blks_hit": 200,
      "shared_blks_read": 5,
      "shared_blks_dirtied": 2,
      "shared_blks_written": 0,
      "local_blks_hit": 0,
      "local_blks_read": 0,
      "local_blks_dirtied": 0,
      "local_blks_written": 0,
      "temp_blks_read": 0,
      "temp_blks_written": 0,
      "blk_read_time": 0,
      "blk_write_time": 0,
      "queryid": -6829298630711561000,
      "md5": "eabc82a0ec9ae7e287269167c797b89b"
    },
    "aa086b8abbfeee586db5726913843173": {
      "rownum": 59,
      "query": "create index concurrently i_u_74 on t_74(i)",
      "calls": 1,
      "total_time": 14.090258,
      "rows": 0,
      "shared_blks_hit": 200,
      "shared_blks_read": 5,
      "shared_blks_dirtied": 2,
      "shared_blks_written": 0,
      "local_blks_hit": 0,
      "local_blks_read": 0,
      "local_blks_dirtied": 0,
      "local_blks_written": 0,
      "temp_blks_read": 0,
      "temp_blks_written": 0,
      "blk_read_time": 0,
      "blk_write_time": 0,
      "queryid": 3821899459888144000,
      "md5": "aa086b8abbfeee586db5726913843173"
    },
    "7166501388435bd7719674b4de4fd9f8": {
      "rownum": 60,
      "query": "create index concurrently i_r_51 on t_51(i)",
      "calls": 1,
      "total_time": 14.051883,
      "rows": 0,
      "shared_blks_hit": 128,
      "shared_blks_read": 5,
      "shared_blks_dirtied": 2,
      "shared_blks_written": 0,
      "local_blks_hit": 0,
      "local_blks_read": 0,
      "local_blks_dirtied": 0,
      "local_blks_written": 0,
      "temp_blks_read": 0,
      "temp_blks_written": 0,
      "blk_read_time": 0,
      "blk_write_time": 0,
      "queryid": -6699952124008687000,
      "md5": "7166501388435bd7719674b4de4fd9f8"
    },
    "a7f6f1594c7fd0f61856735eb299b8ea": {
      "rownum": 61,
      "query": "create index concurrently i_r_65 on t_65(i)",
      "calls": 1,
      "total_time": 14.005394,
      "rows": 0,
      "shared_blks_hit": 128,
      "shared_blks_read": 5,
      "shared_blks_dirtied": 2,
      "shared_blks_written": 0,
      "local_blks_hit": 0,
      "local_blks_read": 0,
      "local_blks_dirtied": 0,
      "local_blks_written": 0,
      "temp_blks_read": 0,
      "temp_blks_written": 0,
      "blk_read_time": 0,
      "blk_write_time": 0,
      "queryid": -4337717079718359600,
      "md5": "a7f6f1594c7fd0f61856735eb299b8ea"
    },
    "13ef04937e522ba8a9d3cc24345b55f7": {
      "rownum": 62,
      "query": "create index concurrently i_u_78 on t_78(i)",
      "calls": 1,
      "total_time": 13.57951,
      "rows": 0,
      "shared_blks_hit": 202,
      "shared_blks_read": 6,
      "shared_blks_dirtied": 3,
      "shared_blks_written": 0,
      "local_blks_hit": 0,
      "local_blks_read": 0,
      "local_blks_dirtied": 0,
      "local_blks_written": 0,
      "temp_blks_read": 0,
      "temp_blks_written": 0,
      "blk_read_time": 0,
      "blk_write_time": 0,
      "queryid": -395470359289702340,
      "md5": "13ef04937e522ba8a9d3cc24345b55f7"
    },
    "818252bc4de136a03e0f3c8d641e8cda": {
      "rownum": 63,
      "query": "create index concurrently i_u_1 on t_1(i)",
      "calls": 1,
      "total_time": 12.764395,
      "rows": 0,
      "shared_blks_hit": 199,
      "shared_blks_read": 8,
      "shared_blks_dirtied": 2,
      "shared_blks_written": 0,
      "local_blks_hit": 0,
      "local_blks_read": 0,
      "local_blks_dirtied": 0,
      "local_blks_written": 0,
      "temp_blks_read": 0,
      "temp_blks_written": 0,
      "blk_read_time": 0,
      "blk_write_time": 0,
      "queryid": 8045454930243187000,
      "md5": "818252bc4de136a03e0f3c8d641e8cda"
    },
    "d53dfd047a819c5d64abeedfb303ae92": {
      "rownum": 64,
      "query": "create index concurrently i_r_50 on t_50(i)",
      "calls": 1,
      "total_time": 12.685093,
      "rows": 0,
      "shared_blks_hit": 128,
      "shared_blks_read": 5,
      "shared_blks_dirtied": 2,
      "shared_blks_written": 0,
      "local_blks_hit": 0,
      "local_blks_read": 0,
      "local_blks_dirtied": 0,
      "local_blks_written": 0,
      "temp_blks_read": 0,
      "temp_blks_written": 0,
      "blk_read_time": 0,
      "blk_write_time": 0,
      "queryid": -2152932359127106300,
      "md5": "d53dfd047a819c5d64abeedfb303ae92"
    },
    "ceae69795aaba40a8057d6c2be57d6ad": {
      "rownum": 65,
      "query": "create index concurrently i_r_61 on t_61(i)",
      "calls": 1,
      "total_time": 12.530385,
      "rows": 0,
      "shared_blks_hit": 128,
      "shared_blks_read": 5,
      "shared_blks_dirtied": 2,
      "shared_blks_written": 0,
      "local_blks_hit": 0,
      "local_blks_read": 0,
      "local_blks_dirtied": 0,
      "local_blks_written": 0,
      "temp_blks_read": 0,
      "temp_blks_written": 0,
      "blk_read_time": 0,
      "blk_write_time": 0,
      "queryid": -5533723081650170000,
      "md5": "ceae69795aaba40a8057d6c2be57d6ad"
    },
    "18733f12451eda1bcdeb5f15ca0e2bff": {
      "rownum": 66,
      "query": "create index concurrently i_u_52 on t_52(i)",
      "calls": 1,
      "total_time": 12.273483,
      "rows": 0,
      "shared_blks_hit": 200,
      "shared_blks_read": 5,
      "shared_blks_dirtied": 2,
      "shared_blks_written": 0,
      "local_blks_hit": 0,
      "local_blks_read": 0,
      "local_blks_dirtied": 0,
      "local_blks_written": 0,
      "temp_blks_read": 0,
      "temp_blks_written": 0,
      "blk_read_time": 0,
      "blk_write_time": 0,
      "queryid": -6687581582105482000,
      "md5": "18733f12451eda1bcdeb5f15ca0e2bff"
    },
    "8b2e13a7d0128bd60630d3193dfe0980": {
      "rownum": 67,
      "query": "create index concurrently i_u_96 on t_96(i)",
      "calls": 1,
      "total_time": 11.98689,
      "rows": 0,
      "shared_blks_hit": 200,
      "shared_blks_read": 5,
      "shared_blks_dirtied": 2,
      "shared_blks_written": 0,
      "local_blks_hit": 0,
      "local_blks_read": 0,
      "local_blks_dirtied": 0,
      "local_blks_written": 0,
      "temp_blks_read": 0,
      "temp_blks_written": 0,
      "blk_read_time": 0,
      "blk_write_time": 0,
      "queryid": -9095195149180732000,
      "md5": "8b2e13a7d0128bd60630d3193dfe0980"
    },
    "9344159b5082c66fa9cb8880e59b7f56": {
      "rownum": 68,
      "query": "create index concurrently i_r_77 on t_77(i)",
      "calls": 1,
      "total_time": 11.570793,
      "rows": 0,
      "shared_blks_hit": 128,
      "shared_blks_read": 5,
      "shared_blks_dirtied": 2,
      "shared_blks_written": 0,
      "local_blks_hit": 0,
      "local_blks_read": 0,
      "local_blks_dirtied": 0,
      "local_blks_written": 0,
      "temp_blks_read": 0,
      "temp_blks_written": 0,
      "blk_read_time": 0,
      "blk_write_time": 0,
      "queryid": 4096752785135302000,
      "md5": "9344159b5082c66fa9cb8880e59b7f56"
    },
    "7313e7a283d57ec584da21632008e6f7": {
      "rownum": 69,
      "query": "create index concurrently i_u_87 on t_87(i)",
      "calls": 1,
      "total_time": 11.467612,
      "rows": 0,
      "shared_blks_hit": 200,
      "shared_blks_read": 5,
      "shared_blks_dirtied": 2,
      "shared_blks_written": 0,
      "local_blks_hit": 0,
      "local_blks_read": 0,
      "local_blks_dirtied": 0,
      "local_blks_written": 0,
      "temp_blks_read": 0,
      "temp_blks_written": 0,
      "blk_read_time": 0,
      "blk_write_time": 0,
      "queryid": 6776931081508499000,
      "md5": "7313e7a283d57ec584da21632008e6f7"
    },
    "c43824b6813a135b2895ad87a7f5b7b8": {
      "rownum": 70,
      "query": "create index concurrently i_u_42 on t_42(i)",
      "calls": 1,
      "total_time": 11.446047,
      "rows": 0,
      "shared_blks_hit": 200,
      "shared_blks_read": 5,
      "shared_blks_dirtied": 2,
      "shared_blks_written": 0,
      "local_blks_hit": 0,
      "local_blks_read": 0,
      "local_blks_dirtied": 0,
      "local_blks_written": 0,
      "temp_blks_read": 0,
      "temp_blks_written": 0,
      "blk_read_time": 0,
      "blk_write_time": 0,
      "queryid": -7304587271352061000,
      "md5": "c43824b6813a135b2895ad87a7f5b7b8"
    },
    "9e4c8c80279f69de75aae81b53e0e10d": {
      "rownum": 71,
      "query": "create index concurrently i_r_48 on t_48(i)",
      "calls": 1,
      "total_time": 11.304065,
      "rows": 0,
      "shared_blks_hit": 128,
      "shared_blks_read": 5,
      "shared_blks_dirtied": 2,
      "shared_blks_written": 0,
      "local_blks_hit": 0,
      "local_blks_read": 0,
      "local_blks_dirtied": 0,
      "local_blks_written": 0,
      "temp_blks_read": 0,
      "temp_blks_written": 0,
      "blk_read_time": 0,
      "blk_write_time": 0,
      "queryid": 8487355650255158000,
      "md5": "9e4c8c80279f69de75aae81b53e0e10d"
    },
    "3bd7ac111bc726514f86460fb67b87db": {
      "rownum": 72,
      "query": "create index concurrently i_r_68 on t_68(i)",
      "calls": 1,
      "total_time": 11.237831,
      "rows": 0,
      "shared_blks_hit": 128,
      "shared_blks_read": 5,
      "shared_blks_dirtied": 2,
      "shared_blks_written": 0,
      "local_blks_hit": 0,
      "local_blks_read": 0,
      "local_blks_dirtied": 0,
      "local_blks_written": 0,
      "temp_blks_read": 0,
      "temp_blks_written": 0,
      "blk_read_time": 0,
      "blk_write_time": 0,
      "queryid": -185707737803468000,
      "md5": "3bd7ac111bc726514f86460fb67b87db"
    },
    "446bb8761a62b724fd27838adcbc3011": {
      "rownum": 73,
      "query": "create index concurrently i_r_99 on t_99(i)",
      "calls": 1,
      "total_time": 11.214989,
      "rows": 0,
      "shared_blks_hit": 128,
      "shared_blks_read": 5,
      "shared_blks_dirtied": 2,
      "shared_blks_written": 0,
      "local_blks_hit": 0,
      "local_blks_read": 0,
      "local_blks_dirtied": 0,
      "local_blks_written": 0,
      "temp_blks_read": 0,
      "temp_blks_written": 0,
      "blk_read_time": 0,
      "blk_write_time": 0,
      "queryid": 1438894243932472000,
      "md5": "446bb8761a62b724fd27838adcbc3011"
    },
    "b61a1d4249f700bd2ed4712449ba052a": {
      "rownum": 74,
      "query": "create index concurrently i_r_93 on t_93(i)",
      "calls": 1,
      "total_time": 11.079063,
      "rows": 0,
      "shared_blks_hit": 128,
      "shared_blks_read": 5,
      "shared_blks_dirtied": 2,
      "shared_blks_written": 0,
      "local_blks_hit": 0,
      "local_blks_read": 0,
      "local_blks_dirtied": 0,
      "local_blks_written": 0,
      "temp_blks_read": 0,
      "temp_blks_written": 0,
      "blk_read_time": 0,
      "blk_write_time": 0,
      "queryid": -1085300093534512900,
      "md5": "b61a1d4249f700bd2ed4712449ba052a"
    },
    "86f2d2662d0f02178c4d27178b84e28a": {
      "rownum": 75,
      "query": "create index concurrently i_u_46 on t_46(i)",
      "calls": 1,
      "total_time": 11.016145,
      "rows": 0,
      "shared_blks_hit": 201,
      "shared_blks_read": 7,
      "shared_blks_dirtied": 5,
      "shared_blks_written": 0,
      "local_blks_hit": 0,
      "local_blks_read": 0,
      "local_blks_dirtied": 0,
      "local_blks_written": 0,
      "temp_blks_read": 0,
      "temp_blks_written": 0,
      "blk_read_time": 0,
      "blk_write_time": 0,
      "queryid": 5347103578192611000,
      "md5": "86f2d2662d0f02178c4d27178b84e28a"
    },
    "da1482a9f4e3fb7e8c5cf044a7608d04": {
      "rownum": 76,
      "query": "create index concurrently i_r_72 on t_72(i)",
      "calls": 1,
      "total_time": 10.811531,
      "rows": 0,
      "shared_blks_hit": 128,
      "shared_blks_read": 5,
      "shared_blks_dirtied": 2,
      "shared_blks_written": 0,
      "local_blks_hit": 0,
      "local_blks_read": 0,
      "local_blks_dirtied": 0,
      "local_blks_written": 0,
      "temp_blks_read": 0,
      "temp_blks_written": 0,
      "blk_read_time": 0,
      "blk_write_time": 0,
      "queryid": 3521734344261747000,
      "md5": "da1482a9f4e3fb7e8c5cf044a7608d04"
    },
    "596d8a5d9c62389b6b91902918211965": {
      "rownum": 77,
      "query": "create index concurrently i_r_74 on t_74(i)",
      "calls": 1,
      "total_time": 10.779218,
      "rows": 0,
      "shared_blks_hit": 128,
      "shared_blks_read": 5,
      "shared_blks_dirtied": 2,
      "shared_blks_written": 0,
      "local_blks_hit": 0,
      "local_blks_read": 0,
      "local_blks_dirtied": 0,
      "local_blks_written": 0,
      "temp_blks_read": 0,
      "temp_blks_written": 0,
      "blk_read_time": 0,
      "blk_write_time": 0,
      "queryid": 6805853024851374000,
      "md5": "596d8a5d9c62389b6b91902918211965"
    },
    "f42880b0f3e80758b3d0c699d435bc94": {
      "rownum": 78,
      "query": "create index concurrently i_r_57 on t_57(i)",
      "calls": 1,
      "total_time": 10.618217,
      "rows": 0,
      "shared_blks_hit": 128,
      "shared_blks_read": 5,
      "shared_blks_dirtied": 2,
      "shared_blks_written": 0,
      "local_blks_hit": 0,
      "local_blks_read": 0,
      "local_blks_dirtied": 0,
      "local_blks_written": 0,
      "temp_blks_read": 0,
      "temp_blks_written": 0,
      "blk_read_time": 0,
      "blk_write_time": 0,
      "queryid": 6065299143204429000,
      "md5": "f42880b0f3e80758b3d0c699d435bc94"
    },
    "97767aa87aa69c5c7b59a8f3c0b2fb3e": {
      "rownum": 79,
      "query": "create index concurrently i_u_81 on t_81(i)",
      "calls": 1,
      "total_time": 10.546577,
      "rows": 0,
      "shared_blks_hit": 200,
      "shared_blks_read": 5,
      "shared_blks_dirtied": 2,
      "shared_blks_written": 0,
      "local_blks_hit": 0,
      "local_blks_read": 0,
      "local_blks_dirtied": 0,
      "local_blks_written": 0,
      "temp_blks_read": 0,
      "temp_blks_written": 0,
      "blk_read_time": 0,
      "blk_write_time": 0,
      "queryid": -538611708982877250,
      "md5": "97767aa87aa69c5c7b59a8f3c0b2fb3e"
    },
    "05c7018013f2efe4c6970c9ecf20b8ed": {
      "rownum": 80,
      "query": "create index concurrently i_u_44 on t_44(i)",
      "calls": 1,
      "total_time": 10.537495,
      "rows": 0,
      "shared_blks_hit": 200,
      "shared_blks_read": 5,
      "shared_blks_dirtied": 2,
      "shared_blks_written": 0,
      "local_blks_hit": 0,
      "local_blks_read": 0,
      "local_blks_dirtied": 0,
      "local_blks_written": 0,
      "temp_blks_read": 0,
      "temp_blks_written": 0,
      "blk_read_time": 0,
      "blk_write_time": 0,
      "queryid": 3837169512090792400,
      "md5": "05c7018013f2efe4c6970c9ecf20b8ed"
    },
    "749605125e82a1a29fd9b05b8c6c53f3": {
      "rownum": 81,
      "query": "create index concurrently i_r_102 on t_102(i)",
      "calls": 1,
      "total_time": 10.456914,
      "rows": 0,
      "shared_blks_hit": 128,
      "shared_blks_read": 5,
      "shared_blks_dirtied": 2,
      "shared_blks_written": 0,
      "local_blks_hit": 0,
      "local_blks_read": 0,
      "local_blks_dirtied": 0,
      "local_blks_written": 0,
      "temp_blks_read": 0,
      "temp_blks_written": 0,
      "blk_read_time": 0,
      "blk_write_time": 0,
      "queryid": 3158560420250906600,
      "md5": "749605125e82a1a29fd9b05b8c6c53f3"
    },
    "501c8ad1f5ed499a8096f051d185840f": {
      "rownum": 82,
      "query": "create index concurrently i_r_45 on t_45(i)",
      "calls": 1,
      "total_time": 10.43265,
      "rows": 0,
      "shared_blks_hit": 128,
      "shared_blks_read": 5,
      "shared_blks_dirtied": 2,
      "shared_blks_written": 0,
      "local_blks_hit": 0,
      "local_blks_read": 0,
      "local_blks_dirtied": 0,
      "local_blks_written": 0,
      "temp_blks_read": 0,
      "temp_blks_written": 0,
      "blk_read_time": 0,
      "blk_write_time": 0,
      "queryid": 1933432499149815000,
      "md5": "501c8ad1f5ed499a8096f051d185840f"
    },
    "9bad4a97bdc81a9589b6b23cc51743ed": {
      "rownum": 83,
      "query": "create index concurrently i_r_64 on t_64(i)",
      "calls": 1,
      "total_time": 10.431381,
      "rows": 0,
      "shared_blks_hit": 128,
      "shared_blks_read": 5,
      "shared_blks_dirtied": 2,
      "shared_blks_written": 0,
      "local_blks_hit": 0,
      "local_blks_read": 0,
      "local_blks_dirtied": 0,
      "local_blks_written": 0,
      "temp_blks_read": 0,
      "temp_blks_written": 0,
      "blk_read_time": 0,
      "blk_write_time": 0,
      "queryid": -7063686397495941000,
      "md5": "9bad4a97bdc81a9589b6b23cc51743ed"
    },
    "db2c7d19cef3a8a9b788e5f16a6ecf13": {
      "rownum": 84,
      "query": "create index concurrently i_r_42 on t_42(i)",
      "calls": 1,
      "total_time": 10.422802,
      "rows": 0,
      "shared_blks_hit": 128,
      "shared_blks_read": 5,
      "shared_blks_dirtied": 2,
      "shared_blks_written": 0,
      "local_blks_hit": 0,
      "local_blks_read": 0,
      "local_blks_dirtied": 0,
      "local_blks_written": 0,
      "temp_blks_read": 0,
      "temp_blks_written": 0,
      "blk_read_time": 0,
      "blk_write_time": 0,
      "queryid": -4880803480357036000,
      "md5": "db2c7d19cef3a8a9b788e5f16a6ecf13"
    },
    "66d082e57854d2e3cf0f42bdfb7910bd": {
      "rownum": 85,
      "query": "create index concurrently i_u_49 on t_49(i)",
      "calls": 1,
      "total_time": 10.15154,
      "rows": 0,
      "shared_blks_hit": 201,
      "shared_blks_read": 5,
      "shared_blks_dirtied": 2,
      "shared_blks_written": 0,
      "local_blks_hit": 0,
      "local_blks_read": 0,
      "local_blks_dirtied": 0,
      "local_blks_written": 0,
      "temp_blks_read": 0,
      "temp_blks_written": 0,
      "blk_read_time": 0,
      "blk_write_time": 0,
      "queryid": 45512294994752580,
      "md5": "66d082e57854d2e3cf0f42bdfb7910bd"
    },
    "4bb3cae75102c3bac3fe8ed447cc414f": {
      "rownum": 86,
      "query": "create index concurrently i_r_33 on t_33(i)",
      "calls": 1,
      "total_time": 10.120294,
      "rows": 0,
      "shared_blks_hit": 128,
      "shared_blks_read": 5,
      "shared_blks_dirtied": 2,
      "shared_blks_written": 0,
      "local_blks_hit": 0,
      "local_blks_read": 0,
      "local_blks_dirtied": 0,
      "local_blks_written": 0,
      "temp_blks_read": 0,
      "temp_blks_written": 0,
      "blk_read_time": 0,
      "blk_write_time": 0,
      "queryid": 3407198261892793000,
      "md5": "4bb3cae75102c3bac3fe8ed447cc414f"
    },
    "5966557e5d4ef69508069b0fbf99b1c8": {
      "rownum": 87,
      "query": "create index concurrently i_u_103 on t_103(i)",
      "calls": 1,
      "total_time": 9.943132,
      "rows": 0,
      "shared_blks_hit": 200,
      "shared_blks_read": 5,
      "shared_blks_dirtied": 2,
      "shared_blks_written": 0,
      "local_blks_hit": 0,
      "local_blks_read": 0,
      "local_blks_dirtied": 0,
      "local_blks_written": 0,
      "temp_blks_read": 0,
      "temp_blks_written": 0,
      "blk_read_time": 0,
      "blk_write_time": 0,
      "queryid": -1618134738108633900,
      "md5": "5966557e5d4ef69508069b0fbf99b1c8"
    },
    "fd1a2747e788f14c196c0273573181ba": {
      "rownum": 88,
      "query": "create index concurrently i_r_87 on t_87(i)",
      "calls": 1,
      "total_time": 9.825687,
      "rows": 0,
      "shared_blks_hit": 128,
      "shared_blks_read": 5,
      "shared_blks_dirtied": 2,
      "shared_blks_written": 0,
      "local_blks_hit": 0,
      "local_blks_read": 0,
      "local_blks_dirtied": 0,
      "local_blks_written": 0,
      "temp_blks_read": 0,
      "temp_blks_written": 0,
      "blk_read_time": 0,
      "blk_write_time": 0,
      "queryid": 3536017651192263000,
      "md5": "fd1a2747e788f14c196c0273573181ba"
    },
    "7e923b18e224be2404867c2195d7d47c": {
      "rownum": 89,
      "query": "create index concurrently i_r_15 on t_15(i)",
      "calls": 1,
      "total_time": 9.790663,
      "rows": 0,
      "shared_blks_hit": 128,
      "shared_blks_read": 5,
      "shared_blks_dirtied": 2,
      "shared_blks_written": 0,
      "local_blks_hit": 0,
      "local_blks_read": 0,
      "local_blks_dirtied": 0,
      "local_blks_written": 0,
      "temp_blks_read": 0,
      "temp_blks_written": 0,
      "blk_read_time": 0,
      "blk_write_time": 0,
      "queryid": 1142841192279002100,
      "md5": "7e923b18e224be2404867c2195d7d47c"
    },
    "c8407bc7219ce0ed65148ba3aae31793": {
      "rownum": 90,
      "query": "create index concurrently i_u_12 on t_12(i)",
      "calls": 1,
      "total_time": 9.709602,
      "rows": 0,
      "shared_blks_hit": 202,
      "shared_blks_read": 6,
      "shared_blks_dirtied": 3,
      "shared_blks_written": 0,
      "local_blks_hit": 0,
      "local_blks_read": 0,
      "local_blks_dirtied": 0,
      "local_blks_written": 0,
      "temp_blks_read": 0,
      "temp_blks_written": 0,
      "blk_read_time": 0,
      "blk_write_time": 0,
      "queryid": -2315564220582489000,
      "md5": "c8407bc7219ce0ed65148ba3aae31793"
    },
    "3345aa319a482ddb5f0882a127d110c2": {
      "rownum": 91,
      "query": "create index concurrently i_r_69 on t_69(i)",
      "calls": 1,
      "total_time": 9.648625,
      "rows": 0,
      "shared_blks_hit": 128,
      "shared_blks_read": 5,
      "shared_blks_dirtied": 2,
      "shared_blks_written": 0,
      "local_blks_hit": 0,
      "local_blks_read": 0,
      "local_blks_dirtied": 0,
      "local_blks_written": 0,
      "temp_blks_read": 0,
      "temp_blks_written": 0,
      "blk_read_time": 0,
      "blk_write_time": 0,
      "queryid": 6638156021187116000,
      "md5": "3345aa319a482ddb5f0882a127d110c2"
    },
    "9e5cd7552ff0f70b2f6f7363a65bca9f": {
      "rownum": 92,
      "query": "create index concurrently i_r_56 on t_56(i)",
      "calls": 1,
      "total_time": 9.568039,
      "rows": 0,
      "shared_blks_hit": 128,
      "shared_blks_read": 5,
      "shared_blks_dirtied": 2,
      "shared_blks_written": 0,
      "local_blks_hit": 0,
      "local_blks_read": 0,
      "local_blks_dirtied": 0,
      "local_blks_written": 0,
      "temp_blks_read": 0,
      "temp_blks_written": 0,
      "blk_read_time": 0,
      "blk_write_time": 0,
      "queryid": 6314351874136435000,
      "md5": "9e5cd7552ff0f70b2f6f7363a65bca9f"
    },
    "886ef5c9001ab1527e2880e5480908a7": {
      "rownum": 93,
      "query": "create index concurrently i_r_71 on t_71(i)",
      "calls": 1,
      "total_time": 9.519283,
      "rows": 0,
      "shared_blks_hit": 128,
      "shared_blks_read": 5,
      "shared_blks_dirtied": 2,
      "shared_blks_written": 0,
      "local_blks_hit": 0,
      "local_blks_read": 0,
      "local_blks_dirtied": 0,
      "local_blks_written": 0,
      "temp_blks_read": 0,
      "temp_blks_written": 0,
      "blk_read_time": 0,
      "blk_write_time": 0,
      "queryid": 5035677124990811000,
      "md5": "886ef5c9001ab1527e2880e5480908a7"
    },
    "223fbc84ae345a90b2a294b7e0fda30e": {
      "rownum": 94,
      "query": "create index concurrently i_u_67 on t_67(i)",
      "calls": 1,
      "total_time": 9.477618,
      "rows": 0,
      "shared_blks_hit": 202,
      "shared_blks_read": 6,
      "shared_blks_dirtied": 3,
      "shared_blks_written": 0,
      "local_blks_hit": 0,
      "local_blks_read": 0,
      "local_blks_dirtied": 0,
      "local_blks_written": 0,
      "temp_blks_read": 0,
      "temp_blks_written": 0,
      "blk_read_time": 0,
      "blk_write_time": 0,
      "queryid": 5384648471908517000,
      "md5": "223fbc84ae345a90b2a294b7e0fda30e"
    },
    "7711bbbadc4cd32a0908248bc4361a1a": {
      "rownum": 95,
      "query": "create index concurrently i_r_67 on t_67(i)",
      "calls": 1,
      "total_time": 9.4638,
      "rows": 0,
      "shared_blks_hit": 128,
      "shared_blks_read": 5,
      "shared_blks_dirtied": 2,
      "shared_blks_written": 0,
      "local_blks_hit": 0,
      "local_blks_read": 0,
      "local_blks_dirtied": 0,
      "local_blks_written": 0,
      "temp_blks_read": 0,
      "temp_blks_written": 0,
      "blk_read_time": 0,
      "blk_write_time": 0,
      "queryid": 8824971584930246000,
      "md5": "7711bbbadc4cd32a0908248bc4361a1a"
    },
    "a06a080c19c016631b1b421910022d35": {
      "rownum": 96,
      "query": "create index concurrently i_r_2 on t_2(i)",
      "calls": 1,
      "total_time": 9.379275,
      "rows": 0,
      "shared_blks_hit": 128,
      "shared_blks_read": 5,
      "shared_blks_dirtied": 2,
      "shared_blks_written": 0,
      "local_blks_hit": 0,
      "local_blks_read": 0,
      "local_blks_dirtied": 0,
      "local_blks_written": 0,
      "temp_blks_read": 0,
      "temp_blks_written": 0,
      "blk_read_time": 0,
      "blk_write_time": 0,
      "queryid": -125555379615651230,
      "md5": "a06a080c19c016631b1b421910022d35"
    },
    "faf5e4d4c53056323de881bb1d4d50ca": {
      "rownum": 97,
      "query": "create index concurrently i_r_59 on t_59(i)",
      "calls": 1,
      "total_time": 9.314778,
      "rows": 0,
      "shared_blks_hit": 128,
      "shared_blks_read": 5,
      "shared_blks_dirtied": 2,
      "shared_blks_written": 0,
      "local_blks_hit": 0,
      "local_blks_read": 0,
      "local_blks_dirtied": 0,
      "local_blks_written": 0,
      "temp_blks_read": 0,
      "temp_blks_written": 0,
      "blk_read_time": 0,
      "blk_write_time": 0,
      "queryid": 5085725682536761000,
      "md5": "faf5e4d4c53056323de881bb1d4d50ca"
    },
    "e1dba8a86023d8c252fc6307b9e3c4d5": {
      "rownum": 98,
      "query": "create index concurrently i_u_61 on t_61(i)",
      "calls": 1,
      "total_time": 9.275866,
      "rows": 0,
      "shared_blks_hit": 200,
      "shared_blks_read": 5,
      "shared_blks_dirtied": 2,
      "shared_blks_written": 0,
      "local_blks_hit": 0,
      "local_blks_read": 0,
      "local_blks_dirtied": 0,
      "local_blks_written": 0,
      "temp_blks_read": 0,
      "temp_blks_written": 0,
      "blk_read_time": 0,
      "blk_write_time": 0,
      "queryid": -3280980557046087700,
      "md5": "e1dba8a86023d8c252fc6307b9e3c4d5"
    },
    "bc436b1b13a59d4fc2024d190b9c7c10": {
      "rownum": 99,
      "query": "create index concurrently i_r_47 on t_47(i)",
      "calls": 1,
      "total_time": 9.256083,
      "rows": 0,
      "shared_blks_hit": 128,
      "shared_blks_read": 5,
      "shared_blks_dirtied": 2,
      "shared_blks_written": 0,
      "local_blks_hit": 0,
      "local_blks_read": 0,
      "local_blks_dirtied": 0,
      "local_blks_written": 0,
      "temp_blks_read": 0,
      "temp_blks_written": 0,
      "blk_read_time": 0,
      "blk_write_time": 0,
      "queryid": -574046320413349100,
      "md5": "bc436b1b13a59d4fc2024d190b9c7c10"
    },
    "3f5256d47a92ecf68cb1198fd3bbf1c0": {
      "rownum": 100,
      "query": "create index concurrently i_r_52 on t_52(i)",
      "calls": 1,
      "total_time": 9.166782,
      "rows": 0,
      "shared_blks_hit": 128,
      "shared_blks_read": 5,
      "shared_blks_dirtied": 2,
      "shared_blks_written": 0,
      "local_blks_hit": 0,
      "local_blks_read": 0,
      "local_blks_dirtied": 0,
      "local_blks_written": 0,
      "temp_blks_read": 0,
      "temp_blks_written": 0,
      "blk_read_time": 0,
      "blk_write_time": 0,
      "queryid": 4228969900036353000,
      "md5": "3f5256d47a92ecf68cb1198fd3bbf1c0"
    }
  }
}
