{
  "snapshot_timestamptz": "2019-10-04T13:23:02.596411+00:00",
  "snapshot_timestamptz_s": 1570195382.59641,
  "queries": {
    "5ea24c6fa36fca74368f683ce46db5e0": {
      "rownum": 1,
      "query": "create table t_slw_q as select id::int8 from generate_series(0, 10000000) _(id)",
      "calls": 1,
      "total_time": 31378.302944,
      "rows": 0,
      "shared_blks_hit": 130,
      "shared_blks_read": 44248,
      "shared_blks_dirtied": 44248,
      "shared_blks_written": 42200,
      "local_blks_hit": 0,
      "local_blks_read": 0,
      "local_blks_dirtied": 0,
      "local_blks_written": 0,
      "temp_blks_read": 17090,
      "temp_blks_written": 17090,
      "blk_read_time": 0,
      "blk_write_time": 0,
      "queryid": -837353630728469800,
      "md5": "5ea24c6fa36fca74368f683ce46db5e0"
    },
    "fc89994603784033979249977e304289": {
      "rownum": 2,
      "query": "VACUUM ANALYZE",
      "calls": 1,
      "total_time": 18048.069022,
      "rows": 0,
      "shared_blks_hit": 137967,
      "shared_blks_read": 185632,
      "shared_blks_dirtied": 94174,
      "shared_blks_written": 81417,
      "local_blks_hit": 0,
      "local_blks_read": 0,
      "local_blks_dirtied": 0,
      "local_blks_written": 0,
      "temp_blks_read": 0,
      "temp_blks_written": 0,
      "blk_read_time": 0,
      "blk_write_time": 0,
      "queryid": -4922882474069691000,
      "md5": "fc89994603784033979249977e304289"
    },
    "8af1e5f39b7de7d8eeaffad3d8acd54b": {
      "rownum": 3,
      "query": "update t_rar_q set t_dat=$1 where t_dat between $2 and $3",
      "calls": 9,
      "total_time": 9933.43441,
      "rows": 745515,
      "shared_blks_hit": 1525842,
      "shared_blks_read": 17271,
      "shared_blks_dirtied": 11902,
      "shared_blks_written": 7939,
      "local_blks_hit": 0,
      "local_blks_read": 0,
      "local_blks_dirtied": 0,
      "local_blks_written": 0,
      "temp_blks_read": 0,
      "temp_blks_written": 0,
      "blk_read_time": 0,
      "blk_write_time": 0,
      "queryid": -3222149299978340400,
      "md5": "8af1e5f39b7de7d8eeaffad3d8acd54b"
    },
    "8729d45b34fea2d78356073d4de81396": {
      "rownum": 4,
      "query": "update t_with_bloat set i = i",
      "calls": 1,
      "total_time": 5623.53411,
      "rows": 1000000,
      "shared_blks_hit": 2013284,
      "shared_blks_read": 8851,
      "shared_blks_dirtied": 8850,
      "shared_blks_written": 4526,
      "local_blks_hit": 0,
      "local_blks_read": 0,
      "local_blks_dirtied": 0,
      "local_blks_written": 0,
      "temp_blks_read": 0,
      "temp_blks_written": 0,
      "blk_read_time": 0,
      "blk_write_time": 0,
      "queryid": 4145010178302556700,
      "md5": "8729d45b34fea2d78356073d4de81396"
    },
    "f04600d0b0c9a2d20505d593f69c9b7f": {
      "rownum": 5,
      "query": "VACUUM (ANALYZE)",
      "calls": 1,
      "total_time": 4289.183384,
      "rows": 0,
      "shared_blks_hit": 59538,
      "shared_blks_read": 96841,
      "shared_blks_dirtied": 23684,
      "shared_blks_written": 16215,
      "local_blks_hit": 0,
      "local_blks_read": 0,
      "local_blks_dirtied": 0,
      "local_blks_written": 0,
      "temp_blks_read": 0,
      "temp_blks_written": 0,
      "blk_read_time": 0,
      "blk_write_time": 0,
      "queryid": 613725734663719400,
      "md5": "f04600d0b0c9a2d20505d593f69c9b7f"
    },
    "7035f68c6b282d8119eec6722d1d3abc": {
      "rownum": 6,
      "query": "create index concurrently i_redundant_2 on t_with_redundant_index(i)",
      "calls": 1,
      "total_time": 3205.310543,
      "rows": 0,
      "shared_blks_hit": 3379,
      "shared_blks_read": 6274,
      "shared_blks_dirtied": 2,
      "shared_blks_written": 0,
      "local_blks_hit": 0,
      "local_blks_read": 0,
      "local_blks_dirtied": 0,
      "local_blks_written": 0,
      "temp_blks_read": 2448,
      "temp_blks_written": 1308,
      "blk_read_time": 0,
      "blk_write_time": 0,
      "queryid": 5045454327338548000,
      "md5": "7035f68c6b282d8119eec6722d1d3abc"
    },
    "2708cb9f644092f24be600bdcf8e0e26": {
      "rownum": 7,
      "query": "create table t_with_redundant_idx as select id, id as f1, id as f2, id as f3, id as f4 from generate_series(1, 1000000) _(id)",
      "calls": 1,
      "total_time": 2968.228,
      "rows": 0,
      "shared_blks_hit": 158,
      "shared_blks_read": 6370,
      "shared_blks_dirtied": 6370,
      "shared_blks_written": 4902,
      "local_blks_hit": 0,
      "local_blks_read": 0,
      "local_blks_dirtied": 0,
      "local_blks_written": 0,
      "temp_blks_read": 1709,
      "temp_blks_written": 1709,
      "blk_read_time": 0,
      "blk_write_time": 0,
      "queryid": 2527906257619262000,
      "md5": "2708cb9f644092f24be600bdcf8e0e26"
    },
    "85058944e069d1ab2406dcb7614028c3": {
      "rownum": 8,
      "query": "create table t_with_bloat as select i from generate_series(1, 1000000) _(i)",
      "calls": 1,
      "total_time": 2709.785157,
      "rows": 0,
      "shared_blks_hit": 132,
      "shared_blks_read": 4429,
      "shared_blks_dirtied": 4429,
      "shared_blks_written": 2377,
      "local_blks_hit": 0,
      "local_blks_read": 0,
      "local_blks_dirtied": 0,
      "local_blks_written": 0,
      "temp_blks_read": 1709,
      "temp_blks_written": 1709,
      "blk_read_time": 0,
      "blk_write_time": 0,
      "queryid": -6446764050704029000,
      "md5": "85058944e069d1ab2406dcb7614028c3"
    },
    "7d09632ff93304084401533d8f67aa16": {
      "rownum": 9,
      "query": "create table t_red_fk_1 as select id::int8 from generate_series(0, 1000000) _(id)",
      "calls": 1,
      "total_time": 2660.079653,
      "rows": 0,
      "shared_blks_hit": 132,
      "shared_blks_read": 4425,
      "shared_blks_dirtied": 4425,
      "shared_blks_written": 2377,
      "local_blks_hit": 0,
      "local_blks_read": 0,
      "local_blks_dirtied": 0,
      "local_blks_written": 0,
      "temp_blks_read": 1709,
      "temp_blks_written": 1709,
      "blk_read_time": 0,
      "blk_write_time": 0,
      "queryid": -5601151487238124000,
      "md5": "7d09632ff93304084401533d8f67aa16"
    },
    "9f65379128be4faffee2e84d5762727c": {
      "rownum": 10,
      "query": "delete from t_f004_empty",
      "calls": 1,
      "total_time": 2614.62023,
      "rows": 1000000,
      "shared_blks_hit": 1004425,
      "shared_blks_read": 4425,
      "shared_blks_dirtied": 4425,
      "shared_blks_written": 2605,
      "local_blks_hit": 0,
      "local_blks_read": 0,
      "local_blks_dirtied": 0,
      "local_blks_written": 0,
      "temp_blks_read": 0,
      "temp_blks_written": 0,
      "blk_read_time": 0,
      "blk_write_time": 0,
      "queryid": -8281246975399820000,
      "md5": "9f65379128be4faffee2e84d5762727c"
    },
    "e722b82f5ebb6dbabf7e05bd0004d039": {
      "rownum": 11,
      "query": "create table t_rar_q as select id, (random() * 1000000)::int8 as t_dat from generate_series(1, 1000000) _(id)",
      "calls": 1,
      "total_time": 2449.00348,
      "rows": 0,
      "shared_blks_hit": 197,
      "shared_blks_read": 5407,
      "shared_blks_dirtied": 5425,
      "shared_blks_written": 3358,
      "local_blks_hit": 0,
      "local_blks_read": 0,
      "local_blks_dirtied": 0,
      "local_blks_written": 0,
      "temp_blks_read": 1709,
      "temp_blks_written": 1709,
      "blk_read_time": 0,
      "blk_write_time": 0,
      "queryid": 8726250694613120000,
      "md5": "e722b82f5ebb6dbabf7e05bd0004d039"
    },
    "9496008daf0f193d85061c9f64bde9ab": {
      "rownum": 12,
      "query": "create table t_red_fk_2 as select id, (random() * 1000000)::int8 as r_t1_id from generate_series(1, 1000000) _(id)",
      "calls": 1,
      "total_time": 2318.185925,
      "rows": 0,
      "shared_blks_hit": 138,
      "shared_blks_read": 5406,
      "shared_blks_dirtied": 5406,
      "shared_blks_written": 3358,
      "local_blks_hit": 0,
      "local_blks_read": 0,
      "local_blks_dirtied": 0,
      "local_blks_written": 0,
      "temp_blks_read": 1709,
      "temp_blks_written": 1709,
      "blk_read_time": 0,
      "blk_write_time": 0,
      "queryid": 591824813582986000,
      "md5": "9496008daf0f193d85061c9f64bde9ab"
    },
    "ef0f4334b8f15b0a142c41903e836106": {
      "rownum": 13,
      "query": "create table exp_redundant.t_with_redundant_ref_idx as select i from generate_series(1, 1000000) _(i)",
      "calls": 1,
      "total_time": 2226.662161,
      "rows": 0,
      "shared_blks_hit": 126,
      "shared_blks_read": 4425,
      "shared_blks_dirtied": 4426,
      "shared_blks_written": 2377,
      "local_blks_hit": 0,
      "local_blks_read": 0,
      "local_blks_dirtied": 0,
      "local_blks_written": 0,
      "temp_blks_read": 1709,
      "temp_blks_written": 1709,
      "blk_read_time": 0,
      "blk_write_time": 0,
      "queryid": -1861943955546907400,
      "md5": "ef0f4334b8f15b0a142c41903e836106"
    },
    "3f094705882eaade4441c4dfbc1809b9": {
      "rownum": 14,
      "query": "create table t_with_unused_index as select i from generate_series(1, 1000000) _(i)",
      "calls": 1,
      "total_time": 2156.168519,
      "rows": 0,
      "shared_blks_hit": 126,
      "shared_blks_read": 4425,
      "shared_blks_dirtied": 4425,
      "shared_blks_written": 2377,
      "local_blks_hit": 0,
      "local_blks_read": 0,
      "local_blks_dirtied": 0,
      "local_blks_written": 0,
      "temp_blks_read": 1709,
      "temp_blks_written": 1709,
      "blk_read_time": 0,
      "blk_write_time": 0,
      "queryid": -678916242629262500,
      "md5": "3f094705882eaade4441c4dfbc1809b9"
    },
    "32f5ef2ab3cfc8ba05d96229f852c456": {
      "rownum": 15,
      "query": "create table t_with_redundant_index as select i from generate_series(1, 1000000) _(i)",
      "calls": 1,
      "total_time": 2146.927671,
      "rows": 0,
      "shared_blks_hit": 128,
      "shared_blks_read": 4425,
      "shared_blks_dirtied": 4427,
      "shared_blks_written": 2377,
      "local_blks_hit": 0,
      "local_blks_read": 0,
      "local_blks_dirtied": 0,
      "local_blks_written": 0,
      "temp_blks_read": 1709,
      "temp_blks_written": 1709,
      "blk_read_time": 0,
      "blk_write_time": 0,
      "queryid": -5095830603244401000,
      "md5": "32f5ef2ab3cfc8ba05d96229f852c456"
    },
    "d16ce3233d3d18f9e990387d5892ee22": {
      "rownum": 16,
      "query": "create table public.t_with_redundant_ref_idx as select i from generate_series(1, 1000000) _(i)",
      "calls": 1,
      "total_time": 2146.078811,
      "rows": 0,
      "shared_blks_hit": 124,
      "shared_blks_read": 4425,
      "shared_blks_dirtied": 4425,
      "shared_blks_written": 2377,
      "local_blks_hit": 0,
      "local_blks_read": 0,
      "local_blks_dirtied": 0,
      "local_blks_written": 0,
      "temp_blks_read": 1709,
      "temp_blks_written": 1709,
      "blk_read_time": 0,
      "blk_write_time": 0,
      "queryid": 4227063200314075600,
      "md5": "d16ce3233d3d18f9e990387d5892ee22"
    },
    "8bd7f2c2ba1ee035dd61d0040f578590": {
      "rownum": 17,
      "query": "create table test_schema.t_with_invalid_index as select i from generate_series(1, 1000000) _(i)",
      "calls": 1,
      "total_time": 2145.740159,
      "rows": 0,
      "shared_blks_hit": 130,
      "shared_blks_read": 4425,
      "shared_blks_dirtied": 4432,
      "shared_blks_written": 2377,
      "local_blks_hit": 0,
      "local_blks_read": 0,
      "local_blks_dirtied": 0,
      "local_blks_written": 0,
      "temp_blks_read": 1709,
      "temp_blks_written": 1709,
      "blk_read_time": 0,
      "blk_write_time": 0,
      "queryid": 5156236148593934000,
      "md5": "8bd7f2c2ba1ee035dd61d0040f578590"
    },
    "c41489b5562148d492ec5f291993b5ee": {
      "rownum": 18,
      "query": "create table t_f004_empty as select i from generate_series(1, 1000000) _(i)",
      "calls": 1,
      "total_time": 1922.076916,
      "rows": 0,
      "shared_blks_hit": 128,
      "shared_blks_read": 4429,
      "shared_blks_dirtied": 4429,
      "shared_blks_written": 2377,
      "local_blks_hit": 0,
      "local_blks_read": 0,
      "local_blks_dirtied": 0,
      "local_blks_written": 0,
      "temp_blks_read": 1709,
      "temp_blks_written": 1709,
      "blk_read_time": 0,
      "blk_write_time": 0,
      "queryid": -3498952347021279,
      "md5": "c41489b5562148d492ec5f291993b5ee"
    },
    "41649b5376672435db270b265abd719b": {
      "rownum": 19,
      "query": "create index r_red_fk_2_fk_idx on t_red_fk_2(r_t1_id)",
      "calls": 1,
      "total_time": 1586.193017,
      "rows": 0,
      "shared_blks_hit": 1084,
      "shared_blks_read": 1923,
      "shared_blks_dirtied": 0,
      "shared_blks_written": 0,
      "local_blks_hit": 0,
      "local_blks_read": 0,
      "local_blks_dirtied": 0,
      "local_blks_written": 0,
      "temp_blks_read": 2448,
      "temp_blks_written": 1320,
      "blk_read_time": 0,
      "blk_write_time": 0,
      "queryid": -2801630118753177600,
      "md5": "41649b5376672435db270b265abd719b"
    },
    "10ea71b17cbe4e8574737f13d9aa74a7": {
      "rownum": 20,
      "query": "create index concurrently t_with_redundant_idx_f1_f2 on t_with_redundant_idx(f1,f2)",
      "calls": 1,
      "total_time": 1365.352509,
      "rows": 0,
      "shared_blks_hit": 3933,
      "shared_blks_read": 8670,
      "shared_blks_dirtied": 2,
      "shared_blks_written": 0,
      "local_blks_hit": 0,
      "local_blks_read": 0,
      "local_blks_dirtied": 0,
      "local_blks_written": 0,
      "temp_blks_read": 2448,
      "temp_blks_written": 1283,
      "blk_read_time": 0,
      "blk_write_time": 0,
      "queryid": -8920212056722243000,
      "md5": "10ea71b17cbe4e8574737f13d9aa74a7"
    },
    "eb413a8ade520c34aa6278929cd8b8d0": {
      "rownum": 21,
      "query": "create index concurrently i_redundant_1 on t_with_redundant_index(i)",
      "calls": 1,
      "total_time": 1264.045013,
      "rows": 0,
      "shared_blks_hit": 3288,
      "shared_blks_read": 6329,
      "shared_blks_dirtied": 1273,
      "shared_blks_written": 1239,
      "local_blks_hit": 0,
      "local_blks_read": 0,
      "local_blks_dirtied": 0,
      "local_blks_written": 0,
      "temp_blks_read": 2448,
      "temp_blks_written": 1277,
      "blk_read_time": 0,
      "blk_write_time": 0,
      "queryid": 566438153080519400,
      "md5": "eb413a8ade520c34aa6278929cd8b8d0"
    },
    "1657dd3ac6a8396cda288ccf95b3e93e": {
      "rownum": 22,
      "query": "create index concurrently t_with_redundant_idx_f3_1 on t_with_redundant_idx(f3)",
      "calls": 1,
      "total_time": 1213.236472,
      "rows": 0,
      "shared_blks_hit": 3704,
      "shared_blks_read": 8869,
      "shared_blks_dirtied": 2,
      "shared_blks_written": 1,
      "local_blks_hit": 0,
      "local_blks_read": 0,
      "local_blks_dirtied": 0,
      "local_blks_written": 0,
      "temp_blks_read": 2448,
      "temp_blks_written": 1283,
      "blk_read_time": 0,
      "blk_write_time": 0,
      "queryid": -7990293000632035000,
      "md5": "1657dd3ac6a8396cda288ccf95b3e93e"
    },
    "1e7bc5cce40a35c4730e436ea664a3f9": {
      "rownum": 23,
      "query": "create index concurrently t_with_redundant_idx_f1_2 on t_with_redundant_idx(f1)",
      "calls": 1,
      "total_time": 1190.443383,
      "rows": 0,
      "shared_blks_hit": 3752,
      "shared_blks_read": 8818,
      "shared_blks_dirtied": 2,
      "shared_blks_written": 981,
      "local_blks_hit": 0,
      "local_blks_read": 0,
      "local_blks_dirtied": 0,
      "local_blks_written": 0,
      "temp_blks_read": 2448,
      "temp_blks_written": 1283,
      "blk_read_time": 0,
      "blk_write_time": 0,
      "queryid": 879148290678321700,
      "md5": "1e7bc5cce40a35c4730e436ea664a3f9"
    },
    "df3e7ad51d29398d30aebde32df0d71d": {
      "rownum": 24,
      "query": "create index concurrently t_with_redundant_idx_f2 on t_with_redundant_idx(f2)",
      "calls": 1,
      "total_time": 1186.649779,
      "rows": 0,
      "shared_blks_hit": 3636,
      "shared_blks_read": 8934,
      "shared_blks_dirtied": 2,
      "shared_blks_written": 356,
      "local_blks_hit": 0,
      "local_blks_read": 0,
      "local_blks_dirtied": 0,
      "local_blks_written": 0,
      "temp_blks_read": 2448,
      "temp_blks_written": 1283,
      "blk_read_time": 0,
      "blk_write_time": 0,
      "queryid": 1902759977384827000,
      "md5": "df3e7ad51d29398d30aebde32df0d71d"
    },
    "76531a1eb8e34ee84b9f6f32762a30e1": {
      "rownum": 25,
      "query": "create index concurrently i_unused on t_with_unused_index(i)",
      "calls": 1,
      "total_time": 1168.451847,
      "rows": 0,
      "shared_blks_hit": 3277,
      "shared_blks_read": 6341,
      "shared_blks_dirtied": 1282,
      "shared_blks_written": 1245,
      "local_blks_hit": 0,
      "local_blks_read": 0,
      "local_blks_dirtied": 0,
      "local_blks_written": 0,
      "temp_blks_read": 2448,
      "temp_blks_written": 1271,
      "blk_read_time": 0,
      "blk_write_time": 0,
      "queryid": -6612128672608002000,
      "md5": "76531a1eb8e34ee84b9f6f32762a30e1"
    },
    "179dd95fcd8662bf4e071266e75a8377": {
      "rownum": 26,
      "query": "create index concurrently t_with_redundant_idx_id on t_with_redundant_idx(id)",
      "calls": 1,
      "total_time": 1160.213446,
      "rows": 0,
      "shared_blks_hit": 3384,
      "shared_blks_read": 9271,
      "shared_blks_dirtied": 2,
      "shared_blks_written": 726,
      "local_blks_hit": 0,
      "local_blks_read": 0,
      "local_blks_dirtied": 0,
      "local_blks_written": 0,
      "temp_blks_read": 2448,
      "temp_blks_written": 1312,
      "blk_read_time": 0,
      "blk_write_time": 0,
      "queryid": 5967467509848557000,
      "md5": "179dd95fcd8662bf4e071266e75a8377"
    },
    "479aad6eb92a27d10c03fb12a793614e": {
      "rownum": 27,
      "query": "create index concurrently t_with_redundant_idx_f1 on t_with_redundant_idx(f1)",
      "calls": 1,
      "total_time": 1159.783566,
      "rows": 0,
      "shared_blks_hit": 3626,
      "shared_blks_read": 8944,
      "shared_blks_dirtied": 2,
      "shared_blks_written": 0,
      "local_blks_hit": 0,
      "local_blks_read": 0,
      "local_blks_dirtied": 0,
      "local_blks_written": 0,
      "temp_blks_read": 2448,
      "temp_blks_written": 1283,
      "blk_read_time": 0,
      "blk_write_time": 0,
      "queryid": -7862275411983427000,
      "md5": "479aad6eb92a27d10c03fb12a793614e"
    },
    "5f8e51e07770412b1911cebb26c55f4b": {
      "rownum": 28,
      "query": "create index t_with_redundant_ref_idx_1 on public.t_with_redundant_ref_idx using btree (i)",
      "calls": 1,
      "total_time": 1156.849202,
      "rows": 0,
      "shared_blks_hit": 1161,
      "shared_blks_read": 1250,
      "shared_blks_dirtied": 1251,
      "shared_blks_written": 1217,
      "local_blks_hit": 0,
      "local_blks_read": 0,
      "local_blks_dirtied": 0,
      "local_blks_written": 0,
      "temp_blks_read": 2448,
      "temp_blks_written": 1283,
      "blk_read_time": 0,
      "blk_write_time": 0,
      "queryid": 7121640066867289000,
      "md5": "5f8e51e07770412b1911cebb26c55f4b"
    },
    "62992e0ccb57f6bdfda778c7c473e8ad": {
      "rownum": 29,
      "query": "create index t_with_redundant_ref_idx_1 on exp_redundant.t_with_redundant_ref_idx using btree (i)",
      "calls": 1,
      "total_time": 1153.122039,
      "rows": 0,
      "shared_blks_hit": 1058,
      "shared_blks_read": 1292,
      "shared_blks_dirtied": 1306,
      "shared_blks_written": 1258,
      "local_blks_hit": 0,
      "local_blks_read": 0,
      "local_blks_dirtied": 0,
      "local_blks_written": 0,
      "temp_blks_read": 2448,
      "temp_blks_written": 1249,
      "blk_read_time": 0,
      "blk_write_time": 0,
      "queryid": -395938069363296600,
      "md5": "62992e0ccb57f6bdfda778c7c473e8ad"
    },
    "95f449a74e628c4e8d47ae2af9b2fd43": {
      "rownum": 30,
      "query": "create index r_red_fk_1_id_idx on t_red_fk_1(id)",
      "calls": 1,
      "total_time": 1141.833017,
      "rows": 0,
      "shared_blks_hit": 1215,
      "shared_blks_read": 1192,
      "shared_blks_dirtied": 0,
      "shared_blks_written": 0,
      "local_blks_hit": 0,
      "local_blks_read": 0,
      "local_blks_dirtied": 0,
      "local_blks_written": 0,
      "temp_blks_read": 2448,
      "temp_blks_written": 1283,
      "blk_read_time": 0,
      "blk_write_time": 0,
      "queryid": 3040282640922053000,
      "md5": "95f449a74e628c4e8d47ae2af9b2fd43"
    },
    "287d9693318affc139279ec76e414f24": {
      "rownum": 31,
      "query": "create index concurrently t_with_redundant_idx_f3_2 on t_with_redundant_idx(f3)",
      "calls": 1,
      "total_time": 1138.124459,
      "rows": 0,
      "shared_blks_hit": 3850,
      "shared_blks_read": 8720,
      "shared_blks_dirtied": 2,
      "shared_blks_written": 0,
      "local_blks_hit": 0,
      "local_blks_read": 0,
      "local_blks_dirtied": 0,
      "local_blks_written": 0,
      "temp_blks_read": 2448,
      "temp_blks_written": 1283,
      "blk_read_time": 0,
      "blk_write_time": 0,
      "queryid": 8565802378619238000,
      "md5": "287d9693318affc139279ec76e414f24"
    },
    "cbcd92704dd802d204b9bc7ee8b39187": {
      "rownum": 32,
      "query": "create index t_rar_q_idx on t_rar_q(id)",
      "calls": 1,
      "total_time": 1118.965541,
      "rows": 0,
      "shared_blks_hit": 1154,
      "shared_blks_read": 1749,
      "shared_blks_dirtied": 1745,
      "shared_blks_written": 1709,
      "local_blks_hit": 0,
      "local_blks_read": 0,
      "local_blks_dirtied": 0,
      "local_blks_written": 0,
      "temp_blks_read": 2448,
      "temp_blks_written": 1256,
      "blk_read_time": 0,
      "blk_write_time": 0,
      "queryid": 2650688778442027500,
      "md5": "cbcd92704dd802d204b9bc7ee8b39187"
    },
    "c8703f324c1fb37854d9a2c6edbaa6a2": {
      "rownum": 33,
      "query": "create index r_red_fk_1_X_idx on t_red_fk_1(id)",
      "calls": 1,
      "total_time": 1097.624871,
      "rows": 0,
      "shared_blks_hit": 1163,
      "shared_blks_read": 1201,
      "shared_blks_dirtied": 0,
      "shared_blks_written": 0,
      "local_blks_hit": 0,
      "local_blks_read": 0,
      "local_blks_dirtied": 0,
      "local_blks_written": 0,
      "temp_blks_read": 2448,
      "temp_blks_written": 1264,
      "blk_read_time": 0,
      "blk_write_time": 0,
      "queryid": 3969450259942249000,
      "md5": "c8703f324c1fb37854d9a2c6edbaa6a2"
    },
    "6bc4ef68211b4d4714588b1314c3b450": {
      "rownum": 34,
      "query": "create index t_with_redundant_ref_idx_3 on public.t_with_redundant_ref_idx using btree (i)",
      "calls": 1,
      "total_time": 1076.563557,
      "rows": 0,
      "shared_blks_hit": 1146,
      "shared_blks_read": 1252,
      "shared_blks_dirtied": 0,
      "shared_blks_written": 0,
      "local_blks_hit": 0,
      "local_blks_read": 0,
      "local_blks_dirtied": 0,
      "local_blks_written": 0,
      "temp_blks_read": 2448,
      "temp_blks_written": 1283,
      "blk_read_time": 0,
      "blk_write_time": 0,
      "queryid": 39141847517093180,
      "md5": "6bc4ef68211b4d4714588b1314c3b450"
    },
    "7d1bf9b05e76b943c47b50b366c65772": {
      "rownum": 35,
      "query": "create index t_with_redundant_ref_idx_3 on exp_redundant.t_with_redundant_ref_idx using btree (i)",
      "calls": 1,
      "total_time": 1074.346534,
      "rows": 0,
      "shared_blks_hit": 1136,
      "shared_blks_read": 1262,
      "shared_blks_dirtied": 0,
      "shared_blks_written": 0,
      "local_blks_hit": 0,
      "local_blks_read": 0,
      "local_blks_dirtied": 0,
      "local_blks_written": 0,
      "temp_blks_read": 2448,
      "temp_blks_written": 1283,
      "blk_read_time": 0,
      "blk_write_time": 0,
      "queryid": -1845904424067371800,
      "md5": "7d1bf9b05e76b943c47b50b366c65772"
    },
    "3ebee924ec35c0d73b9480782463f72e": {
      "rownum": 36,
      "query": "create unique index t_with_redundant_idx_f1_uniq on t_with_redundant_idx (f1)",
      "calls": 1,
      "total_time": 1063.739021,
      "rows": 0,
      "shared_blks_hit": 1215,
      "shared_blks_read": 2216,
      "shared_blks_dirtied": 3,
      "shared_blks_written": 0,
      "local_blks_hit": 0,
      "local_blks_read": 0,
      "local_blks_dirtied": 0,
      "local_blks_written": 0,
      "temp_blks_read": 2449,
      "temp_blks_written": 1284,
      "blk_read_time": 0,
      "blk_write_time": 0,
      "queryid": 1566471017150549200,
      "md5": "3ebee924ec35c0d73b9480782463f72e"
    },
    "7e370d36c2447380a7d5678a0b2040d7": {
      "rownum": 37,
      "query": "create index t_with_redundant_ref_idx_2 on exp_redundant.t_with_redundant_ref_idx using btree (i)",
      "calls": 1,
      "total_time": 1049.818841,
      "rows": 0,
      "shared_blks_hit": 1059,
      "shared_blks_read": 1585,
      "shared_blks_dirtied": 0,
      "shared_blks_written": 0,
      "local_blks_hit": 0,
      "local_blks_read": 0,
      "local_blks_dirtied": 0,
      "local_blks_written": 0,
      "temp_blks_read": 2448,
      "temp_blks_written": 1416,
      "blk_read_time": 0,
      "blk_write_time": 0,
      "queryid": -94268938950487040,
      "md5": "7e370d36c2447380a7d5678a0b2040d7"
    },
    "d2b42fdb3e69ab37ae920aa6154580d5": {
      "rownum": 38,
      "query": "alter table t_red_fk_1 add primary key (id)",
      "calls": 1,
      "total_time": 957.982492,
      "rows": 0,
      "shared_blks_hit": 3221,
      "shared_blks_read": 3649,
      "shared_blks_dirtied": 2383,
      "shared_blks_written": 2345,
      "local_blks_hit": 0,
      "local_blks_read": 0,
      "local_blks_dirtied": 0,
      "local_blks_written": 0,
      "temp_blks_read": 2449,
      "temp_blks_written": 1273,
      "blk_read_time": 0,
      "blk_write_time": 0,
      "queryid": 7202543407834562000,
      "md5": "d2b42fdb3e69ab37ae920aa6154580d5"
    },
    "59e32b402631edd68f57233d02a6ff1c": {
      "rownum": 39,
      "query": "alter table t_with_redundant_idx add primary key (id)",
      "calls": 1,
      "total_time": 936.319791,
      "rows": 0,
      "shared_blks_hit": 3207,
      "shared_blks_read": 6660,
      "shared_blks_dirtied": 4329,
      "shared_blks_written": 4290,
      "local_blks_hit": 0,
      "local_blks_read": 0,
      "local_blks_dirtied": 0,
      "local_blks_written": 0,
      "temp_blks_read": 2449,
      "temp_blks_written": 1279,
      "blk_read_time": 0,
      "blk_write_time": 0,
      "queryid": 3416651331628416000,
      "md5": "59e32b402631edd68f57233d02a6ff1c"
    },
    "63ed402d488d71cb2ac691b882743cad": {
      "rownum": 40,
      "query": "alter table t_red_fk_2 add constraint fk_red_fk2_t1 foreign key (r_t1_id) references t_red_fk_1(id)",
      "calls": 1,
      "total_time": 929.592101,
      "rows": 0,
      "shared_blks_hit": 4600,
      "shared_blks_read": 5533,
      "shared_blks_dirtied": 3366,
      "shared_blks_written": 3326,
      "local_blks_hit": 0,
      "local_blks_read": 0,
      "local_blks_dirtied": 0,
      "local_blks_written": 0,
      "temp_blks_read": 0,
      "temp_blks_written": 0,
      "blk_read_time": 0,
      "blk_write_time": 0,
      "queryid": 2911641097746118700,
      "md5": "63ed402d488d71cb2ac691b882743cad"
    },
    "cdfd61b4586420038e5e614ab85aeeae": {
      "rownum": 41,
      "query": "create index t_with_redundant_ref_idx_2 on public.t_with_redundant_ref_idx using btree (i)",
      "calls": 1,
      "total_time": 868.680928,
      "rows": 0,
      "shared_blks_hit": 1156,
      "shared_blks_read": 1208,
      "shared_blks_dirtied": 0,
      "shared_blks_written": 0,
      "local_blks_hit": 0,
      "local_blks_read": 0,
      "local_blks_dirtied": 0,
      "local_blks_written": 0,
      "temp_blks_read": 2448,
      "temp_blks_written": 1261,
      "blk_read_time": 0,
      "blk_write_time": 0,
      "queryid": -3115028882787390000,
      "md5": "cdfd61b4586420038e5e614ab85aeeae"
    },
    "4acc373047981b2e725d2ee88f314170": {
      "rownum": 42,
      "query": "select count(*) from t_slw_q",
      "calls": 1,
      "total_time": 685.633711,
      "rows": 1,
      "shared_blks_hit": 0,
      "shared_blks_read": 44248,
      "shared_blks_dirtied": 0,
      "shared_blks_written": 0,
      "local_blks_hit": 0,
      "local_blks_read": 0,
      "local_blks_dirtied": 0,
      "local_blks_written": 0,
      "temp_blks_read": 0,
      "temp_blks_written": 0,
      "blk_read_time": 0,
      "blk_write_time": 0,
      "queryid": -3604241719388670000,
      "md5": "4acc373047981b2e725d2ee88f314170"
    },
    "6d85f5ed15e4a22c77379c8c27e4a096": {
      "rownum": 43,
      "query": "create database checkup_test_db",
      "calls": 1,
      "total_time": 625.53054,
      "rows": 0,
      "shared_blks_hit": 61,
      "shared_blks_read": 4,
      "shared_blks_dirtied": 6,
      "shared_blks_written": 0,
      "local_blks_hit": 0,
      "local_blks_read": 0,
      "local_blks_dirtied": 0,
      "local_blks_written": 0,
      "temp_blks_read": 0,
      "temp_blks_written": 0,
      "blk_read_time": 0,
      "blk_write_time": 0,
      "queryid": -2133351059478393300,
      "md5": "6d85f5ed15e4a22c77379c8c27e4a096"
    },
    "182ba4f0ffb554baf311c8fa6800939f": {
      "rownum": 44,
      "query": "create database dbname",
      "calls": 1,
      "total_time": 621.166386,
      "rows": 0,
      "shared_blks_hit": 50,
      "shared_blks_read": 9,
      "shared_blks_dirtied": 3,
      "shared_blks_written": 0,
      "local_blks_hit": 0,
      "local_blks_read": 0,
      "local_blks_dirtied": 0,
      "local_blks_written": 0,
      "temp_blks_read": 0,
      "temp_blks_written": 0,
      "blk_read_time": 0,
      "blk_write_time": 0,
      "queryid": 3617698589948080000,
      "md5": "182ba4f0ffb554baf311c8fa6800939f"
    },
    "6aa3e30a0e616b58a3e395fdfe1210ba": {
      "rownum": 45,
      "query": "analyze t_f004_empty",
      "calls": 2,
      "total_time": 122.328886,
      "rows": 0,
      "shared_blks_hit": 6488,
      "shared_blks_read": 2419,
      "shared_blks_dirtied": 2413,
      "shared_blks_written": 2378,
      "local_blks_hit": 0,
      "local_blks_read": 0,
      "local_blks_dirtied": 0,
      "local_blks_written": 0,
      "temp_blks_read": 0,
      "temp_blks_written": 0,
      "blk_read_time": 0,
      "blk_write_time": 0,
      "queryid": -5293816547023798000,
      "md5": "6aa3e30a0e616b58a3e395fdfe1210ba"
    },
    "d02d1aef973dfdb7a87f56b6b6dfea91": {
      "rownum": 46,
      "query": "create table bloated as select i from generate_series(1, 100000) _(i)",
      "calls": 1,
      "total_time": 64.587942,
      "rows": 0,
      "shared_blks_hit": 126,
      "shared_blks_read": 443,
      "shared_blks_dirtied": 444,
      "shared_blks_written": 0,
      "local_blks_hit": 0,
      "local_blks_read": 0,
      "local_blks_dirtied": 0,
      "local_blks_written": 0,
      "temp_blks_read": 171,
      "temp_blks_written": 171,
      "blk_read_time": 0,
      "blk_write_time": 0,
      "queryid": -2951921325210440700,
      "md5": "d02d1aef973dfdb7a87f56b6b6dfea91"
    },
    "23bbd085bb37c5fafcd10ade38dfacf7": {
      "rownum": 47,
      "query": "create index i_bloated on bloated(i)",
      "calls": 1,
      "total_time": 38.935008,
      "rows": 0,
      "shared_blks_hit": 534,
      "shared_blks_read": 0,
      "shared_blks_dirtied": 0,
      "shared_blks_written": 0,
      "local_blks_hit": 0,
      "local_blks_read": 0,
      "local_blks_dirtied": 0,
      "local_blks_written": 0,
      "temp_blks_read": 0,
      "temp_blks_written": 0,
      "blk_read_time": 0,
      "blk_write_time": 0,
      "queryid": 8841083458873351000,
      "md5": "23bbd085bb37c5fafcd10ade38dfacf7"
    },
    "ab7d8f0edf844d85869cd324de44e515": {
      "rownum": 48,
      "query": "delete from bloated where i % $1 = $2",
      "calls": 1,
      "total_time": 29.91418,
      "rows": 50000,
      "shared_blks_hit": 50443,
      "shared_blks_read": 0,
      "shared_blks_dirtied": 0,
      "shared_blks_written": 0,
      "local_blks_hit": 0,
      "local_blks_read": 0,
      "local_blks_dirtied": 0,
      "local_blks_written": 0,
      "temp_blks_read": 0,
      "temp_blks_written": 0,
      "blk_read_time": 0,
      "blk_write_time": 0,
      "queryid": -3076169388096589300,
      "md5": "ab7d8f0edf844d85869cd324de44e515"
    },
    "b7d373c8db27e676fdfdc77dc47b08a0": {
      "rownum": 49,
      "query": "CREATE TABLE test_schema.orders\n(\n id serial,\n cnt integer,\n CONSTRAINT orders_pk PRIMARY KEY (id)\n)",
      "calls": 1,
      "total_time": 19.663942,
      "rows": 0,
      "shared_blks_hit": 464,
      "shared_blks_read": 31,
      "shared_blks_dirtied": 48,
      "shared_blks_written": 0,
      "local_blks_hit": 0,
      "local_blks_read": 0,
      "local_blks_dirtied": 0,
      "local_blks_written": 0,
      "temp_blks_read": 0,
      "temp_blks_written": 0,
      "blk_read_time": 0,
      "blk_write_time": 0,
      "queryid": -1491185255100233500,
      "md5": "b7d373c8db27e676fdfdc77dc47b08a0"
    },
    "04c04f974feb16a092143f1db522dcdd": {
      "rownum": 50,
      "query": "create index concurrently i_u_36 on t_36(i)",
      "calls": 1,
      "total_time": 17.567181,
      "rows": 0,
      "shared_blks_hit": 201,
      "shared_blks_read": 7,
      "shared_blks_dirtied": 4,
      "shared_blks_written": 0,
      "local_blks_hit": 0,
      "local_blks_read": 0,
      "local_blks_dirtied": 0,
      "local_blks_written": 0,
      "temp_blks_read": 0,
      "temp_blks_written": 0,
      "blk_read_time": 0,
      "blk_write_time": 0,
      "queryid": 7820838637134668000,
      "md5": "04c04f974feb16a092143f1db522dcdd"
    },
    "b56c0bbcdd112624648ef48f216f3e92": {
      "rownum": 51,
      "query": "alter system set random_page_cost = 2.22",
      "calls": 1,
      "total_time": 15.109658,
      "rows": 0,
      "shared_blks_hit": 0,
      "shared_blks_read": 0,
      "shared_blks_dirtied": 0,
      "shared_blks_written": 0,
      "local_blks_hit": 0,
      "local_blks_read": 0,
      "local_blks_dirtied": 0,
      "local_blks_written": 0,
      "temp_blks_read": 0,
      "temp_blks_written": 0,
      "blk_read_time": 0,
      "blk_write_time": 0,
      "queryid": 1881993450838449000,
      "md5": "b56c0bbcdd112624648ef48f216f3e92"
    },
    "a9e7f554158a28bbac8fddfabab3b59f": {
      "rownum": 52,
      "query": "create table t_27 as select i from generate_series(1, 1000) _(i)",
      "calls": 1,
      "total_time": 8.568664,
      "rows": 0,
      "shared_blks_hit": 232,
      "shared_blks_read": 8,
      "shared_blks_dirtied": 8,
      "shared_blks_written": 0,
      "local_blks_hit": 0,
      "local_blks_read": 0,
      "local_blks_dirtied": 0,
      "local_blks_written": 0,
      "temp_blks_read": 0,
      "temp_blks_written": 0,
      "blk_read_time": 0,
      "blk_write_time": 0,
      "queryid": 2660756427945084400,
      "md5": "a9e7f554158a28bbac8fddfabab3b59f"
    },
    "43e9adb569a681a982ad22290f73fcf2": {
      "rownum": 53,
      "query": "select pg_reload_conf()",
      "calls": 1,
      "total_time": 8.162951,
      "rows": 1,
      "shared_blks_hit": 0,
      "shared_blks_read": 0,
      "shared_blks_dirtied": 0,
      "shared_blks_written": 0,
      "local_blks_hit": 0,
      "local_blks_read": 0,
      "local_blks_dirtied": 0,
      "local_blks_written": 0,
      "temp_blks_read": 0,
      "temp_blks_written": 0,
      "blk_read_time": 0,
      "blk_write_time": 0,
      "queryid": -6290564462188021000,
      "md5": "43e9adb569a681a982ad22290f73fcf2"
    },
    "734762bee8278fb48b3f3983a5eae884": {
      "rownum": 54,
      "query": "create extension if not exists pg_stat_kcache",
      "calls": 1,
      "total_time": 6.278192,
      "rows": 0,
      "shared_blks_hit": 1413,
      "shared_blks_read": 67,
      "shared_blks_dirtied": 21,
      "shared_blks_written": 0,
      "local_blks_hit": 0,
      "local_blks_read": 0,
      "local_blks_dirtied": 0,
      "local_blks_written": 0,
      "temp_blks_read": 0,
      "temp_blks_written": 0,
      "blk_read_time": 0,
      "blk_write_time": 0,
      "queryid": 2571546517107304400,
      "md5": "734762bee8278fb48b3f3983a5eae884"
    },
    "4a39616c48d4e9ef96f99ae0021866db": {
      "rownum": 55,
      "query": "create index concurrently i_u_86 on t_86(i)",
      "calls": 1,
      "total_time": 4.979357,
      "rows": 0,
      "shared_blks_hit": 200,
      "shared_blks_read": 5,
      "shared_blks_dirtied": 2,
      "shared_blks_written": 0,
      "local_blks_hit": 0,
      "local_blks_read": 0,
      "local_blks_dirtied": 0,
      "local_blks_written": 0,
      "temp_blks_read": 0,
      "temp_blks_written": 0,
      "blk_read_time": 0,
      "blk_write_time": 0,
      "queryid": -1053132768723272000,
      "md5": "4a39616c48d4e9ef96f99ae0021866db"
    },
    "8751b42f7348ebb91b0eb1108ae12026": {
      "rownum": 56,
      "query": "create index concurrently i_u_22 on t_22(i)",
      "calls": 1,
      "total_time": 4.977235,
      "rows": 0,
      "shared_blks_hit": 200,
      "shared_blks_read": 5,
      "shared_blks_dirtied": 2,
      "shared_blks_written": 0,
      "local_blks_hit": 0,
      "local_blks_read": 0,
      "local_blks_dirtied": 0,
      "local_blks_written": 0,
      "temp_blks_read": 0,
      "temp_blks_written": 0,
      "blk_read_time": 0,
      "blk_write_time": 0,
      "queryid": -8138552098508099000,
      "md5": "8751b42f7348ebb91b0eb1108ae12026"
    },
    "8ccb59c5221adf4c48ce3ddb3557a91d": {
      "rownum": 57,
      "query": "create index concurrently i_u_89 on t_89(i)",
      "calls": 1,
      "total_time": 4.943278,
      "rows": 0,
      "shared_blks_hit": 200,
      "shared_blks_read": 5,
      "shared_blks_dirtied": 2,
      "shared_blks_written": 0,
      "local_blks_hit": 0,
      "local_blks_read": 0,
      "local_blks_dirtied": 0,
      "local_blks_written": 0,
      "temp_blks_read": 0,
      "temp_blks_written": 0,
      "blk_read_time": 0,
      "blk_write_time": 0,
      "queryid": -6362236483748202000,
      "md5": "8ccb59c5221adf4c48ce3ddb3557a91d"
    },
    "607420b7ab000cbfecd67b661a26d750": {
      "rownum": 58,
      "query": "create index concurrently i_u_64 on t_64(i)",
      "calls": 1,
      "total_time": 4.920236,
      "rows": 0,
      "shared_blks_hit": 200,
      "shared_blks_read": 5,
      "shared_blks_dirtied": 2,
      "shared_blks_written": 0,
      "local_blks_hit": 0,
      "local_blks_read": 0,
      "local_blks_dirtied": 0,
      "local_blks_written": 0,
      "temp_blks_read": 0,
      "temp_blks_written": 0,
      "blk_read_time": 0,
      "blk_write_time": 0,
      "queryid": 177860461183167600,
      "md5": "607420b7ab000cbfecd67b661a26d750"
    },
    "818252bc4de136a03e0f3c8d641e8cda": {
      "rownum": 59,
      "query": "create index concurrently i_u_1 on t_1(i)",
      "calls": 1,
      "total_time": 4.853571,
      "rows": 0,
      "shared_blks_hit": 198,
      "shared_blks_read": 9,
      "shared_blks_dirtied": 2,
      "shared_blks_written": 0,
      "local_blks_hit": 0,
      "local_blks_read": 0,
      "local_blks_dirtied": 0,
      "local_blks_written": 0,
      "temp_blks_read": 0,
      "temp_blks_written": 0,
      "blk_read_time": 0,
      "blk_write_time": 0,
      "queryid": 8045454930243187000,
      "md5": "818252bc4de136a03e0f3c8d641e8cda"
    },
    "ff68c2d52ff52cf5a1df23f0176ea83d": {
      "rownum": 60,
      "query": "create index concurrently i_u_70 on t_70(i)",
      "calls": 1,
      "total_time": 4.820896,
      "rows": 0,
      "shared_blks_hit": 200,
      "shared_blks_read": 5,
      "shared_blks_dirtied": 2,
      "shared_blks_written": 0,
      "local_blks_hit": 0,
      "local_blks_read": 0,
      "local_blks_dirtied": 0,
      "local_blks_written": 0,
      "temp_blks_read": 0,
      "temp_blks_written": 0,
      "blk_read_time": 0,
      "blk_write_time": 0,
      "queryid": 3694177823672669000,
      "md5": "ff68c2d52ff52cf5a1df23f0176ea83d"
    },
    "60577f89851a7e823dddf932c7b9a772": {
      "rownum": 61,
      "query": "create index concurrently i_u_73 on t_73(i)",
      "calls": 1,
      "total_time": 4.801518,
      "rows": 0,
      "shared_blks_hit": 200,
      "shared_blks_read": 5,
      "shared_blks_dirtied": 2,
      "shared_blks_written": 0,
      "local_blks_hit": 0,
      "local_blks_read": 0,
      "local_blks_dirtied": 0,
      "local_blks_written": 0,
      "temp_blks_read": 0,
      "temp_blks_written": 0,
      "blk_read_time": 0,
      "blk_write_time": 0,
      "queryid": 5482691881180305000,
      "md5": "60577f89851a7e823dddf932c7b9a772"
    },
    "1bb72296d32b0705644fc00154cb9bfc": {
      "rownum": 62,
      "query": "create index concurrently i_u_97 on t_97(i)",
      "calls": 1,
      "total_time": 4.755955,
      "rows": 0,
      "shared_blks_hit": 200,
      "shared_blks_read": 5,
      "shared_blks_dirtied": 2,
      "shared_blks_written": 0,
      "local_blks_hit": 0,
      "local_blks_read": 0,
      "local_blks_dirtied": 0,
      "local_blks_written": 0,
      "temp_blks_read": 0,
      "temp_blks_written": 0,
      "blk_read_time": 0,
      "blk_write_time": 0,
      "queryid": -1547472426000537000,
      "md5": "1bb72296d32b0705644fc00154cb9bfc"
    },
    "69f13564a6e86497ffe11a95494eb4d2": {
      "rownum": 63,
      "query": "create index concurrently i_u_68 on t_68(i)",
      "calls": 1,
      "total_time": 4.734767,
      "rows": 0,
      "shared_blks_hit": 200,
      "shared_blks_read": 5,
      "shared_blks_dirtied": 2,
      "shared_blks_written": 0,
      "local_blks_hit": 0,
      "local_blks_read": 0,
      "local_blks_dirtied": 0,
      "local_blks_written": 0,
      "temp_blks_read": 0,
      "temp_blks_written": 0,
      "blk_read_time": 0,
      "blk_write_time": 0,
      "queryid": 3856153419129616000,
      "md5": "69f13564a6e86497ffe11a95494eb4d2"
    },
    "3d99ebb0f08e4e30c4d0fac3925c186a": {
      "rownum": 64,
      "query": "create index concurrently i_u_15 on t_15(i)",
      "calls": 1,
      "total_time": 4.719608,
      "rows": 0,
      "shared_blks_hit": 200,
      "shared_blks_read": 5,
      "shared_blks_dirtied": 2,
      "shared_blks_written": 0,
      "local_blks_hit": 0,
      "local_blks_read": 0,
      "local_blks_dirtied": 0,
      "local_blks_written": 0,
      "temp_blks_read": 0,
      "temp_blks_written": 0,
      "blk_read_time": 0,
      "blk_write_time": 0,
      "queryid": -4814288640910277000,
      "md5": "3d99ebb0f08e4e30c4d0fac3925c186a"
    },
    "78dfb4af65e83f32278169c52886aa24": {
      "rownum": 65,
      "query": "create index concurrently i_u_6 on t_6(i)",
      "calls": 1,
      "total_time": 4.707455,
      "rows": 0,
      "shared_blks_hit": 202,
      "shared_blks_read": 5,
      "shared_blks_dirtied": 2,
      "shared_blks_written": 0,
      "local_blks_hit": 0,
      "local_blks_read": 0,
      "local_blks_dirtied": 0,
      "local_blks_written": 0,
      "temp_blks_read": 0,
      "temp_blks_written": 0,
      "blk_read_time": 0,
      "blk_write_time": 0,
      "queryid": 6636228606930650000,
      "md5": "78dfb4af65e83f32278169c52886aa24"
    },
    "2c0c1350e2adba9638f3a7f7bbfecb56": {
      "rownum": 66,
      "query": "create index concurrently i_u_62 on t_62(i)",
      "calls": 1,
      "total_time": 4.699021,
      "rows": 0,
      "shared_blks_hit": 200,
      "shared_blks_read": 5,
      "shared_blks_dirtied": 2,
      "shared_blks_written": 0,
      "local_blks_hit": 0,
      "local_blks_read": 0,
      "local_blks_dirtied": 0,
      "local_blks_written": 0,
      "temp_blks_read": 0,
      "temp_blks_written": 0,
      "blk_read_time": 0,
      "blk_write_time": 0,
      "queryid": 6282300036154518000,
      "md5": "2c0c1350e2adba9638f3a7f7bbfecb56"
    },
    "9c44381ca6dd5986c0063fcdd2adcc9d": {
      "rownum": 67,
      "query": "create index concurrently i_u_13 on t_13(i)",
      "calls": 1,
      "total_time": 4.690052,
      "rows": 0,
      "shared_blks_hit": 201,
      "shared_blks_read": 6,
      "shared_blks_dirtied": 4,
      "shared_blks_written": 0,
      "local_blks_hit": 0,
      "local_blks_read": 0,
      "local_blks_dirtied": 0,
      "local_blks_written": 0,
      "temp_blks_read": 0,
      "temp_blks_written": 0,
      "blk_read_time": 0,
      "blk_write_time": 0,
      "queryid": 2109411843385159400,
      "md5": "9c44381ca6dd5986c0063fcdd2adcc9d"
    },
    "86f2d2662d0f02178c4d27178b84e28a": {
      "rownum": 68,
      "query": "create index concurrently i_u_46 on t_46(i)",
      "calls": 1,
      "total_time": 4.667584,
      "rows": 0,
      "shared_blks_hit": 201,
      "shared_blks_read": 7,
      "shared_blks_dirtied": 5,
      "shared_blks_written": 0,
      "local_blks_hit": 0,
      "local_blks_read": 0,
      "local_blks_dirtied": 0,
      "local_blks_written": 0,
      "temp_blks_read": 0,
      "temp_blks_written": 0,
      "blk_read_time": 0,
      "blk_write_time": 0,
      "queryid": 5347103578192611000,
      "md5": "86f2d2662d0f02178c4d27178b84e28a"
    },
    "b919a36eae8f0a98c94770db91953cf1": {
      "rownum": 69,
      "query": "create index concurrently i_u_23 on t_23(i)",
      "calls": 1,
      "total_time": 4.655766,
      "rows": 0,
      "shared_blks_hit": 200,
      "shared_blks_read": 5,
      "shared_blks_dirtied": 2,
      "shared_blks_written": 0,
      "local_blks_hit": 0,
      "local_blks_read": 0,
      "local_blks_dirtied": 0,
      "local_blks_written": 0,
      "temp_blks_read": 0,
      "temp_blks_written": 0,
      "blk_read_time": 0,
      "blk_write_time": 0,
      "queryid": 2142545078770753000,
      "md5": "b919a36eae8f0a98c94770db91953cf1"
    },
    "c8407bc7219ce0ed65148ba3aae31793": {
      "rownum": 70,
      "query": "create index concurrently i_u_12 on t_12(i)",
      "calls": 1,
      "total_time": 4.637873,
      "rows": 0,
      "shared_blks_hit": 200,
      "shared_blks_read": 5,
      "shared_blks_dirtied": 2,
      "shared_blks_written": 0,
      "local_blks_hit": 0,
      "local_blks_read": 0,
      "local_blks_dirtied": 0,
      "local_blks_written": 0,
      "temp_blks_read": 0,
      "temp_blks_written": 0,
      "blk_read_time": 0,
      "blk_write_time": 0,
      "queryid": -2315564220582489000,
      "md5": "c8407bc7219ce0ed65148ba3aae31793"
    },
    "b881554b6a21856a7175b6a2ca9707e0": {
      "rownum": 71,
      "query": "create index concurrently i_u_41 on t_41(i)",
      "calls": 1,
      "total_time": 4.633386,
      "rows": 0,
      "shared_blks_hit": 200,
      "shared_blks_read": 5,
      "shared_blks_dirtied": 2,
      "shared_blks_written": 0,
      "local_blks_hit": 0,
      "local_blks_read": 0,
      "local_blks_dirtied": 0,
      "local_blks_written": 0,
      "temp_blks_read": 0,
      "temp_blks_written": 0,
      "blk_read_time": 0,
      "blk_write_time": 0,
      "queryid": -8638876604929383000,
      "md5": "b881554b6a21856a7175b6a2ca9707e0"
    },
    "268b8b11852dc1d4f8737d447745457f": {
      "rownum": 72,
      "query": "create index concurrently i_u_69 on t_69(i)",
      "calls": 1,
      "total_time": 4.632239,
      "rows": 0,
      "shared_blks_hit": 200,
      "shared_blks_read": 5,
      "shared_blks_dirtied": 2,
      "shared_blks_written": 0,
      "local_blks_hit": 0,
      "local_blks_read": 0,
      "local_blks_dirtied": 0,
      "local_blks_written": 0,
      "temp_blks_read": 0,
      "temp_blks_written": 0,
      "blk_read_time": 0,
      "blk_write_time": 0,
      "queryid": -2417487707257360400,
      "md5": "268b8b11852dc1d4f8737d447745457f"
    },
    "d1aa370375231a28b1bf87b87d275518": {
      "rownum": 73,
      "query": "create index concurrently i_u_51 on t_51(i)",
      "calls": 1,
      "total_time": 4.615648,
      "rows": 0,
      "shared_blks_hit": 200,
      "shared_blks_read": 5,
      "shared_blks_dirtied": 2,
      "shared_blks_written": 0,
      "local_blks_hit": 0,
      "local_blks_read": 0,
      "local_blks_dirtied": 0,
      "local_blks_written": 0,
      "temp_blks_read": 0,
      "temp_blks_written": 0,
      "blk_read_time": 0,
      "blk_write_time": 0,
      "queryid": -9109055381621161000,
      "md5": "d1aa370375231a28b1bf87b87d275518"
    },
    "b8c08ec60e7a41f9adb481c3ac8604dc": {
      "rownum": 74,
      "query": "create index concurrently i_r_25 on t_25(i)",
      "calls": 1,
      "total_time": 4.566867,
      "rows": 0,
      "shared_blks_hit": 128,
      "shared_blks_read": 5,
      "shared_blks_dirtied": 2,
      "shared_blks_written": 0,
      "local_blks_hit": 0,
      "local_blks_read": 0,
      "local_blks_dirtied": 0,
      "local_blks_written": 0,
      "temp_blks_read": 0,
      "temp_blks_written": 0,
      "blk_read_time": 0,
      "blk_write_time": 0,
      "queryid": -5174086021994938000,
      "md5": "b8c08ec60e7a41f9adb481c3ac8604dc"
    },
    "be98f16c74082a7d3572ce77b0b61703": {
      "rownum": 75,
      "query": "create index concurrently i_u_31 on t_31(i)",
      "calls": 1,
      "total_time": 4.565941,
      "rows": 0,
      "shared_blks_hit": 200,
      "shared_blks_read": 5,
      "shared_blks_dirtied": 2,
      "shared_blks_written": 0,
      "local_blks_hit": 0,
      "local_blks_read": 0,
      "local_blks_dirtied": 0,
      "local_blks_written": 0,
      "temp_blks_read": 0,
      "temp_blks_written": 0,
      "blk_read_time": 0,
      "blk_write_time": 0,
      "queryid": 3944725477671802400,
      "md5": "be98f16c74082a7d3572ce77b0b61703"
    },
    "3c9550312851ca5e4224ca3a5ab30781": {
      "rownum": 76,
      "query": "create index concurrently i_u_24 on t_24(i)",
      "calls": 1,
      "total_time": 4.560153,
      "rows": 0,
      "shared_blks_hit": 200,
      "shared_blks_read": 5,
      "shared_blks_dirtied": 2,
      "shared_blks_written": 0,
      "local_blks_hit": 0,
      "local_blks_read": 0,
      "local_blks_dirtied": 0,
      "local_blks_written": 0,
      "temp_blks_read": 0,
      "temp_blks_written": 0,
      "blk_read_time": 0,
      "blk_write_time": 0,
      "queryid": -6090390826024436000,
      "md5": "3c9550312851ca5e4224ca3a5ab30781"
    },
    "888b92abb0a2dd2ad03fa2b1dea20444": {
      "rownum": 77,
      "query": "create index concurrently i_u_27 on t_27(i)",
      "calls": 1,
      "total_time": 4.558835,
      "rows": 0,
      "shared_blks_hit": 200,
      "shared_blks_read": 5,
      "shared_blks_dirtied": 2,
      "shared_blks_written": 0,
      "local_blks_hit": 0,
      "local_blks_read": 0,
      "local_blks_dirtied": 0,
      "local_blks_written": 0,
      "temp_blks_read": 0,
      "temp_blks_written": 0,
      "blk_read_time": 0,
      "blk_write_time": 0,
      "queryid": 2355117878904613400,
      "md5": "888b92abb0a2dd2ad03fa2b1dea20444"
    },
    "1d17cb23ed3f89bb04e36bf688f5b562": {
      "rownum": 78,
      "query": "create index concurrently i_u_102 on t_102(i)",
      "calls": 1,
      "total_time": 4.556425,
      "rows": 0,
      "shared_blks_hit": 200,
      "shared_blks_read": 5,
      "shared_blks_dirtied": 2,
      "shared_blks_written": 0,
      "local_blks_hit": 0,
      "local_blks_read": 0,
      "local_blks_dirtied": 0,
      "local_blks_written": 0,
      "temp_blks_read": 0,
      "temp_blks_written": 0,
      "blk_read_time": 0,
      "blk_write_time": 0,
      "queryid": -5710846019281592000,
      "md5": "1d17cb23ed3f89bb04e36bf688f5b562"
    },
    "eabc82a0ec9ae7e287269167c797b89b": {
      "rownum": 79,
      "query": "create index concurrently i_u_75 on t_75(i)",
      "calls": 1,
      "total_time": 4.546634,
      "rows": 0,
      "shared_blks_hit": 200,
      "shared_blks_read": 5,
      "shared_blks_dirtied": 2,
      "shared_blks_written": 0,
      "local_blks_hit": 0,
      "local_blks_read": 0,
      "local_blks_dirtied": 0,
      "local_blks_written": 0,
      "temp_blks_read": 0,
      "temp_blks_written": 0,
      "blk_read_time": 0,
      "blk_write_time": 0,
      "queryid": -6829298630711561000,
      "md5": "eabc82a0ec9ae7e287269167c797b89b"
    },
    "8265c4f09eeb112c689c1601be9f146c": {
      "rownum": 80,
      "query": "create index concurrently i_u_26 on t_26(i)",
      "calls": 1,
      "total_time": 4.537799,
      "rows": 0,
      "shared_blks_hit": 200,
      "shared_blks_read": 5,
      "shared_blks_dirtied": 2,
      "shared_blks_written": 0,
      "local_blks_hit": 0,
      "local_blks_read": 0,
      "local_blks_dirtied": 0,
      "local_blks_written": 0,
      "temp_blks_read": 0,
      "temp_blks_written": 0,
      "blk_read_time": 0,
      "blk_write_time": 0,
      "queryid": -473895448742837800,
      "md5": "8265c4f09eeb112c689c1601be9f146c"
    },
    "2e1706424ae2c505e875fe6751c3ca70": {
      "rownum": 81,
      "query": "create index concurrently i_u_101 on t_101(i)",
      "calls": 1,
      "total_time": 4.535467,
      "rows": 0,
      "shared_blks_hit": 200,
      "shared_blks_read": 5,
      "shared_blks_dirtied": 2,
      "shared_blks_written": 0,
      "local_blks_hit": 0,
      "local_blks_read": 0,
      "local_blks_dirtied": 0,
      "local_blks_written": 0,
      "temp_blks_read": 0,
      "temp_blks_written": 0,
      "blk_read_time": 0,
      "blk_write_time": 0,
      "queryid": 3961073174282794000,
      "md5": "2e1706424ae2c505e875fe6751c3ca70"
    },
    "fed0e4499a9729c3b78cd109db1b7d9b": {
      "rownum": 82,
      "query": "create index concurrently i_u_66 on t_66(i)",
      "calls": 1,
      "total_time": 4.526101,
      "rows": 0,
      "shared_blks_hit": 200,
      "shared_blks_read": 5,
      "shared_blks_dirtied": 2,
      "shared_blks_written": 0,
      "local_blks_hit": 0,
      "local_blks_read": 0,
      "local_blks_dirtied": 0,
      "local_blks_written": 0,
      "temp_blks_read": 0,
      "temp_blks_written": 0,
      "blk_read_time": 0,
      "blk_write_time": 0,
      "queryid": -8619781519737684000,
      "md5": "fed0e4499a9729c3b78cd109db1b7d9b"
    },
    "fd36d197223bfa1f11b5de9850ef504d": {
      "rownum": 83,
      "query": "create index concurrently i_u_19 on t_19(i)",
      "calls": 1,
      "total_time": 4.51763,
      "rows": 0,
      "shared_blks_hit": 200,
      "shared_blks_read": 5,
      "shared_blks_dirtied": 2,
      "shared_blks_written": 0,
      "local_blks_hit": 0,
      "local_blks_read": 0,
      "local_blks_dirtied": 0,
      "local_blks_written": 0,
      "temp_blks_read": 0,
      "temp_blks_written": 0,
      "blk_read_time": 0,
      "blk_write_time": 0,
      "queryid": -4370099307141729000,
      "md5": "fd36d197223bfa1f11b5de9850ef504d"
    },
    "e40aa4827ead39f6deb5d2f5dd0f42f7": {
      "rownum": 84,
      "query": "create index concurrently i_u_85 on t_85(i)",
      "calls": 1,
      "total_time": 4.499637,
      "rows": 0,
      "shared_blks_hit": 200,
      "shared_blks_read": 5,
      "shared_blks_dirtied": 2,
      "shared_blks_written": 0,
      "local_blks_hit": 0,
      "local_blks_read": 0,
      "local_blks_dirtied": 0,
      "local_blks_written": 0,
      "temp_blks_read": 0,
      "temp_blks_written": 0,
      "blk_read_time": 0,
      "blk_write_time": 0,
      "queryid": -6813202730317392000,
      "md5": "e40aa4827ead39f6deb5d2f5dd0f42f7"
    },
    "5f942db4e9893ea20712fe3383e566fb": {
      "rownum": 85,
      "query": "create index concurrently i_u_38 on t_38(i)",
      "calls": 1,
      "total_time": 4.486805,
      "rows": 0,
      "shared_blks_hit": 200,
      "shared_blks_read": 5,
      "shared_blks_dirtied": 2,
      "shared_blks_written": 0,
      "local_blks_hit": 0,
      "local_blks_read": 0,
      "local_blks_dirtied": 0,
      "local_blks_written": 0,
      "temp_blks_read": 0,
      "temp_blks_written": 0,
      "blk_read_time": 0,
      "blk_write_time": 0,
      "queryid": -1286408037136076500,
      "md5": "5f942db4e9893ea20712fe3383e566fb"
    },
    "97767aa87aa69c5c7b59a8f3c0b2fb3e": {
      "rownum": 86,
      "query": "create index concurrently i_u_81 on t_81(i)",
      "calls": 1,
      "total_time": 4.483603,
      "rows": 0,
      "shared_blks_hit": 202,
      "shared_blks_read": 6,
      "shared_blks_dirtied": 3,
      "shared_blks_written": 0,
      "local_blks_hit": 0,
      "local_blks_read": 0,
      "local_blks_dirtied": 0,
      "local_blks_written": 0,
      "temp_blks_read": 0,
      "temp_blks_written": 0,
      "blk_read_time": 0,
      "blk_write_time": 0,
      "queryid": -538611708982877250,
      "md5": "97767aa87aa69c5c7b59a8f3c0b2fb3e"
    },
    "d7ad511435a8074f8204e0a5fc752fb5": {
      "rownum": 87,
      "query": "create index concurrently i_u_57 on t_57(i)",
      "calls": 1,
      "total_time": 4.479752,
      "rows": 0,
      "shared_blks_hit": 200,
      "shared_blks_read": 5,
      "shared_blks_dirtied": 2,
      "shared_blks_written": 0,
      "local_blks_hit": 0,
      "local_blks_read": 0,
      "local_blks_dirtied": 0,
      "local_blks_written": 0,
      "temp_blks_read": 0,
      "temp_blks_written": 0,
      "blk_read_time": 0,
      "blk_write_time": 0,
      "queryid": -6679962080422574000,
      "md5": "d7ad511435a8074f8204e0a5fc752fb5"
    },
    "5966557e5d4ef69508069b0fbf99b1c8": {
      "rownum": 88,
      "query": "create index concurrently i_u_103 on t_103(i)",
      "calls": 1,
      "total_time": 4.479406,
      "rows": 0,
      "shared_blks_hit": 200,
      "shared_blks_read": 5,
      "shared_blks_dirtied": 2,
      "shared_blks_written": 0,
      "local_blks_hit": 0,
      "local_blks_read": 0,
      "local_blks_dirtied": 0,
      "local_blks_written": 0,
      "temp_blks_read": 0,
      "temp_blks_written": 0,
      "blk_read_time": 0,
      "blk_write_time": 0,
      "queryid": -1618134738108633900,
      "md5": "5966557e5d4ef69508069b0fbf99b1c8"
    },
    "2ed2b006905a49fbffa106a9d7b3a69a": {
      "rownum": 89,
      "query": "create index concurrently i_u_105 on t_105(i)",
      "calls": 1,
      "total_time": 4.479127,
      "rows": 0,
      "shared_blks_hit": 200,
      "shared_blks_read": 5,
      "shared_blks_dirtied": 2,
      "shared_blks_written": 0,
      "local_blks_hit": 0,
      "local_blks_read": 0,
      "local_blks_dirtied": 0,
      "local_blks_written": 0,
      "temp_blks_read": 0,
      "temp_blks_written": 0,
      "blk_read_time": 0,
      "blk_write_time": 0,
      "queryid": -4387101759094203000,
      "md5": "2ed2b006905a49fbffa106a9d7b3a69a"
    },
    "aa086b8abbfeee586db5726913843173": {
      "rownum": 90,
      "query": "create index concurrently i_u_74 on t_74(i)",
      "calls": 1,
      "total_time": 4.474322,
      "rows": 0,
      "shared_blks_hit": 200,
      "shared_blks_read": 5,
      "shared_blks_dirtied": 2,
      "shared_blks_written": 0,
      "local_blks_hit": 0,
      "local_blks_read": 0,
      "local_blks_dirtied": 0,
      "local_blks_written": 0,
      "temp_blks_read": 0,
      "temp_blks_written": 0,
      "blk_read_time": 0,
      "blk_write_time": 0,
      "queryid": 3821899459888144000,
      "md5": "aa086b8abbfeee586db5726913843173"
    },
    "dd04a37bb539f70a80da4c8db2b3f8d5": {
      "rownum": 91,
      "query": "create index concurrently i_u_17 on t_17(i)",
      "calls": 1,
      "total_time": 4.469173,
      "rows": 0,
      "shared_blks_hit": 200,
      "shared_blks_read": 5,
      "shared_blks_dirtied": 2,
      "shared_blks_written": 0,
      "local_blks_hit": 0,
      "local_blks_read": 0,
      "local_blks_dirtied": 0,
      "local_blks_written": 0,
      "temp_blks_read": 0,
      "temp_blks_written": 0,
      "blk_read_time": 0,
      "blk_write_time": 0,
      "queryid": -9210096558086614000,
      "md5": "dd04a37bb539f70a80da4c8db2b3f8d5"
    },
    "eaa202496fbbe510012c2230129cbb45": {
      "rownum": 92,
      "query": "create index concurrently i_u_48 on t_48(i)",
      "calls": 1,
      "total_time": 4.443789,
      "rows": 0,
      "shared_blks_hit": 201,
      "shared_blks_read": 5,
      "shared_blks_dirtied": 2,
      "shared_blks_written": 0,
      "local_blks_hit": 0,
      "local_blks_read": 0,
      "local_blks_dirtied": 0,
      "local_blks_written": 0,
      "temp_blks_read": 0,
      "temp_blks_written": 0,
      "blk_read_time": 0,
      "blk_write_time": 0,
      "queryid": -5371677106063814000,
      "md5": "eaa202496fbbe510012c2230129cbb45"
    },
    "d8100704c95aee7b2cd43745d5623728": {
      "rownum": 93,
      "query": "create index concurrently i_u_88 on t_88(i)",
      "calls": 1,
      "total_time": 4.43459,
      "rows": 0,
      "shared_blks_hit": 200,
      "shared_blks_read": 5,
      "shared_blks_dirtied": 2,
      "shared_blks_written": 0,
      "local_blks_hit": 0,
      "local_blks_read": 0,
      "local_blks_dirtied": 0,
      "local_blks_written": 0,
      "temp_blks_read": 0,
      "temp_blks_written": 0,
      "blk_read_time": 0,
      "blk_write_time": 0,
      "queryid": 7072348099606454000,
      "md5": "d8100704c95aee7b2cd43745d5623728"
    },
    "13ef04937e522ba8a9d3cc24345b55f7": {
      "rownum": 94,
      "query": "create index concurrently i_u_78 on t_78(i)",
      "calls": 1,
      "total_time": 4.434457,
      "rows": 0,
      "shared_blks_hit": 200,
      "shared_blks_read": 5,
      "shared_blks_dirtied": 2,
      "shared_blks_written": 0,
      "local_blks_hit": 0,
      "local_blks_read": 0,
      "local_blks_dirtied": 0,
      "local_blks_written": 0,
      "temp_blks_read": 0,
      "temp_blks_written": 0,
      "blk_read_time": 0,
      "blk_write_time": 0,
      "queryid": -395470359289702340,
      "md5": "13ef04937e522ba8a9d3cc24345b55f7"
    },
    "e14db728617b9a4a821317eabad381d0": {
      "rownum": 95,
      "query": "create index concurrently i_u_54 on t_54(i)",
      "calls": 1,
      "total_time": 4.431286,
      "rows": 0,
      "shared_blks_hit": 202,
      "shared_blks_read": 6,
      "shared_blks_dirtied": 3,
      "shared_blks_written": 0,
      "local_blks_hit": 0,
      "local_blks_read": 0,
      "local_blks_dirtied": 0,
      "local_blks_written": 0,
      "temp_blks_read": 0,
      "temp_blks_written": 0,
      "blk_read_time": 0,
      "blk_write_time": 0,
      "queryid": -8689212092523305000,
      "md5": "e14db728617b9a4a821317eabad381d0"
    },
    "bd781b985e95b2f95ed2b653acb2a7fa": {
      "rownum": 96,
      "query": "create index concurrently i_u_32 on t_32(i)",
      "calls": 1,
      "total_time": 4.430134,
      "rows": 0,
      "shared_blks_hit": 200,
      "shared_blks_read": 5,
      "shared_blks_dirtied": 2,
      "shared_blks_written": 0,
      "local_blks_hit": 0,
      "local_blks_read": 0,
      "local_blks_dirtied": 0,
      "local_blks_written": 0,
      "temp_blks_read": 0,
      "temp_blks_written": 0,
      "blk_read_time": 0,
      "blk_write_time": 0,
      "queryid": -1758551660026658600,
      "md5": "bd781b985e95b2f95ed2b653acb2a7fa"
    },
    "832dfdec23b0cc6188738046c75da919": {
      "rownum": 97,
      "query": "create index concurrently i_u_8 on t_8(i)",
      "calls": 1,
      "total_time": 4.42896,
      "rows": 0,
      "shared_blks_hit": 202,
      "shared_blks_read": 5,
      "shared_blks_dirtied": 2,
      "shared_blks_written": 0,
      "local_blks_hit": 0,
      "local_blks_read": 0,
      "local_blks_dirtied": 0,
      "local_blks_written": 0,
      "temp_blks_read": 0,
      "temp_blks_written": 0,
      "blk_read_time": 0,
      "blk_write_time": 0,
      "queryid": 3666704987953131000,
      "md5": "832dfdec23b0cc6188738046c75da919"
    },
    "65a6c2403f3ea0fc83e8b98500318ebc": {
      "rownum": 98,
      "query": "create extension if not exists pg_stat_statements",
      "calls": 1,
      "total_time": 4.400939,
      "rows": 0,
      "shared_blks_hit": 687,
      "shared_blks_read": 140,
      "shared_blks_dirtied": 50,
      "shared_blks_written": 0,
      "local_blks_hit": 0,
      "local_blks_read": 0,
      "local_blks_dirtied": 0,
      "local_blks_written": 0,
      "temp_blks_read": 0,
      "temp_blks_written": 0,
      "blk_read_time": 0,
      "blk_write_time": 0,
      "queryid": -5169817456611317000,
      "md5": "65a6c2403f3ea0fc83e8b98500318ebc"
    },
    "e1dba8a86023d8c252fc6307b9e3c4d5": {
      "rownum": 99,
      "query": "create index concurrently i_u_61 on t_61(i)",
      "calls": 1,
      "total_time": 4.398778,
      "rows": 0,
      "shared_blks_hit": 200,
      "shared_blks_read": 5,
      "shared_blks_dirtied": 2,
      "shared_blks_written": 0,
      "local_blks_hit": 0,
      "local_blks_read": 0,
      "local_blks_dirtied": 0,
      "local_blks_written": 0,
      "temp_blks_read": 0,
      "temp_blks_written": 0,
      "blk_read_time": 0,
      "blk_write_time": 0,
      "queryid": -3280980557046087700,
      "md5": "e1dba8a86023d8c252fc6307b9e3c4d5"
    },
    "efb369d7e68290bc9b6c404975148fa8": {
      "rownum": 100,
      "query": "create index concurrently i_u_45 on t_45(i)",
      "calls": 1,
      "total_time": 4.388426,
      "rows": 0,
      "shared_blks_hit": 200,
      "shared_blks_read": 5,
      "shared_blks_dirtied": 2,
      "shared_blks_written": 0,
      "local_blks_hit": 0,
      "local_blks_read": 0,
      "local_blks_dirtied": 0,
      "local_blks_written": 0,
      "temp_blks_read": 0,
      "temp_blks_written": 0,
      "blk_read_time": 0,
      "blk_write_time": 0,
      "queryid": 2993078089717746700,
      "md5": "efb369d7e68290bc9b6c404975148fa8"
    }
  }
}
