{
  "snapshot_timestamptz": "2019-10-03T08:18:21.061462+00:00",
  "snapshot_timestamptz_s": 1570090701.06146,
  "queries": {
    "5ea24c6fa36fca74368f683ce46db5e0": {
      "rownum": 1,
      "query": "create table t_slw_q as select id::int8 from generate_series(0, 10000000) _(id)",
      "calls": 1,
      "total_time": 32457.66424,
      "rows": 0,
      "shared_blks_hit": 130,
      "shared_blks_read": 44248,
      "shared_blks_dirtied": 44248,
      "shared_blks_written": 42200,
      "local_blks_hit": 0,
      "local_blks_read": 0,
      "local_blks_dirtied": 0,
      "local_blks_written": 0,
      "temp_blks_read": 17090,
      "temp_blks_written": 17090,
      "blk_read_time": 0,
      "blk_write_time": 0,
      "queryid": -837353630728469800,
      "md5": "5ea24c6fa36fca74368f683ce46db5e0"
    },
    "fc89994603784033979249977e304289": {
      "rownum": 2,
      "query": "VACUUM ANALYZE",
      "calls": 1,
      "total_time": 21662.221067,
      "rows": 0,
      "shared_blks_hit": 137959,
      "shared_blks_read": 185640,
      "shared_blks_dirtied": 94045,
      "shared_blks_written": 81420,
      "local_blks_hit": 0,
      "local_blks_read": 0,
      "local_blks_dirtied": 0,
      "local_blks_written": 0,
      "temp_blks_read": 0,
      "temp_blks_written": 0,
      "blk_read_time": 0,
      "blk_write_time": 0,
      "queryid": -4922882474069691000,
      "md5": "fc89994603784033979249977e304289"
    },
    "f04600d0b0c9a2d20505d593f69c9b7f": {
      "rownum": 3,
      "query": "VACUUM (ANALYZE)",
      "calls": 1,
      "total_time": 7349.532098,
      "rows": 0,
      "shared_blks_hit": 57352,
      "shared_blks_read": 94858,
      "shared_blks_dirtied": 21303,
      "shared_blks_written": 13961,
      "local_blks_hit": 0,
      "local_blks_read": 0,
      "local_blks_dirtied": 0,
      "local_blks_written": 0,
      "temp_blks_read": 0,
      "temp_blks_written": 0,
      "blk_read_time": 0,
      "blk_write_time": 0,
      "queryid": 613725734663719400,
      "md5": "f04600d0b0c9a2d20505d593f69c9b7f"
    },
    "8af1e5f39b7de7d8eeaffad3d8acd54b": {
      "rownum": 4,
      "query": "update t_rar_q set t_dat=$1 where t_dat between $2 and $3",
      "calls": 9,
      "total_time": 6307.381941,
      "rows": 744959,
      "shared_blks_hit": 1523127,
      "shared_blks_read": 17331,
      "shared_blks_dirtied": 11962,
      "shared_blks_written": 8923,
      "local_blks_hit": 0,
      "local_blks_read": 0,
      "local_blks_dirtied": 0,
      "local_blks_written": 0,
      "temp_blks_read": 0,
      "temp_blks_written": 0,
      "blk_read_time": 0,
      "blk_write_time": 0,
      "queryid": -3222149299978340400,
      "md5": "8af1e5f39b7de7d8eeaffad3d8acd54b"
    },
    "7d09632ff93304084401533d8f67aa16": {
      "rownum": 5,
      "query": "create table t_red_fk_1 as select id::int8 from generate_series(0, 1000000) _(id)",
      "calls": 1,
      "total_time": 5607.822922,
      "rows": 0,
      "shared_blks_hit": 132,
      "shared_blks_read": 4425,
      "shared_blks_dirtied": 4425,
      "shared_blks_written": 2377,
      "local_blks_hit": 0,
      "local_blks_read": 0,
      "local_blks_dirtied": 0,
      "local_blks_written": 0,
      "temp_blks_read": 1709,
      "temp_blks_written": 1709,
      "blk_read_time": 0,
      "blk_write_time": 0,
      "queryid": -5601151487238124000,
      "md5": "7d09632ff93304084401533d8f67aa16"
    },
    "8729d45b34fea2d78356073d4de81396": {
      "rownum": 6,
      "query": "update t_with_bloat set i = i",
      "calls": 1,
      "total_time": 5546.229265,
      "rows": 1000000,
      "shared_blks_hit": 2013284,
      "shared_blks_read": 8851,
      "shared_blks_dirtied": 8850,
      "shared_blks_written": 4275,
      "local_blks_hit": 0,
      "local_blks_read": 0,
      "local_blks_dirtied": 0,
      "local_blks_written": 0,
      "temp_blks_read": 0,
      "temp_blks_written": 0,
      "blk_read_time": 0,
      "blk_write_time": 0,
      "queryid": 4145010178302556700,
      "md5": "8729d45b34fea2d78356073d4de81396"
    },
    "7035f68c6b282d8119eec6722d1d3abc": {
      "rownum": 7,
      "query": "create index concurrently i_redundant_2 on t_with_redundant_index(i)",
      "calls": 1,
      "total_time": 3245.296113,
      "rows": 0,
      "shared_blks_hit": 3357,
      "shared_blks_read": 6251,
      "shared_blks_dirtied": 2,
      "shared_blks_written": 0,
      "local_blks_hit": 0,
      "local_blks_read": 0,
      "local_blks_dirtied": 0,
      "local_blks_written": 0,
      "temp_blks_read": 2448,
      "temp_blks_written": 1283,
      "blk_read_time": 0,
      "blk_write_time": 0,
      "queryid": 5045454327338548000,
      "md5": "7035f68c6b282d8119eec6722d1d3abc"
    },
    "9f65379128be4faffee2e84d5762727c": {
      "rownum": 8,
      "query": "delete from t_f004_empty",
      "calls": 1,
      "total_time": 3142.704013,
      "rows": 1000000,
      "shared_blks_hit": 1004425,
      "shared_blks_read": 4425,
      "shared_blks_dirtied": 4425,
      "shared_blks_written": 2264,
      "local_blks_hit": 0,
      "local_blks_read": 0,
      "local_blks_dirtied": 0,
      "local_blks_written": 0,
      "temp_blks_read": 0,
      "temp_blks_written": 0,
      "blk_read_time": 0,
      "blk_write_time": 0,
      "queryid": -8281246975399820000,
      "md5": "9f65379128be4faffee2e84d5762727c"
    },
    "2708cb9f644092f24be600bdcf8e0e26": {
      "rownum": 9,
      "query": "create table t_with_redundant_idx as select id, id as f1, id as f2, id as f3, id as f4 from generate_series(1, 1000000) _(id)",
      "calls": 1,
      "total_time": 3129.485216,
      "rows": 0,
      "shared_blks_hit": 158,
      "shared_blks_read": 6370,
      "shared_blks_dirtied": 6370,
      "shared_blks_written": 4903,
      "local_blks_hit": 0,
      "local_blks_read": 0,
      "local_blks_dirtied": 0,
      "local_blks_written": 0,
      "temp_blks_read": 1709,
      "temp_blks_written": 1709,
      "blk_read_time": 0,
      "blk_write_time": 0,
      "queryid": 2527906257619262000,
      "md5": "2708cb9f644092f24be600bdcf8e0e26"
    },
    "85058944e069d1ab2406dcb7614028c3": {
      "rownum": 10,
      "query": "create table t_with_bloat as select i from generate_series(1, 1000000) _(i)",
      "calls": 1,
      "total_time": 2926.680528,
      "rows": 0,
      "shared_blks_hit": 132,
      "shared_blks_read": 4429,
      "shared_blks_dirtied": 4429,
      "shared_blks_written": 2377,
      "local_blks_hit": 0,
      "local_blks_read": 0,
      "local_blks_dirtied": 0,
      "local_blks_written": 0,
      "temp_blks_read": 1709,
      "temp_blks_written": 1709,
      "blk_read_time": 0,
      "blk_write_time": 0,
      "queryid": -6446764050704029000,
      "md5": "85058944e069d1ab2406dcb7614028c3"
    },
    "e722b82f5ebb6dbabf7e05bd0004d039": {
      "rownum": 11,
      "query": "create table t_rar_q as select id, (random() * 1000000)::int8 as t_dat from generate_series(1, 1000000) _(id)",
      "calls": 1,
      "total_time": 2529.339437,
      "rows": 0,
      "shared_blks_hit": 197,
      "shared_blks_read": 5407,
      "shared_blks_dirtied": 5425,
      "shared_blks_written": 3358,
      "local_blks_hit": 0,
      "local_blks_read": 0,
      "local_blks_dirtied": 0,
      "local_blks_written": 0,
      "temp_blks_read": 1709,
      "temp_blks_written": 1709,
      "blk_read_time": 0,
      "blk_write_time": 0,
      "queryid": 8726250694613120000,
      "md5": "e722b82f5ebb6dbabf7e05bd0004d039"
    },
    "9496008daf0f193d85061c9f64bde9ab": {
      "rownum": 12,
      "query": "create table t_red_fk_2 as select id, (random() * 1000000)::int8 as r_t1_id from generate_series(1, 1000000) _(id)",
      "calls": 1,
      "total_time": 2414.42979,
      "rows": 0,
      "shared_blks_hit": 138,
      "shared_blks_read": 5406,
      "shared_blks_dirtied": 5406,
      "shared_blks_written": 3358,
      "local_blks_hit": 0,
      "local_blks_read": 0,
      "local_blks_dirtied": 0,
      "local_blks_written": 0,
      "temp_blks_read": 1709,
      "temp_blks_written": 1709,
      "blk_read_time": 0,
      "blk_write_time": 0,
      "queryid": 591824813582986000,
      "md5": "9496008daf0f193d85061c9f64bde9ab"
    },
    "ef0f4334b8f15b0a142c41903e836106": {
      "rownum": 13,
      "query": "create table exp_redundant.t_with_redundant_ref_idx as select i from generate_series(1, 1000000) _(i)",
      "calls": 1,
      "total_time": 2346.186131,
      "rows": 0,
      "shared_blks_hit": 126,
      "shared_blks_read": 4425,
      "shared_blks_dirtied": 4426,
      "shared_blks_written": 2377,
      "local_blks_hit": 0,
      "local_blks_read": 0,
      "local_blks_dirtied": 0,
      "local_blks_written": 0,
      "temp_blks_read": 1709,
      "temp_blks_written": 1709,
      "blk_read_time": 0,
      "blk_write_time": 0,
      "queryid": -1861943955546907400,
      "md5": "ef0f4334b8f15b0a142c41903e836106"
    },
    "32f5ef2ab3cfc8ba05d96229f852c456": {
      "rownum": 14,
      "query": "create table t_with_redundant_index as select i from generate_series(1, 1000000) _(i)",
      "calls": 1,
      "total_time": 2280.521618,
      "rows": 0,
      "shared_blks_hit": 128,
      "shared_blks_read": 4425,
      "shared_blks_dirtied": 4427,
      "shared_blks_written": 2377,
      "local_blks_hit": 0,
      "local_blks_read": 0,
      "local_blks_dirtied": 0,
      "local_blks_written": 0,
      "temp_blks_read": 1709,
      "temp_blks_written": 1709,
      "blk_read_time": 0,
      "blk_write_time": 0,
      "queryid": -5095830603244401000,
      "md5": "32f5ef2ab3cfc8ba05d96229f852c456"
    },
    "3f094705882eaade4441c4dfbc1809b9": {
      "rownum": 15,
      "query": "create table t_with_unused_index as select i from generate_series(1, 1000000) _(i)",
      "calls": 1,
      "total_time": 2232.246934,
      "rows": 0,
      "shared_blks_hit": 126,
      "shared_blks_read": 4425,
      "shared_blks_dirtied": 4425,
      "shared_blks_written": 2377,
      "local_blks_hit": 0,
      "local_blks_read": 0,
      "local_blks_dirtied": 0,
      "local_blks_written": 0,
      "temp_blks_read": 1709,
      "temp_blks_written": 1709,
      "blk_read_time": 0,
      "blk_write_time": 0,
      "queryid": -678916242629262500,
      "md5": "3f094705882eaade4441c4dfbc1809b9"
    },
    "d16ce3233d3d18f9e990387d5892ee22": {
      "rownum": 16,
      "query": "create table public.t_with_redundant_ref_idx as select i from generate_series(1, 1000000) _(i)",
      "calls": 1,
      "total_time": 2231.560208,
      "rows": 0,
      "shared_blks_hit": 124,
      "shared_blks_read": 4425,
      "shared_blks_dirtied": 4425,
      "shared_blks_written": 2377,
      "local_blks_hit": 0,
      "local_blks_read": 0,
      "local_blks_dirtied": 0,
      "local_blks_written": 0,
      "temp_blks_read": 1709,
      "temp_blks_written": 1709,
      "blk_read_time": 0,
      "blk_write_time": 0,
      "queryid": 4227063200314075600,
      "md5": "d16ce3233d3d18f9e990387d5892ee22"
    },
    "8bd7f2c2ba1ee035dd61d0040f578590": {
      "rownum": 17,
      "query": "create table test_schema.t_with_invalid_index as select i from generate_series(1, 1000000) _(i)",
      "calls": 1,
      "total_time": 2224.586829,
      "rows": 0,
      "shared_blks_hit": 130,
      "shared_blks_read": 4425,
      "shared_blks_dirtied": 4432,
      "shared_blks_written": 2377,
      "local_blks_hit": 0,
      "local_blks_read": 0,
      "local_blks_dirtied": 0,
      "local_blks_written": 0,
      "temp_blks_read": 1709,
      "temp_blks_written": 1709,
      "blk_read_time": 0,
      "blk_write_time": 0,
      "queryid": 5156236148593934000,
      "md5": "8bd7f2c2ba1ee035dd61d0040f578590"
    },
    "c41489b5562148d492ec5f291993b5ee": {
      "rownum": 18,
      "query": "create table t_f004_empty as select i from generate_series(1, 1000000) _(i)",
      "calls": 1,
      "total_time": 1903.079229,
      "rows": 0,
      "shared_blks_hit": 128,
      "shared_blks_read": 4429,
      "shared_blks_dirtied": 4429,
      "shared_blks_written": 2377,
      "local_blks_hit": 0,
      "local_blks_read": 0,
      "local_blks_dirtied": 0,
      "local_blks_written": 0,
      "temp_blks_read": 1709,
      "temp_blks_written": 1709,
      "blk_read_time": 0,
      "blk_write_time": 0,
      "queryid": -3498952347021279,
      "md5": "c41489b5562148d492ec5f291993b5ee"
    },
    "41649b5376672435db270b265abd719b": {
      "rownum": 19,
      "query": "create index r_red_fk_2_fk_idx on t_red_fk_2(r_t1_id)",
      "calls": 1,
      "total_time": 1625.185,
      "rows": 0,
      "shared_blks_hit": 1095,
      "shared_blks_read": 1830,
      "shared_blks_dirtied": 0,
      "shared_blks_written": 0,
      "local_blks_hit": 0,
      "local_blks_read": 0,
      "local_blks_dirtied": 0,
      "local_blks_written": 0,
      "temp_blks_read": 2448,
      "temp_blks_written": 1283,
      "blk_read_time": 0,
      "blk_write_time": 0,
      "queryid": -2801630118753177600,
      "md5": "41649b5376672435db270b265abd719b"
    },
    "10ea71b17cbe4e8574737f13d9aa74a7": {
      "rownum": 20,
      "query": "create index concurrently t_with_redundant_idx_f1_f2 on t_with_redundant_idx(f1,f2)",
      "calls": 1,
      "total_time": 1353.578945,
      "rows": 0,
      "shared_blks_hit": 3965,
      "shared_blks_read": 8638,
      "shared_blks_dirtied": 2,
      "shared_blks_written": 0,
      "local_blks_hit": 0,
      "local_blks_read": 0,
      "local_blks_dirtied": 0,
      "local_blks_written": 0,
      "temp_blks_read": 2448,
      "temp_blks_written": 1283,
      "blk_read_time": 0,
      "blk_write_time": 0,
      "queryid": -8920212056722243000,
      "md5": "10ea71b17cbe4e8574737f13d9aa74a7"
    },
    "d2b42fdb3e69ab37ae920aa6154580d5": {
      "rownum": 21,
      "query": "alter table t_red_fk_1 add primary key (id)",
      "calls": 1,
      "total_time": 1283.801871,
      "rows": 0,
      "shared_blks_hit": 2771,
      "shared_blks_read": 4529,
      "shared_blks_dirtied": 2383,
      "shared_blks_written": 2345,
      "local_blks_hit": 0,
      "local_blks_read": 0,
      "local_blks_dirtied": 0,
      "local_blks_written": 0,
      "temp_blks_read": 3959,
      "temp_blks_written": 3022,
      "blk_read_time": 0,
      "blk_write_time": 0,
      "queryid": 7202543407834562000,
      "md5": "d2b42fdb3e69ab37ae920aa6154580d5"
    },
    "eb413a8ade520c34aa6278929cd8b8d0": {
      "rownum": 22,
      "query": "create index concurrently i_redundant_1 on t_with_redundant_index(i)",
      "calls": 1,
      "total_time": 1257.667717,
      "rows": 0,
      "shared_blks_hit": 3312,
      "shared_blks_read": 6316,
      "shared_blks_dirtied": 1260,
      "shared_blks_written": 1226,
      "local_blks_hit": 0,
      "local_blks_read": 0,
      "local_blks_dirtied": 0,
      "local_blks_written": 0,
      "temp_blks_read": 2448,
      "temp_blks_written": 1283,
      "blk_read_time": 0,
      "blk_write_time": 0,
      "queryid": 566438153080519400,
      "md5": "eb413a8ade520c34aa6278929cd8b8d0"
    },
    "1657dd3ac6a8396cda288ccf95b3e93e": {
      "rownum": 23,
      "query": "create index concurrently t_with_redundant_idx_f3_1 on t_with_redundant_idx(f3)",
      "calls": 1,
      "total_time": 1247.415229,
      "rows": 0,
      "shared_blks_hit": 3688,
      "shared_blks_read": 8885,
      "shared_blks_dirtied": 2,
      "shared_blks_written": 1,
      "local_blks_hit": 0,
      "local_blks_read": 0,
      "local_blks_dirtied": 0,
      "local_blks_written": 0,
      "temp_blks_read": 2448,
      "temp_blks_written": 1283,
      "blk_read_time": 0,
      "blk_write_time": 0,
      "queryid": -7990293000632035000,
      "md5": "1657dd3ac6a8396cda288ccf95b3e93e"
    },
    "1e7bc5cce40a35c4730e436ea664a3f9": {
      "rownum": 24,
      "query": "create index concurrently t_with_redundant_idx_f1_2 on t_with_redundant_idx(f1)",
      "calls": 1,
      "total_time": 1233.808273,
      "rows": 0,
      "shared_blks_hit": 3705,
      "shared_blks_read": 8865,
      "shared_blks_dirtied": 2,
      "shared_blks_written": 842,
      "local_blks_hit": 0,
      "local_blks_read": 0,
      "local_blks_dirtied": 0,
      "local_blks_written": 0,
      "temp_blks_read": 2448,
      "temp_blks_written": 1283,
      "blk_read_time": 0,
      "blk_write_time": 0,
      "queryid": 879148290678321700,
      "md5": "1e7bc5cce40a35c4730e436ea664a3f9"
    },
    "df3e7ad51d29398d30aebde32df0d71d": {
      "rownum": 25,
      "query": "create index concurrently t_with_redundant_idx_f2 on t_with_redundant_idx(f2)",
      "calls": 1,
      "total_time": 1199.761512,
      "rows": 0,
      "shared_blks_hit": 3694,
      "shared_blks_read": 8876,
      "shared_blks_dirtied": 2,
      "shared_blks_written": 357,
      "local_blks_hit": 0,
      "local_blks_read": 0,
      "local_blks_dirtied": 0,
      "local_blks_written": 0,
      "temp_blks_read": 2448,
      "temp_blks_written": 1283,
      "blk_read_time": 0,
      "blk_write_time": 0,
      "queryid": 1902759977384827000,
      "md5": "df3e7ad51d29398d30aebde32df0d71d"
    },
    "287d9693318affc139279ec76e414f24": {
      "rownum": 26,
      "query": "create index concurrently t_with_redundant_idx_f3_2 on t_with_redundant_idx(f3)",
      "calls": 1,
      "total_time": 1199.547182,
      "rows": 0,
      "shared_blks_hit": 3848,
      "shared_blks_read": 8722,
      "shared_blks_dirtied": 2,
      "shared_blks_written": 0,
      "local_blks_hit": 0,
      "local_blks_read": 0,
      "local_blks_dirtied": 0,
      "local_blks_written": 0,
      "temp_blks_read": 2448,
      "temp_blks_written": 1283,
      "blk_read_time": 0,
      "blk_write_time": 0,
      "queryid": 8565802378619238000,
      "md5": "287d9693318affc139279ec76e414f24"
    },
    "5f8e51e07770412b1911cebb26c55f4b": {
      "rownum": 27,
      "query": "create index t_with_redundant_ref_idx_1 on public.t_with_redundant_ref_idx using btree (i)",
      "calls": 1,
      "total_time": 1189.902818,
      "rows": 0,
      "shared_blks_hit": 1128,
      "shared_blks_read": 1280,
      "shared_blks_dirtied": 1281,
      "shared_blks_written": 1247,
      "local_blks_hit": 0,
      "local_blks_read": 0,
      "local_blks_dirtied": 0,
      "local_blks_written": 0,
      "temp_blks_read": 2448,
      "temp_blks_written": 1281,
      "blk_read_time": 0,
      "blk_write_time": 0,
      "queryid": 7121640066867289000,
      "md5": "5f8e51e07770412b1911cebb26c55f4b"
    },
    "479aad6eb92a27d10c03fb12a793614e": {
      "rownum": 28,
      "query": "create index concurrently t_with_redundant_idx_f1 on t_with_redundant_idx(f1)",
      "calls": 1,
      "total_time": 1181.839146,
      "rows": 0,
      "shared_blks_hit": 3571,
      "shared_blks_read": 8999,
      "shared_blks_dirtied": 2,
      "shared_blks_written": 0,
      "local_blks_hit": 0,
      "local_blks_read": 0,
      "local_blks_dirtied": 0,
      "local_blks_written": 0,
      "temp_blks_read": 2448,
      "temp_blks_written": 1283,
      "blk_read_time": 0,
      "blk_write_time": 0,
      "queryid": -7862275411983427000,
      "md5": "479aad6eb92a27d10c03fb12a793614e"
    },
    "179dd95fcd8662bf4e071266e75a8377": {
      "rownum": 29,
      "query": "create index concurrently t_with_redundant_idx_id on t_with_redundant_idx(id)",
      "calls": 1,
      "total_time": 1180.209978,
      "rows": 0,
      "shared_blks_hit": 3338,
      "shared_blks_read": 9241,
      "shared_blks_dirtied": 2,
      "shared_blks_written": 432,
      "local_blks_hit": 0,
      "local_blks_read": 0,
      "local_blks_dirtied": 0,
      "local_blks_written": 0,
      "temp_blks_read": 2448,
      "temp_blks_written": 1283,
      "blk_read_time": 0,
      "blk_write_time": 0,
      "queryid": 5967467509848557000,
      "md5": "179dd95fcd8662bf4e071266e75a8377"
    },
    "76531a1eb8e34ee84b9f6f32762a30e1": {
      "rownum": 30,
      "query": "create index concurrently i_unused on t_with_unused_index(i)",
      "calls": 1,
      "total_time": 1175.914931,
      "rows": 0,
      "shared_blks_hit": 3274,
      "shared_blks_read": 6351,
      "shared_blks_dirtied": 1292,
      "shared_blks_written": 1255,
      "local_blks_hit": 0,
      "local_blks_read": 0,
      "local_blks_dirtied": 0,
      "local_blks_written": 0,
      "temp_blks_read": 2448,
      "temp_blks_written": 1275,
      "blk_read_time": 0,
      "blk_write_time": 0,
      "queryid": -6612128672608002000,
      "md5": "76531a1eb8e34ee84b9f6f32762a30e1"
    },
    "62992e0ccb57f6bdfda778c7c473e8ad": {
      "rownum": 31,
      "query": "create index t_with_redundant_ref_idx_1 on exp_redundant.t_with_redundant_ref_idx using btree (i)",
      "calls": 1,
      "total_time": 1174.789226,
      "rows": 0,
      "shared_blks_hit": 1151,
      "shared_blks_read": 1261,
      "shared_blks_dirtied": 1275,
      "shared_blks_written": 1227,
      "local_blks_hit": 0,
      "local_blks_read": 0,
      "local_blks_dirtied": 0,
      "local_blks_written": 0,
      "temp_blks_read": 2448,
      "temp_blks_written": 1283,
      "blk_read_time": 0,
      "blk_write_time": 0,
      "queryid": -395938069363296600,
      "md5": "62992e0ccb57f6bdfda778c7c473e8ad"
    },
    "cbcd92704dd802d204b9bc7ee8b39187": {
      "rownum": 32,
      "query": "create index t_rar_q_idx on t_rar_q(id)",
      "calls": 1,
      "total_time": 1148.291044,
      "rows": 0,
      "shared_blks_hit": 1135,
      "shared_blks_read": 1728,
      "shared_blks_dirtied": 1724,
      "shared_blks_written": 1688,
      "local_blks_hit": 0,
      "local_blks_read": 0,
      "local_blks_dirtied": 0,
      "local_blks_written": 0,
      "temp_blks_read": 2448,
      "temp_blks_written": 1238,
      "blk_read_time": 0,
      "blk_write_time": 0,
      "queryid": 2650688778442027500,
      "md5": "cbcd92704dd802d204b9bc7ee8b39187"
    },
    "95f449a74e628c4e8d47ae2af9b2fd43": {
      "rownum": 33,
      "query": "create index r_red_fk_1_id_idx on t_red_fk_1(id)",
      "calls": 1,
      "total_time": 1135.085163,
      "rows": 0,
      "shared_blks_hit": 1167,
      "shared_blks_read": 1225,
      "shared_blks_dirtied": 0,
      "shared_blks_written": 0,
      "local_blks_hit": 0,
      "local_blks_read": 0,
      "local_blks_dirtied": 0,
      "local_blks_written": 0,
      "temp_blks_read": 2448,
      "temp_blks_written": 1275,
      "blk_read_time": 0,
      "blk_write_time": 0,
      "queryid": 3040282640922053000,
      "md5": "95f449a74e628c4e8d47ae2af9b2fd43"
    },
    "7e370d36c2447380a7d5678a0b2040d7": {
      "rownum": 34,
      "query": "create index t_with_redundant_ref_idx_2 on exp_redundant.t_with_redundant_ref_idx using btree (i)",
      "calls": 1,
      "total_time": 1117.34301,
      "rows": 0,
      "shared_blks_hit": 1153,
      "shared_blks_read": 1224,
      "shared_blks_dirtied": 0,
      "shared_blks_written": 0,
      "local_blks_hit": 0,
      "local_blks_read": 0,
      "local_blks_dirtied": 0,
      "local_blks_written": 0,
      "temp_blks_read": 2448,
      "temp_blks_written": 1268,
      "blk_read_time": 0,
      "blk_write_time": 0,
      "queryid": -94268938950487040,
      "md5": "7e370d36c2447380a7d5678a0b2040d7"
    },
    "c8703f324c1fb37854d9a2c6edbaa6a2": {
      "rownum": 35,
      "query": "create index r_red_fk_1_X_idx on t_red_fk_1(id)",
      "calls": 1,
      "total_time": 1107.872887,
      "rows": 0,
      "shared_blks_hit": 1186,
      "shared_blks_read": 1247,
      "shared_blks_dirtied": 0,
      "shared_blks_written": 0,
      "local_blks_hit": 0,
      "local_blks_read": 0,
      "local_blks_dirtied": 0,
      "local_blks_written": 0,
      "temp_blks_read": 2448,
      "temp_blks_written": 1302,
      "blk_read_time": 0,
      "blk_write_time": 0,
      "queryid": 3969450259942249000,
      "md5": "c8703f324c1fb37854d9a2c6edbaa6a2"
    },
    "6bc4ef68211b4d4714588b1314c3b450": {
      "rownum": 36,
      "query": "create index t_with_redundant_ref_idx_3 on public.t_with_redundant_ref_idx using btree (i)",
      "calls": 1,
      "total_time": 1105.688919,
      "rows": 0,
      "shared_blks_hit": 1164,
      "shared_blks_read": 1226,
      "shared_blks_dirtied": 0,
      "shared_blks_written": 0,
      "local_blks_hit": 0,
      "local_blks_read": 0,
      "local_blks_dirtied": 0,
      "local_blks_written": 0,
      "temp_blks_read": 2449,
      "temp_blks_written": 1279,
      "blk_read_time": 0,
      "blk_write_time": 0,
      "queryid": 39141847517093180,
      "md5": "6bc4ef68211b4d4714588b1314c3b450"
    },
    "cdfd61b4586420038e5e614ab85aeeae": {
      "rownum": 37,
      "query": "create index t_with_redundant_ref_idx_2 on public.t_with_redundant_ref_idx using btree (i)",
      "calls": 1,
      "total_time": 1104.782215,
      "rows": 0,
      "shared_blks_hit": 1131,
      "shared_blks_read": 1277,
      "shared_blks_dirtied": 0,
      "shared_blks_written": 0,
      "local_blks_hit": 0,
      "local_blks_read": 0,
      "local_blks_dirtied": 0,
      "local_blks_written": 0,
      "temp_blks_read": 2448,
      "temp_blks_written": 1285,
      "blk_read_time": 0,
      "blk_write_time": 0,
      "queryid": -3115028882787390000,
      "md5": "cdfd61b4586420038e5e614ab85aeeae"
    },
    "3ebee924ec35c0d73b9480782463f72e": {
      "rownum": 38,
      "query": "create unique index t_with_redundant_idx_f1_uniq on t_with_redundant_idx (f1)",
      "calls": 1,
      "total_time": 1103.641794,
      "rows": 0,
      "shared_blks_hit": 1217,
      "shared_blks_read": 2182,
      "shared_blks_dirtied": 3,
      "shared_blks_written": 33,
      "local_blks_hit": 0,
      "local_blks_read": 0,
      "local_blks_dirtied": 0,
      "local_blks_written": 0,
      "temp_blks_read": 2449,
      "temp_blks_written": 1272,
      "blk_read_time": 0,
      "blk_write_time": 0,
      "queryid": 1566471017150549200,
      "md5": "3ebee924ec35c0d73b9480782463f72e"
    },
    "7d1bf9b05e76b943c47b50b366c65772": {
      "rownum": 39,
      "query": "create index t_with_redundant_ref_idx_3 on exp_redundant.t_with_redundant_ref_idx using btree (i)",
      "calls": 1,
      "total_time": 1098.330159,
      "rows": 0,
      "shared_blks_hit": 1163,
      "shared_blks_read": 1260,
      "shared_blks_dirtied": 0,
      "shared_blks_written": 0,
      "local_blks_hit": 0,
      "local_blks_read": 0,
      "local_blks_dirtied": 0,
      "local_blks_written": 0,
      "temp_blks_read": 2448,
      "temp_blks_written": 1297,
      "blk_read_time": 0,
      "blk_write_time": 0,
      "queryid": -1845904424067371800,
      "md5": "7d1bf9b05e76b943c47b50b366c65772"
    },
    "182ba4f0ffb554baf311c8fa6800939f": {
      "rownum": 40,
      "query": "create database dbname",
      "calls": 1,
      "total_time": 1071.243055,
      "rows": 0,
      "shared_blks_hit": 50,
      "shared_blks_read": 9,
      "shared_blks_dirtied": 3,
      "shared_blks_written": 0,
      "local_blks_hit": 0,
      "local_blks_read": 0,
      "local_blks_dirtied": 0,
      "local_blks_written": 0,
      "temp_blks_read": 0,
      "temp_blks_written": 0,
      "blk_read_time": 0,
      "blk_write_time": 0,
      "queryid": 3617698589948080000,
      "md5": "182ba4f0ffb554baf311c8fa6800939f"
    },
    "59e32b402631edd68f57233d02a6ff1c": {
      "rownum": 41,
      "query": "alter table t_with_redundant_idx add primary key (id)",
      "calls": 1,
      "total_time": 1056.571561,
      "rows": 0,
      "shared_blks_hit": 3240,
      "shared_blks_read": 6575,
      "shared_blks_dirtied": 4329,
      "shared_blks_written": 4290,
      "local_blks_hit": 0,
      "local_blks_read": 0,
      "local_blks_dirtied": 0,
      "local_blks_written": 0,
      "temp_blks_read": 2449,
      "temp_blks_written": 1259,
      "blk_read_time": 0,
      "blk_write_time": 0,
      "queryid": 3416651331628416000,
      "md5": "59e32b402631edd68f57233d02a6ff1c"
    },
    "63ed402d488d71cb2ac691b882743cad": {
      "rownum": 42,
      "query": "alter table t_red_fk_2 add constraint fk_red_fk2_t1 foreign key (r_t1_id) references t_red_fk_1(id)",
      "calls": 1,
      "total_time": 986.222488,
      "rows": 0,
      "shared_blks_hit": 4600,
      "shared_blks_read": 5533,
      "shared_blks_dirtied": 3366,
      "shared_blks_written": 3326,
      "local_blks_hit": 0,
      "local_blks_read": 0,
      "local_blks_dirtied": 0,
      "local_blks_written": 0,
      "temp_blks_read": 0,
      "temp_blks_written": 0,
      "blk_read_time": 0,
      "blk_write_time": 0,
      "queryid": 2911641097746118700,
      "md5": "63ed402d488d71cb2ac691b882743cad"
    },
    "6d85f5ed15e4a22c77379c8c27e4a096": {
      "rownum": 43,
      "query": "create database checkup_test_db",
      "calls": 1,
      "total_time": 800.095933,
      "rows": 0,
      "shared_blks_hit": 61,
      "shared_blks_read": 4,
      "shared_blks_dirtied": 6,
      "shared_blks_written": 0,
      "local_blks_hit": 0,
      "local_blks_read": 0,
      "local_blks_dirtied": 0,
      "local_blks_written": 0,
      "temp_blks_read": 0,
      "temp_blks_written": 0,
      "blk_read_time": 0,
      "blk_write_time": 0,
      "queryid": -2133351059478393300,
      "md5": "6d85f5ed15e4a22c77379c8c27e4a096"
    },
    "4acc373047981b2e725d2ee88f314170": {
      "rownum": 44,
      "query": "select count(*) from t_slw_q",
      "calls": 1,
      "total_time": 707.626642,
      "rows": 1,
      "shared_blks_hit": 0,
      "shared_blks_read": 44248,
      "shared_blks_dirtied": 0,
      "shared_blks_written": 0,
      "local_blks_hit": 0,
      "local_blks_read": 0,
      "local_blks_dirtied": 0,
      "local_blks_written": 0,
      "temp_blks_read": 0,
      "temp_blks_written": 0,
      "blk_read_time": 0,
      "blk_write_time": 0,
      "queryid": -3604241719388670000,
      "md5": "4acc373047981b2e725d2ee88f314170"
    },
    "6aa3e30a0e616b58a3e395fdfe1210ba": {
      "rownum": 45,
      "query": "analyze t_f004_empty",
      "calls": 2,
      "total_time": 133.235754,
      "rows": 0,
      "shared_blks_hit": 6481,
      "shared_blks_read": 2426,
      "shared_blks_dirtied": 2420,
      "shared_blks_written": 2385,
      "local_blks_hit": 0,
      "local_blks_read": 0,
      "local_blks_dirtied": 0,
      "local_blks_written": 0,
      "temp_blks_read": 0,
      "temp_blks_written": 0,
      "blk_read_time": 0,
      "blk_write_time": 0,
      "queryid": -5293816547023798000,
      "md5": "6aa3e30a0e616b58a3e395fdfe1210ba"
    },
    "d02d1aef973dfdb7a87f56b6b6dfea91": {
      "rownum": 46,
      "query": "create table bloated as select i from generate_series(1, 100000) _(i)",
      "calls": 1,
      "total_time": 71.196108,
      "rows": 0,
      "shared_blks_hit": 126,
      "shared_blks_read": 443,
      "shared_blks_dirtied": 444,
      "shared_blks_written": 0,
      "local_blks_hit": 0,
      "local_blks_read": 0,
      "local_blks_dirtied": 0,
      "local_blks_written": 0,
      "temp_blks_read": 171,
      "temp_blks_written": 171,
      "blk_read_time": 0,
      "blk_write_time": 0,
      "queryid": -2951921325210440700,
      "md5": "d02d1aef973dfdb7a87f56b6b6dfea91"
    },
    "b7d373c8db27e676fdfdc77dc47b08a0": {
      "rownum": 47,
      "query": "CREATE TABLE test_schema.orders\n(\n id serial,\n cnt integer,\n CONSTRAINT orders_pk PRIMARY KEY (id)\n)",
      "calls": 1,
      "total_time": 64.686217,
      "rows": 0,
      "shared_blks_hit": 463,
      "shared_blks_read": 29,
      "shared_blks_dirtied": 45,
      "shared_blks_written": 0,
      "local_blks_hit": 0,
      "local_blks_read": 0,
      "local_blks_dirtied": 0,
      "local_blks_written": 0,
      "temp_blks_read": 0,
      "temp_blks_written": 0,
      "blk_read_time": 0,
      "blk_write_time": 0,
      "queryid": -1491185255100233500,
      "md5": "b7d373c8db27e676fdfdc77dc47b08a0"
    },
    "23bbd085bb37c5fafcd10ade38dfacf7": {
      "rownum": 48,
      "query": "create index i_bloated on bloated(i)",
      "calls": 1,
      "total_time": 45.520022,
      "rows": 0,
      "shared_blks_hit": 534,
      "shared_blks_read": 0,
      "shared_blks_dirtied": 0,
      "shared_blks_written": 0,
      "local_blks_hit": 0,
      "local_blks_read": 0,
      "local_blks_dirtied": 0,
      "local_blks_written": 0,
      "temp_blks_read": 0,
      "temp_blks_written": 0,
      "blk_read_time": 0,
      "blk_write_time": 0,
      "queryid": 8841083458873351000,
      "md5": "23bbd085bb37c5fafcd10ade38dfacf7"
    },
    "ab7d8f0edf844d85869cd324de44e515": {
      "rownum": 49,
      "query": "delete from bloated where i % $1 = $2",
      "calls": 1,
      "total_time": 31.417113,
      "rows": 50000,
      "shared_blks_hit": 50443,
      "shared_blks_read": 0,
      "shared_blks_dirtied": 0,
      "shared_blks_written": 0,
      "local_blks_hit": 0,
      "local_blks_read": 0,
      "local_blks_dirtied": 0,
      "local_blks_written": 0,
      "temp_blks_read": 0,
      "temp_blks_written": 0,
      "blk_read_time": 0,
      "blk_write_time": 0,
      "queryid": -3076169388096589300,
      "md5": "ab7d8f0edf844d85869cd324de44e515"
    },
    "55b742b024771036230e287939b965ec": {
      "rownum": 50,
      "query": "create table t_38 as select i from generate_series(1, 1000) _(i)",
      "calls": 1,
      "total_time": 31.175209,
      "rows": 0,
      "shared_blks_hit": 230,
      "shared_blks_read": 8,
      "shared_blks_dirtied": 8,
      "shared_blks_written": 0,
      "local_blks_hit": 0,
      "local_blks_read": 0,
      "local_blks_dirtied": 0,
      "local_blks_written": 0,
      "temp_blks_read": 0,
      "temp_blks_written": 0,
      "blk_read_time": 0,
      "blk_write_time": 0,
      "queryid": 6353077014253033000,
      "md5": "55b742b024771036230e287939b965ec"
    },
    "ef59487da25a372e106c2191e92201d2": {
      "rownum": 51,
      "query": "create index concurrently i_u_91 on t_91(i)",
      "calls": 1,
      "total_time": 30.967985,
      "rows": 0,
      "shared_blks_hit": 200,
      "shared_blks_read": 5,
      "shared_blks_dirtied": 2,
      "shared_blks_written": 0,
      "local_blks_hit": 0,
      "local_blks_read": 0,
      "local_blks_dirtied": 0,
      "local_blks_written": 0,
      "temp_blks_read": 0,
      "temp_blks_written": 0,
      "blk_read_time": 0,
      "blk_write_time": 0,
      "queryid": -2208259693067776500,
      "md5": "ef59487da25a372e106c2191e92201d2"
    },
    "b56c0bbcdd112624648ef48f216f3e92": {
      "rownum": 52,
      "query": "alter system set random_page_cost = 2.22",
      "calls": 1,
      "total_time": 29.764038,
      "rows": 0,
      "shared_blks_hit": 0,
      "shared_blks_read": 0,
      "shared_blks_dirtied": 0,
      "shared_blks_written": 0,
      "local_blks_hit": 0,
      "local_blks_read": 0,
      "local_blks_dirtied": 0,
      "local_blks_written": 0,
      "temp_blks_read": 0,
      "temp_blks_written": 0,
      "blk_read_time": 0,
      "blk_write_time": 0,
      "queryid": 1881993450838449000,
      "md5": "b56c0bbcdd112624648ef48f216f3e92"
    },
    "85de2db5848273f1255406c86862398b": {
      "rownum": 53,
      "query": "create table t_4 as select i from generate_series(1, 1000) _(i)",
      "calls": 1,
      "total_time": 28.817169,
      "rows": 0,
      "shared_blks_hit": 233,
      "shared_blks_read": 7,
      "shared_blks_dirtied": 9,
      "shared_blks_written": 0,
      "local_blks_hit": 0,
      "local_blks_read": 0,
      "local_blks_dirtied": 0,
      "local_blks_written": 0,
      "temp_blks_read": 0,
      "temp_blks_written": 0,
      "blk_read_time": 0,
      "blk_write_time": 0,
      "queryid": -7018469535310114000,
      "md5": "85de2db5848273f1255406c86862398b"
    },
    "04c04f974feb16a092143f1db522dcdd": {
      "rownum": 54,
      "query": "create index concurrently i_u_36 on t_36(i)",
      "calls": 1,
      "total_time": 28.505315,
      "rows": 0,
      "shared_blks_hit": 201,
      "shared_blks_read": 7,
      "shared_blks_dirtied": 5,
      "shared_blks_written": 0,
      "local_blks_hit": 0,
      "local_blks_read": 0,
      "local_blks_dirtied": 0,
      "local_blks_written": 0,
      "temp_blks_read": 0,
      "temp_blks_written": 0,
      "blk_read_time": 0,
      "blk_write_time": 0,
      "queryid": 7820838637134668000,
      "md5": "04c04f974feb16a092143f1db522dcdd"
    },
    "18733f12451eda1bcdeb5f15ca0e2bff": {
      "rownum": 55,
      "query": "create index concurrently i_u_52 on t_52(i)",
      "calls": 1,
      "total_time": 27.845233,
      "rows": 0,
      "shared_blks_hit": 200,
      "shared_blks_read": 5,
      "shared_blks_dirtied": 2,
      "shared_blks_written": 0,
      "local_blks_hit": 0,
      "local_blks_read": 0,
      "local_blks_dirtied": 0,
      "local_blks_written": 0,
      "temp_blks_read": 0,
      "temp_blks_written": 0,
      "blk_read_time": 0,
      "blk_write_time": 0,
      "queryid": -6687581582105482000,
      "md5": "18733f12451eda1bcdeb5f15ca0e2bff"
    },
    "534893864001d79aacd9d460040640db": {
      "rownum": 56,
      "query": "create index concurrently i_u_95 on t_95(i)",
      "calls": 1,
      "total_time": 24.153535,
      "rows": 0,
      "shared_blks_hit": 202,
      "shared_blks_read": 6,
      "shared_blks_dirtied": 3,
      "shared_blks_written": 0,
      "local_blks_hit": 0,
      "local_blks_read": 0,
      "local_blks_dirtied": 0,
      "local_blks_written": 0,
      "temp_blks_read": 0,
      "temp_blks_written": 0,
      "blk_read_time": 0,
      "blk_write_time": 0,
      "queryid": -5310216488601905000,
      "md5": "534893864001d79aacd9d460040640db"
    },
    "8b2e13a7d0128bd60630d3193dfe0980": {
      "rownum": 57,
      "query": "create index concurrently i_u_96 on t_96(i)",
      "calls": 1,
      "total_time": 19.49313,
      "rows": 0,
      "shared_blks_hit": 200,
      "shared_blks_read": 5,
      "shared_blks_dirtied": 2,
      "shared_blks_written": 0,
      "local_blks_hit": 0,
      "local_blks_read": 0,
      "local_blks_dirtied": 0,
      "local_blks_written": 0,
      "temp_blks_read": 0,
      "temp_blks_written": 0,
      "blk_read_time": 0,
      "blk_write_time": 0,
      "queryid": -9095195149180732000,
      "md5": "8b2e13a7d0128bd60630d3193dfe0980"
    },
    "8ccb59c5221adf4c48ce3ddb3557a91d": {
      "rownum": 58,
      "query": "create index concurrently i_u_89 on t_89(i)",
      "calls": 1,
      "total_time": 18.775806,
      "rows": 0,
      "shared_blks_hit": 200,
      "shared_blks_read": 5,
      "shared_blks_dirtied": 2,
      "shared_blks_written": 0,
      "local_blks_hit": 0,
      "local_blks_read": 0,
      "local_blks_dirtied": 0,
      "local_blks_written": 0,
      "temp_blks_read": 0,
      "temp_blks_written": 0,
      "blk_read_time": 0,
      "blk_write_time": 0,
      "queryid": -6362236483748202000,
      "md5": "8ccb59c5221adf4c48ce3ddb3557a91d"
    },
    "03d23b5cfbcf86fb38952fd1ea484095": {
      "rownum": 59,
      "query": "create index concurrently i_r_98 on t_98(i)",
      "calls": 1,
      "total_time": 17.709515,
      "rows": 0,
      "shared_blks_hit": 128,
      "shared_blks_read": 5,
      "shared_blks_dirtied": 2,
      "shared_blks_written": 0,
      "local_blks_hit": 0,
      "local_blks_read": 0,
      "local_blks_dirtied": 0,
      "local_blks_written": 0,
      "temp_blks_read": 0,
      "temp_blks_written": 0,
      "blk_read_time": 0,
      "blk_write_time": 0,
      "queryid": -5201601287574351000,
      "md5": "03d23b5cfbcf86fb38952fd1ea484095"
    },
    "b446e2e137a39bc8967fc3423fce7c04": {
      "rownum": 60,
      "query": "create index concurrently i_r_96 on t_96(i)",
      "calls": 1,
      "total_time": 17.52869,
      "rows": 0,
      "shared_blks_hit": 128,
      "shared_blks_read": 5,
      "shared_blks_dirtied": 2,
      "shared_blks_written": 0,
      "local_blks_hit": 0,
      "local_blks_read": 0,
      "local_blks_dirtied": 0,
      "local_blks_written": 0,
      "temp_blks_read": 0,
      "temp_blks_written": 0,
      "blk_read_time": 0,
      "blk_write_time": 0,
      "queryid": 7459137016503246000,
      "md5": "b446e2e137a39bc8967fc3423fce7c04"
    },
    "0d0215f3ac8860fafde3c7e25398858c": {
      "rownum": 61,
      "query": "create index concurrently i_r_89 on t_89(i)",
      "calls": 1,
      "total_time": 16.436123,
      "rows": 0,
      "shared_blks_hit": 128,
      "shared_blks_read": 5,
      "shared_blks_dirtied": 2,
      "shared_blks_written": 0,
      "local_blks_hit": 0,
      "local_blks_read": 0,
      "local_blks_dirtied": 0,
      "local_blks_written": 0,
      "temp_blks_read": 0,
      "temp_blks_written": 0,
      "blk_read_time": 0,
      "blk_write_time": 0,
      "queryid": -3989627531761156600,
      "md5": "0d0215f3ac8860fafde3c7e25398858c"
    },
    "8cb71b3cf469951b794e0ad97ebb41d0": {
      "rownum": 62,
      "query": "create index concurrently i_r_91 on t_91(i)",
      "calls": 1,
      "total_time": 16.425085,
      "rows": 0,
      "shared_blks_hit": 128,
      "shared_blks_read": 5,
      "shared_blks_dirtied": 2,
      "shared_blks_written": 0,
      "local_blks_hit": 0,
      "local_blks_read": 0,
      "local_blks_dirtied": 0,
      "local_blks_written": 0,
      "temp_blks_read": 0,
      "temp_blks_written": 0,
      "blk_read_time": 0,
      "blk_write_time": 0,
      "queryid": -2878883449529606000,
      "md5": "8cb71b3cf469951b794e0ad97ebb41d0"
    },
    "3d4555ebfe6e9f8f399e8ad04bc5563a": {
      "rownum": 63,
      "query": "create index concurrently i_u_90 on t_90(i)",
      "calls": 1,
      "total_time": 16.244469,
      "rows": 0,
      "shared_blks_hit": 200,
      "shared_blks_read": 5,
      "shared_blks_dirtied": 2,
      "shared_blks_written": 0,
      "local_blks_hit": 0,
      "local_blks_read": 0,
      "local_blks_dirtied": 0,
      "local_blks_written": 0,
      "temp_blks_read": 0,
      "temp_blks_written": 0,
      "blk_read_time": 0,
      "blk_write_time": 0,
      "queryid": 7317672215511584000,
      "md5": "3d4555ebfe6e9f8f399e8ad04bc5563a"
    },
    "1b6e863cc516e195743c16300c28a7dc": {
      "rownum": 64,
      "query": "create index concurrently i_r_95 on t_95(i)",
      "calls": 1,
      "total_time": 15.186342,
      "rows": 0,
      "shared_blks_hit": 128,
      "shared_blks_read": 5,
      "shared_blks_dirtied": 2,
      "shared_blks_written": 0,
      "local_blks_hit": 0,
      "local_blks_read": 0,
      "local_blks_dirtied": 0,
      "local_blks_written": 0,
      "temp_blks_read": 0,
      "temp_blks_written": 0,
      "blk_read_time": 0,
      "blk_write_time": 0,
      "queryid": 578522942946942000,
      "md5": "1b6e863cc516e195743c16300c28a7dc"
    },
    "b881554b6a21856a7175b6a2ca9707e0": {
      "rownum": 65,
      "query": "create index concurrently i_u_41 on t_41(i)",
      "calls": 1,
      "total_time": 14.336251,
      "rows": 0,
      "shared_blks_hit": 200,
      "shared_blks_read": 5,
      "shared_blks_dirtied": 2,
      "shared_blks_written": 0,
      "local_blks_hit": 0,
      "local_blks_read": 0,
      "local_blks_dirtied": 0,
      "local_blks_written": 0,
      "temp_blks_read": 0,
      "temp_blks_written": 0,
      "blk_read_time": 0,
      "blk_write_time": 0,
      "queryid": -8638876604929383000,
      "md5": "b881554b6a21856a7175b6a2ca9707e0"
    },
    "4d53d73dc09b8f7c5403360ca96967aa": {
      "rownum": 66,
      "query": "create index concurrently i_u_94 on t_94(i)",
      "calls": 1,
      "total_time": 13.468425,
      "rows": 0,
      "shared_blks_hit": 200,
      "shared_blks_read": 5,
      "shared_blks_dirtied": 2,
      "shared_blks_written": 0,
      "local_blks_hit": 0,
      "local_blks_read": 0,
      "local_blks_dirtied": 0,
      "local_blks_written": 0,
      "temp_blks_read": 0,
      "temp_blks_written": 0,
      "blk_read_time": 0,
      "blk_write_time": 0,
      "queryid": 8950445517835704000,
      "md5": "4d53d73dc09b8f7c5403360ca96967aa"
    },
    "c5942a1e47e06099163319f0c6b72ab0": {
      "rownum": 67,
      "query": "create index concurrently i_r_49 on t_49(i)",
      "calls": 1,
      "total_time": 13.229272,
      "rows": 0,
      "shared_blks_hit": 130,
      "shared_blks_read": 6,
      "shared_blks_dirtied": 3,
      "shared_blks_written": 0,
      "local_blks_hit": 0,
      "local_blks_read": 0,
      "local_blks_dirtied": 0,
      "local_blks_written": 0,
      "temp_blks_read": 0,
      "temp_blks_written": 0,
      "blk_read_time": 0,
      "blk_write_time": 0,
      "queryid": -7730285031161037000,
      "md5": "c5942a1e47e06099163319f0c6b72ab0"
    },
    "d1aa370375231a28b1bf87b87d275518": {
      "rownum": 68,
      "query": "create index concurrently i_u_51 on t_51(i)",
      "calls": 1,
      "total_time": 12.674398,
      "rows": 0,
      "shared_blks_hit": 200,
      "shared_blks_read": 5,
      "shared_blks_dirtied": 2,
      "shared_blks_written": 0,
      "local_blks_hit": 0,
      "local_blks_read": 0,
      "local_blks_dirtied": 0,
      "local_blks_written": 0,
      "temp_blks_read": 0,
      "temp_blks_written": 0,
      "blk_read_time": 0,
      "blk_write_time": 0,
      "queryid": -9109055381621161000,
      "md5": "d1aa370375231a28b1bf87b87d275518"
    },
    "5f942db4e9893ea20712fe3383e566fb": {
      "rownum": 69,
      "query": "create index concurrently i_u_38 on t_38(i)",
      "calls": 1,
      "total_time": 11.678995,
      "rows": 0,
      "shared_blks_hit": 200,
      "shared_blks_read": 5,
      "shared_blks_dirtied": 2,
      "shared_blks_written": 0,
      "local_blks_hit": 0,
      "local_blks_read": 0,
      "local_blks_dirtied": 0,
      "local_blks_written": 0,
      "temp_blks_read": 0,
      "temp_blks_written": 0,
      "blk_read_time": 0,
      "blk_write_time": 0,
      "queryid": -1286408037136076500,
      "md5": "5f942db4e9893ea20712fe3383e566fb"
    },
    "1a667f9ff12fa3e80b7d3b8a7a93f023": {
      "rownum": 70,
      "query": "create index concurrently i_u_92 on t_92(i)",
      "calls": 1,
      "total_time": 11.366396,
      "rows": 0,
      "shared_blks_hit": 200,
      "shared_blks_read": 5,
      "shared_blks_dirtied": 2,
      "shared_blks_written": 0,
      "local_blks_hit": 0,
      "local_blks_read": 0,
      "local_blks_dirtied": 0,
      "local_blks_written": 0,
      "temp_blks_read": 0,
      "temp_blks_written": 0,
      "blk_read_time": 0,
      "blk_write_time": 0,
      "queryid": 4142488168978146300,
      "md5": "1a667f9ff12fa3e80b7d3b8a7a93f023"
    },
    "7166501388435bd7719674b4de4fd9f8": {
      "rownum": 71,
      "query": "create index concurrently i_r_51 on t_51(i)",
      "calls": 1,
      "total_time": 11.360435,
      "rows": 0,
      "shared_blks_hit": 128,
      "shared_blks_read": 5,
      "shared_blks_dirtied": 2,
      "shared_blks_written": 0,
      "local_blks_hit": 0,
      "local_blks_read": 0,
      "local_blks_dirtied": 0,
      "local_blks_written": 0,
      "temp_blks_read": 0,
      "temp_blks_written": 0,
      "blk_read_time": 0,
      "blk_write_time": 0,
      "queryid": -6699952124008687000,
      "md5": "7166501388435bd7719674b4de4fd9f8"
    },
    "501c8ad1f5ed499a8096f051d185840f": {
      "rownum": 72,
      "query": "create index concurrently i_r_45 on t_45(i)",
      "calls": 1,
      "total_time": 11.321751,
      "rows": 0,
      "shared_blks_hit": 128,
      "shared_blks_read": 5,
      "shared_blks_dirtied": 2,
      "shared_blks_written": 0,
      "local_blks_hit": 0,
      "local_blks_read": 0,
      "local_blks_dirtied": 0,
      "local_blks_written": 0,
      "temp_blks_read": 0,
      "temp_blks_written": 0,
      "blk_read_time": 0,
      "blk_write_time": 0,
      "queryid": 1933432499149815000,
      "md5": "501c8ad1f5ed499a8096f051d185840f"
    },
    "8370278e09e93e9dc3861f745e88480d": {
      "rownum": 73,
      "query": "create index concurrently i_r_90 on t_90(i)",
      "calls": 1,
      "total_time": 11.075476,
      "rows": 0,
      "shared_blks_hit": 128,
      "shared_blks_read": 5,
      "shared_blks_dirtied": 2,
      "shared_blks_written": 0,
      "local_blks_hit": 0,
      "local_blks_read": 0,
      "local_blks_dirtied": 0,
      "local_blks_written": 0,
      "temp_blks_read": 0,
      "temp_blks_written": 0,
      "blk_read_time": 0,
      "blk_write_time": 0,
      "queryid": -1945772972835754500,
      "md5": "8370278e09e93e9dc3861f745e88480d"
    },
    "54d52758a2fe8169e3aab569f07f8ac7": {
      "rownum": 74,
      "query": "create index concurrently i_r_92 on t_92(i)",
      "calls": 1,
      "total_time": 10.48259,
      "rows": 0,
      "shared_blks_hit": 129,
      "shared_blks_read": 6,
      "shared_blks_dirtied": 4,
      "shared_blks_written": 0,
      "local_blks_hit": 0,
      "local_blks_read": 0,
      "local_blks_dirtied": 0,
      "local_blks_written": 0,
      "temp_blks_read": 0,
      "temp_blks_written": 0,
      "blk_read_time": 0,
      "blk_write_time": 0,
      "queryid": -7437082922194741000,
      "md5": "54d52758a2fe8169e3aab569f07f8ac7"
    },
    "b61a1d4249f700bd2ed4712449ba052a": {
      "rownum": 75,
      "query": "create index concurrently i_r_93 on t_93(i)",
      "calls": 1,
      "total_time": 10.043145,
      "rows": 0,
      "shared_blks_hit": 128,
      "shared_blks_read": 5,
      "shared_blks_dirtied": 2,
      "shared_blks_written": 0,
      "local_blks_hit": 0,
      "local_blks_read": 0,
      "local_blks_dirtied": 0,
      "local_blks_written": 0,
      "temp_blks_read": 0,
      "temp_blks_written": 0,
      "blk_read_time": 0,
      "blk_write_time": 0,
      "queryid": -1085300093534512900,
      "md5": "b61a1d4249f700bd2ed4712449ba052a"
    },
    "efb369d7e68290bc9b6c404975148fa8": {
      "rownum": 76,
      "query": "create index concurrently i_u_45 on t_45(i)",
      "calls": 1,
      "total_time": 9.237108,
      "rows": 0,
      "shared_blks_hit": 200,
      "shared_blks_read": 5,
      "shared_blks_dirtied": 2,
      "shared_blks_written": 0,
      "local_blks_hit": 0,
      "local_blks_read": 0,
      "local_blks_dirtied": 0,
      "local_blks_written": 0,
      "temp_blks_read": 0,
      "temp_blks_written": 0,
      "blk_read_time": 0,
      "blk_write_time": 0,
      "queryid": 2993078089717746700,
      "md5": "efb369d7e68290bc9b6c404975148fa8"
    },
    "333347634d76aef134f726073ff02ab7": {
      "rownum": 77,
      "query": "create index concurrently i_r_85 on t_85(i)",
      "calls": 1,
      "total_time": 8.767026,
      "rows": 0,
      "shared_blks_hit": 128,
      "shared_blks_read": 5,
      "shared_blks_dirtied": 2,
      "shared_blks_written": 0,
      "local_blks_hit": 0,
      "local_blks_read": 0,
      "local_blks_dirtied": 0,
      "local_blks_written": 0,
      "temp_blks_read": 0,
      "temp_blks_written": 0,
      "blk_read_time": 0,
      "blk_write_time": 0,
      "queryid": 1003455205449021300,
      "md5": "333347634d76aef134f726073ff02ab7"
    },
    "66d082e57854d2e3cf0f42bdfb7910bd": {
      "rownum": 78,
      "query": "create index concurrently i_u_49 on t_49(i)",
      "calls": 1,
      "total_time": 8.573314,
      "rows": 0,
      "shared_blks_hit": 201,
      "shared_blks_read": 5,
      "shared_blks_dirtied": 2,
      "shared_blks_written": 0,
      "local_blks_hit": 0,
      "local_blks_read": 0,
      "local_blks_dirtied": 0,
      "local_blks_written": 0,
      "temp_blks_read": 0,
      "temp_blks_written": 0,
      "blk_read_time": 0,
      "blk_write_time": 0,
      "queryid": 45512294994752580,
      "md5": "66d082e57854d2e3cf0f42bdfb7910bd"
    },
    "43e9adb569a681a982ad22290f73fcf2": {
      "rownum": 79,
      "query": "select pg_reload_conf()",
      "calls": 1,
      "total_time": 8.497437,
      "rows": 1,
      "shared_blks_hit": 0,
      "shared_blks_read": 0,
      "shared_blks_dirtied": 0,
      "shared_blks_written": 0,
      "local_blks_hit": 0,
      "local_blks_read": 0,
      "local_blks_dirtied": 0,
      "local_blks_written": 0,
      "temp_blks_read": 0,
      "temp_blks_written": 0,
      "blk_read_time": 0,
      "blk_write_time": 0,
      "queryid": -6290564462188021000,
      "md5": "43e9adb569a681a982ad22290f73fcf2"
    },
    "86f2d2662d0f02178c4d27178b84e28a": {
      "rownum": 80,
      "query": "create index concurrently i_u_46 on t_46(i)",
      "calls": 1,
      "total_time": 8.36972,
      "rows": 0,
      "shared_blks_hit": 201,
      "shared_blks_read": 7,
      "shared_blks_dirtied": 5,
      "shared_blks_written": 0,
      "local_blks_hit": 0,
      "local_blks_read": 0,
      "local_blks_dirtied": 0,
      "local_blks_written": 0,
      "temp_blks_read": 0,
      "temp_blks_written": 0,
      "blk_read_time": 0,
      "blk_write_time": 0,
      "queryid": 5347103578192611000,
      "md5": "86f2d2662d0f02178c4d27178b84e28a"
    },
    "3f5256d47a92ecf68cb1198fd3bbf1c0": {
      "rownum": 81,
      "query": "create index concurrently i_r_52 on t_52(i)",
      "calls": 1,
      "total_time": 7.493728,
      "rows": 0,
      "shared_blks_hit": 128,
      "shared_blks_read": 5,
      "shared_blks_dirtied": 2,
      "shared_blks_written": 0,
      "local_blks_hit": 0,
      "local_blks_read": 0,
      "local_blks_dirtied": 0,
      "local_blks_written": 0,
      "temp_blks_read": 0,
      "temp_blks_written": 0,
      "blk_read_time": 0,
      "blk_write_time": 0,
      "queryid": 4228969900036353000,
      "md5": "3f5256d47a92ecf68cb1198fd3bbf1c0"
    },
    "28dc3c924e72370594c0ba4c1b259642": {
      "rownum": 82,
      "query": "create index concurrently i_u_50 on t_50(i)",
      "calls": 1,
      "total_time": 7.425592,
      "rows": 0,
      "shared_blks_hit": 200,
      "shared_blks_read": 5,
      "shared_blks_dirtied": 2,
      "shared_blks_written": 0,
      "local_blks_hit": 0,
      "local_blks_read": 0,
      "local_blks_dirtied": 0,
      "local_blks_written": 0,
      "temp_blks_read": 0,
      "temp_blks_written": 0,
      "blk_read_time": 0,
      "blk_write_time": 0,
      "queryid": 7953863237307717000,
      "md5": "28dc3c924e72370594c0ba4c1b259642"
    },
    "661e02ee3ad50cb6c6a884d896504a06": {
      "rownum": 83,
      "query": "create index concurrently i_u_98 on t_98(i)",
      "calls": 1,
      "total_time": 7.330338,
      "rows": 0,
      "shared_blks_hit": 200,
      "shared_blks_read": 5,
      "shared_blks_dirtied": 2,
      "shared_blks_written": 0,
      "local_blks_hit": 0,
      "local_blks_read": 0,
      "local_blks_dirtied": 0,
      "local_blks_written": 0,
      "temp_blks_read": 0,
      "temp_blks_written": 0,
      "blk_read_time": 0,
      "blk_write_time": 0,
      "queryid": 3457780516455988700,
      "md5": "661e02ee3ad50cb6c6a884d896504a06"
    },
    "f03b8cda75e4d8a70069e3c3dfd0990d": {
      "rownum": 84,
      "query": "create index concurrently i_r_40 on t_40(i)",
      "calls": 1,
      "total_time": 7.180002,
      "rows": 0,
      "shared_blks_hit": 128,
      "shared_blks_read": 5,
      "shared_blks_dirtied": 2,
      "shared_blks_written": 0,
      "local_blks_hit": 0,
      "local_blks_read": 0,
      "local_blks_dirtied": 0,
      "local_blks_written": 0,
      "temp_blks_read": 0,
      "temp_blks_written": 0,
      "blk_read_time": 0,
      "blk_write_time": 0,
      "queryid": -345104657200452600,
      "md5": "f03b8cda75e4d8a70069e3c3dfd0990d"
    },
    "734762bee8278fb48b3f3983a5eae884": {
      "rownum": 85,
      "query": "create extension if not exists pg_stat_kcache",
      "calls": 1,
      "total_time": 7.084799,
      "rows": 0,
      "shared_blks_hit": 1413,
      "shared_blks_read": 67,
      "shared_blks_dirtied": 21,
      "shared_blks_written": 0,
      "local_blks_hit": 0,
      "local_blks_read": 0,
      "local_blks_dirtied": 0,
      "local_blks_written": 0,
      "temp_blks_read": 0,
      "temp_blks_written": 0,
      "blk_read_time": 0,
      "blk_write_time": 0,
      "queryid": 2571546517107304400,
      "md5": "734762bee8278fb48b3f3983a5eae884"
    },
    "eb2b07eab8864a07c73b40e09963abb0": {
      "rownum": 86,
      "query": "create index concurrently i_r_29 on t_29(i)",
      "calls": 1,
      "total_time": 6.900332,
      "rows": 0,
      "shared_blks_hit": 128,
      "shared_blks_read": 5,
      "shared_blks_dirtied": 2,
      "shared_blks_written": 0,
      "local_blks_hit": 0,
      "local_blks_read": 0,
      "local_blks_dirtied": 0,
      "local_blks_written": 0,
      "temp_blks_read": 0,
      "temp_blks_written": 0,
      "blk_read_time": 0,
      "blk_write_time": 0,
      "queryid": 3107774250204707000,
      "md5": "eb2b07eab8864a07c73b40e09963abb0"
    },
    "db2c7d19cef3a8a9b788e5f16a6ecf13": {
      "rownum": 87,
      "query": "create index concurrently i_r_42 on t_42(i)",
      "calls": 1,
      "total_time": 6.832252,
      "rows": 0,
      "shared_blks_hit": 128,
      "shared_blks_read": 5,
      "shared_blks_dirtied": 2,
      "shared_blks_written": 0,
      "local_blks_hit": 0,
      "local_blks_read": 0,
      "local_blks_dirtied": 0,
      "local_blks_written": 0,
      "temp_blks_read": 0,
      "temp_blks_written": 0,
      "blk_read_time": 0,
      "blk_write_time": 0,
      "queryid": -4880803480357036000,
      "md5": "db2c7d19cef3a8a9b788e5f16a6ecf13"
    },
    "42e39dfb2220c056b9c0e1f5010549ba": {
      "rownum": 88,
      "query": "create index concurrently i_u_47 on t_47(i)",
      "calls": 1,
      "total_time": 6.773702,
      "rows": 0,
      "shared_blks_hit": 201,
      "shared_blks_read": 5,
      "shared_blks_dirtied": 2,
      "shared_blks_written": 0,
      "local_blks_hit": 0,
      "local_blks_read": 0,
      "local_blks_dirtied": 0,
      "local_blks_written": 0,
      "temp_blks_read": 0,
      "temp_blks_written": 0,
      "blk_read_time": 0,
      "blk_write_time": 0,
      "queryid": 1135009546166922100,
      "md5": "42e39dfb2220c056b9c0e1f5010549ba"
    },
    "bc436b1b13a59d4fc2024d190b9c7c10": {
      "rownum": 89,
      "query": "create index concurrently i_r_47 on t_47(i)",
      "calls": 1,
      "total_time": 6.495094,
      "rows": 0,
      "shared_blks_hit": 128,
      "shared_blks_read": 5,
      "shared_blks_dirtied": 2,
      "shared_blks_written": 0,
      "local_blks_hit": 0,
      "local_blks_read": 0,
      "local_blks_dirtied": 0,
      "local_blks_written": 0,
      "temp_blks_read": 0,
      "temp_blks_written": 0,
      "blk_read_time": 0,
      "blk_write_time": 0,
      "queryid": -574046320413349100,
      "md5": "bc436b1b13a59d4fc2024d190b9c7c10"
    },
    "7efe85498cb778ab5f172e11c6813b23": {
      "rownum": 90,
      "query": "create index concurrently i_u_40 on t_40(i)",
      "calls": 1,
      "total_time": 6.410135,
      "rows": 0,
      "shared_blks_hit": 200,
      "shared_blks_read": 5,
      "shared_blks_dirtied": 2,
      "shared_blks_written": 0,
      "local_blks_hit": 0,
      "local_blks_read": 0,
      "local_blks_dirtied": 0,
      "local_blks_written": 0,
      "temp_blks_read": 0,
      "temp_blks_written": 0,
      "blk_read_time": 0,
      "blk_write_time": 0,
      "queryid": 3875616994366767600,
      "md5": "7efe85498cb778ab5f172e11c6813b23"
    },
    "818252bc4de136a03e0f3c8d641e8cda": {
      "rownum": 91,
      "query": "create index concurrently i_u_1 on t_1(i)",
      "calls": 1,
      "total_time": 6.368721,
      "rows": 0,
      "shared_blks_hit": 198,
      "shared_blks_read": 9,
      "shared_blks_dirtied": 2,
      "shared_blks_written": 0,
      "local_blks_hit": 0,
      "local_blks_read": 0,
      "local_blks_dirtied": 0,
      "local_blks_written": 0,
      "temp_blks_read": 0,
      "temp_blks_written": 0,
      "blk_read_time": 0,
      "blk_write_time": 0,
      "queryid": 8045454930243187000,
      "md5": "818252bc4de136a03e0f3c8d641e8cda"
    },
    "c498528e5eec9bedd4d9f96905e98457": {
      "rownum": 92,
      "query": "create index concurrently i_u_93 on t_93(i)",
      "calls": 1,
      "total_time": 6.357299,
      "rows": 0,
      "shared_blks_hit": 200,
      "shared_blks_read": 5,
      "shared_blks_dirtied": 2,
      "shared_blks_written": 0,
      "local_blks_hit": 0,
      "local_blks_read": 0,
      "local_blks_dirtied": 0,
      "local_blks_written": 0,
      "temp_blks_read": 0,
      "temp_blks_written": 0,
      "blk_read_time": 0,
      "blk_write_time": 0,
      "queryid": 1134231873159412500,
      "md5": "c498528e5eec9bedd4d9f96905e98457"
    },
    "0caf1b5bb4332f7bac11b0bebdda642d": {
      "rownum": 93,
      "query": "create index concurrently i_r_44 on t_44(i)",
      "calls": 1,
      "total_time": 6.330886,
      "rows": 0,
      "shared_blks_hit": 128,
      "shared_blks_read": 5,
      "shared_blks_dirtied": 2,
      "shared_blks_written": 0,
      "local_blks_hit": 0,
      "local_blks_read": 0,
      "local_blks_dirtied": 0,
      "local_blks_written": 0,
      "temp_blks_read": 0,
      "temp_blks_written": 0,
      "blk_read_time": 0,
      "blk_write_time": 0,
      "queryid": 366084289547209800,
      "md5": "0caf1b5bb4332f7bac11b0bebdda642d"
    },
    "1bb72296d32b0705644fc00154cb9bfc": {
      "rownum": 94,
      "query": "create index concurrently i_u_97 on t_97(i)",
      "calls": 1,
      "total_time": 6.229025,
      "rows": 0,
      "shared_blks_hit": 200,
      "shared_blks_read": 5,
      "shared_blks_dirtied": 2,
      "shared_blks_written": 0,
      "local_blks_hit": 0,
      "local_blks_read": 0,
      "local_blks_dirtied": 0,
      "local_blks_written": 0,
      "temp_blks_read": 0,
      "temp_blks_written": 0,
      "blk_read_time": 0,
      "blk_write_time": 0,
      "queryid": -1547472426000537000,
      "md5": "1bb72296d32b0705644fc00154cb9bfc"
    },
    "eaa202496fbbe510012c2230129cbb45": {
      "rownum": 95,
      "query": "create index concurrently i_u_48 on t_48(i)",
      "calls": 1,
      "total_time": 6.226109,
      "rows": 0,
      "shared_blks_hit": 201,
      "shared_blks_read": 5,
      "shared_blks_dirtied": 2,
      "shared_blks_written": 0,
      "local_blks_hit": 0,
      "local_blks_read": 0,
      "local_blks_dirtied": 0,
      "local_blks_written": 0,
      "temp_blks_read": 0,
      "temp_blks_written": 0,
      "blk_read_time": 0,
      "blk_write_time": 0,
      "queryid": -5371677106063814000,
      "md5": "eaa202496fbbe510012c2230129cbb45"
    },
    "ff68c2d52ff52cf5a1df23f0176ea83d": {
      "rownum": 96,
      "query": "create index concurrently i_u_70 on t_70(i)",
      "calls": 1,
      "total_time": 6.160768,
      "rows": 0,
      "shared_blks_hit": 200,
      "shared_blks_read": 5,
      "shared_blks_dirtied": 2,
      "shared_blks_written": 0,
      "local_blks_hit": 0,
      "local_blks_read": 0,
      "local_blks_dirtied": 0,
      "local_blks_written": 0,
      "temp_blks_read": 0,
      "temp_blks_written": 0,
      "blk_read_time": 0,
      "blk_write_time": 0,
      "queryid": 3694177823672669000,
      "md5": "ff68c2d52ff52cf5a1df23f0176ea83d"
    },
    "495e0810a63f32bd94cccdbd7e263bac": {
      "rownum": 97,
      "query": "create index concurrently i_r_39 on t_39(i)",
      "calls": 1,
      "total_time": 6.077179,
      "rows": 0,
      "shared_blks_hit": 128,
      "shared_blks_read": 5,
      "shared_blks_dirtied": 2,
      "shared_blks_written": 0,
      "local_blks_hit": 0,
      "local_blks_read": 0,
      "local_blks_dirtied": 0,
      "local_blks_written": 0,
      "temp_blks_read": 0,
      "temp_blks_written": 0,
      "blk_read_time": 0,
      "blk_write_time": 0,
      "queryid": 356722072638649660,
      "md5": "495e0810a63f32bd94cccdbd7e263bac"
    },
    "8dea1d6a28f753879c4a544e1cb99d3d": {
      "rownum": 98,
      "query": "create index concurrently i_r_94 on t_94(i)",
      "calls": 1,
      "total_time": 6.041507,
      "rows": 0,
      "shared_blks_hit": 128,
      "shared_blks_read": 5,
      "shared_blks_dirtied": 2,
      "shared_blks_written": 0,
      "local_blks_hit": 0,
      "local_blks_read": 0,
      "local_blks_dirtied": 0,
      "local_blks_written": 0,
      "temp_blks_read": 0,
      "temp_blks_written": 0,
      "blk_read_time": 0,
      "blk_write_time": 0,
      "queryid": -3961781611296621600,
      "md5": "8dea1d6a28f753879c4a544e1cb99d3d"
    },
    "3e48ba03a449895afd732ed65af2a6ff": {
      "rownum": 99,
      "query": "create index concurrently i_r_28 on t_28(i)",
      "calls": 1,
      "total_time": 5.950259,
      "rows": 0,
      "shared_blks_hit": 128,
      "shared_blks_read": 5,
      "shared_blks_dirtied": 2,
      "shared_blks_written": 0,
      "local_blks_hit": 0,
      "local_blks_read": 0,
      "local_blks_dirtied": 0,
      "local_blks_written": 0,
      "temp_blks_read": 0,
      "temp_blks_written": 0,
      "blk_read_time": 0,
      "blk_write_time": 0,
      "queryid": 4145640601518494700,
      "md5": "3e48ba03a449895afd732ed65af2a6ff"
    },
    "9e4c8c80279f69de75aae81b53e0e10d": {
      "rownum": 100,
      "query": "create index concurrently i_r_48 on t_48(i)",
      "calls": 1,
      "total_time": 5.809748,
      "rows": 0,
      "shared_blks_hit": 128,
      "shared_blks_read": 5,
      "shared_blks_dirtied": 2,
      "shared_blks_written": 0,
      "local_blks_hit": 0,
      "local_blks_read": 0,
      "local_blks_dirtied": 0,
      "local_blks_written": 0,
      "temp_blks_read": 0,
      "temp_blks_written": 0,
      "blk_read_time": 0,
      "blk_write_time": 0,
      "queryid": 8487355650255158000,
      "md5": "9e4c8c80279f69de75aae81b53e0e10d"
    }
  }
}
